Workbook
Name contract_no: view__cover!$R$1
Name contract_nos: _xlfn.DROP(log_contracts!$B:$B,1)
Name ipc_date_end: view__cover!$L$5
Name ipc_date_start: view__cover!$L$4
Name ipc_no: view__cover!$R$2

Sheet view__cover
A1: #VALUE! | C1: Kolin Construction, Tourism, Industry and Trading Co. Inc. Kolin İnşaat, Turizm, Sənaye və Ticarət Co. Inc. | J1: Contract No | K1: ="KLN-SPP2-"&_xlfn.XLOOKUP(R1,log_contracts!B:B,log_contracts!C:C)&"-"&TEXT(R1,"000") -> KLN-SPP2-AA-031 | N1: Contract no: | O1: 31 | R1: =IF(O1="",_xlfn.XLOOKUP(P2,log_ipcs!A:A,log_ipcs!C:C,,0),O1) -> 31 | U1: ATTENTION!!!➡️➡️ | V1: =HYPERLINK("\\DATA\DataServer\Teknik Ofis\00_SPP2 Taseron Sozlesmeleri\000_FOLLOW-UP\S2 Subcon IPC Log.xlsx","Open IPC Log to Fix #REF error") -> Open IPC Log to Fix #REF error
J2: IPC No | K2: =R2 -> 14 | N2: IPC no | O2: =IF(Q2="",MAX(_xlfn.ANCHORARRAY(S2)),Q2) -> 14 | P2: 129 | R2: =IF(O2="",_xlfn.XLOOKUP(P2,log_ipcs!A:A,log_ipcs!D:D,,0),O2) -> 14 | S2: {=_xlfn._xlws.FILTER(log_ipcs!D:D,log_ipcs!C:C=contract_no)} -> 1 | U2: 1 | V2: =HYPERLINK("\\DATA\DataServer\Teknik Ofis\00_SPP2 Taseron Sozlesmeleri\"&_xlfn.XLOOKUP(O1,log_contracts!B:B,log_contracts!I:I,,0)&"\ipcs\"&IF(U2="",O2,U2)&"\"&O1&"-"&IF(U2="",O2,U2)&".pdf","Open"&" "&O1&"-"&IF(U2="",O2,U2)&" PDF") -> Open 31-1 PDF
A3: Interim Payment Certificate (IPC) Müvəqqəti Ödəniş Şəhadətnaməsi | S3: 2 | U3: =_xlfn.MAXIFS(INDIRECT("'[S2 Subcon IPC Log.xlsx]Subcon IPC Log'!"&"D:D"),INDIRECT("'[S2 Subcon IPC Log.xlsx]Subcon IPC Log'!"&"C:C"),K1)=MAX(_xlfn.ANCHORARRAY(S2)) -> #REF!
A4: Project : Layihə: | C4: Construction of the facilities and buildings, storages, and other structures, including roads and all industrial utilities for establishment of “Sitalchay 2” Production Plant | J4: Invoice Period (Start): Faktura müddəti (başlanğıc): | L4: =VLOOKUP(TEXT(O1,"000")&"-"&TEXT(O2,"000"),log_ipcs!B:F,4,0) -> 46082 | N4: =IF(L6>L4,"ERROR","") | S4: 3
J5: Invoice Period (Finish): Faktura müddəti (Son): | L5: {=EOMONTH(MAX(_xlfn.LET(_xlpm.ym,_xlfn._xlws.FILTER(quantities!B:C,(quantities!D:D=contract_no)*(quantities!E:E=ipc_no)),DATE(INDEX(_xlpm.ym,,1),INDEX(_xlpm.ym,,2),1))),0)} -> 46112 | S5: 4
A6: Subcontractor: Subpodratçı: | C6: =_xlfn.XLOOKUP(R1,log_contracts!B:B,log_contracts!E:E,,0) -> NAR TRANSPORT SERVICES MMC | J6: Commencement Date: Başlanğıc tarixi: | L6: {=_xlfn.XLOOKUP(R1,_xlfn._TRO_TRAILING(log_contracts!B:B),_xlfn._TRO_TRAILING(log_contracts!H:H),,0)} -> 45693 | S6: 5
J7: Completion Date: Bitmə tarixi: | S7: 6
A8: Scope of Work: İşin həcmi: | C8: =_xlfn.XLOOKUP(R1,log_contracts!B:B,log_contracts!F:F,,0) -> Rental Vehicle Kiralıq Vasitə | J8: Contract Type (Subc.): Müqavilənin növü (Subp.): | L8: Unit Price Vahidin qiyməti | S8: 7
J9: Contract Value: Müqavilənin dəyəri: | S9: 8
A10: Payment Table Ödəniş cədvəli | S10: 9
S11: 10
A12: A | B12: ="Cumulative Value Of The Works Executed as of " & TEXT(L5," DD/MMM/YYYY") &CHAR(10)&TEXT(L5,"DD/MMM/YYYY") & "cu il tarixindən etibarən görülmüş işlərin ümumi dəyəri:" -> Cumulative Value Of The Works Executed as of 31/Mar/2026 31/Mar/2026cu il tarixindən etibarən görülmüş işlərin ümumi dəyəri: | J12: =view_calc!I165 -> 734672 | M12: =SUMIFS( INDIRECT("'[S2 Subcon IPC Log.xlsx]Subcon IPC Log'!"&"$O:$O"), INDIRECT("'[S2 Subcon IPC Log.xlsx]Subcon IPC Log'!"&"$C:$C"), K1, INDIRECT("'[S2 Subcon IPC Log.xlsx]Subcon IPC Log'!"&"$D:$D"), "<="&K2) -> #REF! | N12: =ROUND(M12,1)=ROUND(J12,1) -> #REF! | O12: =J12-M12 -> #REF! | S12: 11
A13: B | B13: Cumulative Value of The Previous Payment : Öncəki ödənişlərin ümumi dəyəri: | J13: {=SUM(_xlfn.ANCHORARRAY(view_calc!D6)*_xlfn.ANCHORARRAY(view_calc!G6),IFERROR(_xlfn.ANCHORARRAY(view_calc!D62)*_xlfn.ANCHORARRAY(view_calc!G62),0),IFERROR(_xlfn.ANCHORARRAY(view_calc!D118)*_xlfn.ANCHORARRAY(view_calc!G118),0))} -> 729770.22 | S13: 12
A14: C | B14: Value of The Works Executed Within Current Period [A B] : Cari müddət [A B] ərzində görülmüş işlərin dəyəri: | J14: =J12-J13 -> 4901.7857 | M14: =SUMIFS( INDIRECT("'[S2 Subcon IPC Log.xlsx]Subcon IPC Log'!"&"$O:$O"), INDIRECT("'[S2 Subcon IPC Log.xlsx]Subcon IPC Log'!"&"$C:$C"), K1, INDIRECT("'[S2 Subcon IPC Log.xlsx]Subcon IPC Log'!"&"$D:$D"), K2) -> #REF! | N14: =IF(J14="","",ROUND(M14,1)=ROUND(J14,1)) -> #REF! | O14: =J14-M14 -> #REF! | S14: 13
A15: D | B15: Deductions Çıxılmalar | C15: Advance Payment: Avans ödənişi: | J15: =F22 -> 0 | S15: 14
C16: On Site Deductions (Lunch,fuel,etc): Sahə üzrə çıxılmalar (Yemək, yanacaq və s.)
C17: Delay Penalties: Yubanmaya görə cərimələr:
C18: Retention: Saxlanılma:
C19: Others: Digərləri:
C22: Total Amount (Deductions): Cəmi (Çıxılmalar): | F22: =SUM(F15:I21) -> 0
A23: E | B23: Net Payment: [ C D ] Xalis ödəniş: [ C D ] | J23: =J14-J15 -> 4901.7857
A24: Subcontractor Subpodratçı | D24: Technical Office Manager Texniki Şöbə Rəhbəri | G24: Site Manager Sahə Rəhbəri | J24: Approved by: Project Manager Təsdiqləyən şəxs: Layihə Rəhbəri
A25: …... / …... / 202….. | D25: …... / …... / 202….. | G25: …... / …... / 202….. | J25: …... / …... / 202…..
A29: =+C6 -> NAR TRANSPORT SERVICES MMC | D29: ERDİNÇ DELİBAŞI | G29: TURGAY BAL | J29: TEOMAN ULUDAĞ

Sheet view_calc
C1: Kolin Construction, Tourism, Industry and Trading Co. Inc. Kolin İnşaat, Turizm, Sənaye və Ticarət Co. Inc. | H1: Contract No | I1: =view__cover!K1 -> KLN-SPP2-AA-031 | N1: {=_xlfn._xlws.SORT(_xlfn.UNIQUE(_xlfn._xlws.FILTER(quantities!J:J,(quantities!D:D=contract_no)*(quantities!E:E<=ipc_no))))} -> 1 | Q1: =ROWS(_xlfn.ANCHORARRAY(N1)) -> 143
H2: IPC No | I2: =view__cover!$K$2 -> 14 | N2: 2
A3: Interim Payment Certificate Müvəqqəti Ödəniş Şəhadətnaməsi | J3: =view__cover!$N$1 -> Contract no: | K3: =contract_no -> 31 | N3: 3
A4: No | B4: Description of the Work İşin təsviri | C4: Unit Vahid | D4: Previous Quantity Önceki Kəmiyyət | E4: Current Quantity Hazirki Kəmiyyət | F4: Total Quantity Ümumi Kəmiyyət | G4: Unit Price Vahidin dəyəri | H4: Current Amount Hazırki Məbləğ | I4: Amount Məbləğ | J4: =view__cover!$N$2 -> IPC no | K4: =ipc_no -> 14 | N4: 4
D5: A | E5: B = C A | F5: C | G5: D | H5: F = B x D | I5: E = C x D | N5: 5
A6: {=_xlfn.TAKE(_xlfn.ANCHORARRAY(N1),50)} -> 1 | B6: {=_xlfn.XLOOKUP(contract_no&"-"&_xlfn.ANCHORARRAY(A6),log_prices!B:B,log_prices!F:F,,0)} -> SERVICE - 99LT168 - Baku-single | C6: {=_xlfn.XLOOKUP(contract_no&"-"&_xlfn.ANCHORARRAY(A6),log_prices!B:B,log_prices!G:G,,0)} -> single | D6: {=SUMIFS(quantities!G:G,quantities!D:D,contract_no,quantities!E:E,"<"&ipc_no,quantities!J:J,_xlfn.ANCHORARRAY(A6))} -> 57 | E6: {=_xlfn.ANCHORARRAY(F6)-_xlfn.ANCHORARRAY(D6)} -> 0 | F6: {=SUMIFS(quantities!G:G,quantities!D:D,contract_no,quantities!E:E,"<="&ipc_no,quantities!J:J,_xlfn.ANCHORARRAY(A6))} -> 57 | G6: {=_xlfn.XLOOKUP(contract_no&"-"&_xlfn.ANCHORARRAY(A6),log_prices!B:B,log_prices!I:I,,0)} -> 73.33 | H6: {=_xlfn.ANCHORARRAY(E6)*_xlfn.ANCHORARRAY(G6)} -> 0 | I6: {=_xlfn.ANCHORARRAY(F6)*_xlfn.ANCHORARRAY(G6)} -> 4179.81 | N6: 6
A7: 2 | B7: SERVICE - 99LT168 - Baku-hour | C7: hour | D7: 2 | E7: 0 | F7: 2 | G7: 7.333 | H7: 0 | I7: 14.666 | N7: 7
A8: 3 | B8: SERVICE - 99HZ395 - Sumqayıt-single | C8: single | D8: 384 | E8: 0 | F8: 384 | G8: 65 | H8: 0 | I8: 24960 | N8: 9
A9: 4 | B9: SERVICE - 99HZ395 - Sumqayıt-hour | C9: hour | D9: 369 | E9: 0 | F9: 369 | G9: 6.5 | H9: 0 | I9: 2398.5 | N9: 11
A10: 5 | B10: SERVICE - 90OV187 - Baku-single | C10: single | D10: 47 | E10: 0 | F10: 47 | G10: 73.33 | H10: 0 | I10: 3446.51 | N10: 12
A11: 6 | B11: SERVICE - 90OV187 - Baku-hour | C11: hour | D11: 49 | E11: 0 | F11: 49 | G11: 7.333 | H11: 0 | I11: 359.317 | N11: 13
A12: 7 | B12: SERVICE - 77UG347 - Sumqayıt-single | C12: single | D12: 6 | E12: 0 | F12: 6 | G12: 65 | H12: 0 | I12: 390 | N12: 15
A13: 9 | B13: SERVICE - 99FB123 - Baku-single | C13: single | D13: 6 | E13: 0 | F13: 6 | G13: 73.33 | H13: 0 | I13: 439.98 | N13: 16
A14: 11 | B14: SERVICE - 90ZP408 - Site-single | C14: single | D14: 97 | E14: 0 | F14: 97 | G14: 55.36 | H14: 0 | I14: 5369.92 | N14: 17
A15: 12 | B15: SERVICE - 90ZP408 - Site-hour | C15: hour | D15: 32.3 | E15: 0 | F15: 32.3 | G15: 5.536 | H15: 0 | I15: 178.8128 | N15: 19
A16: 13 | B16: SERVICE - 77AT386 - Procurement-single | C16: single | D16: 371 | E16: 0 | F16: 371 | G16: 46.67 | H16: 0 | I16: 17314.57 | N16: 20
A17: 15 | B17: SERVICE - 66CC029 - Site-single | C17: single | D17: 105 | E17: 0 | F17: 105 | G17: 55.36 | H17: 0 | I17: 5812.8 | N17: 21
A18: 16 | B18: SERVICE - 66CC029 - Site-hour | C18: hour | D18: 212 | E18: 0 | F18: 212 | G18: 5.536 | H18: 0 | I18: 1173.632 | N18: 22
... A55: 54 | B55: SERVICE - 53BD338 - Site-hour | C55: hour | D55: 70 | E55: 0 | F55: 70 | G55: 5.536 | H55: 0 | I55: 387.52 | N55: 60
N56: 61
A57: ="PAGE TOTAL (AZN)"&CHAR(10)&"SƏHİFƏNİN CƏMİ (AZN)" -> PAGE TOTAL (AZN) SƏHİFƏNİN CƏMİ (AZN) | H57: {=SUM(IFERROR(_xlfn._xlws.FILTER(H6:H56,H6:H56>0),0))} -> 0 | I57: {=SUM(_xlfn._xlws.FILTER(I6:I56,I6:I56>0))} -> 247385.95 | N57: 62
N58: 63
A59: =view__cover!A29 -> NAR TRANSPORT SERVICES MMC | C59: =_xlfn.LET(_xlpm.r,_xlfn.XLOOKUP(contract_no,log_contracts!B:B,log_contracts!G:G),IF(_xlpm.r=0,"",_xlpm.r)) -> İbrahim Kemik | E59: MEHMET TEVFİK ÇELİKKOL | H59: Mehmet Özgün DEDEKARGINOĞLU | N59: 65
A60: Subcontractor Subpodratçı | C60: Department Chief Bölmə Şefi | E60: Contract and Progress Payment Chief Ödəniş Sertifikatı Üzrə Məsul şəxs | H60: Technical Office Cheif Texniki Şöbə Şefi | N60: 67
A61: =IF(A62="","","PREVIOUS PAGE TOTAL (AZN)"&CHAR(10)&"ƏVVƏLKİ SƏHİFƏNİN CƏMİ (AZN)") -> PREVIOUS PAGE TOTAL (AZN) ƏVVƏLKİ SƏHİFƏNİN CƏMİ (AZN) | H61: =H57 -> 0 | I61: =I57 -> 247385.95 | N61: 68
A62: {=IFERROR(_xlfn.TAKE(_xlfn.DROP(_xlfn.ANCHORARRAY(N1),50),50),"")} -> 55 | B62: {=IFERROR(_xlfn.XLOOKUP(contract_no&"-"&_xlfn.ANCHORARRAY(A62),log_prices!B:B,log_prices!F:F,,0),"")} -> SERVICE - 53BD338 - Site-single | C62: {=IFERROR(_xlfn.XLOOKUP(contract_no&"-"&_xlfn.ANCHORARRAY(A62),log_prices!B:B,log_prices!G:G,,0),"")} -> single | D62: {=IFERROR(SUMIFS(quantities!G:G,quantities!D:D,contract_no,quantities!E:E,"<"&ipc_no,quantities!J:J,_xlfn.ANCHORARRAY(A62)),"")} -> 60 | E62: {=_xlfn.ANCHORARRAY(F62)-_xlfn.ANCHORARRAY(D62)} -> 0 | F62: {=IFERROR(SUMIFS(quantities!G:G,quantities!D:D,contract_no,quantities!E:E,"<="&ipc_no,quantities!J:J,_xlfn.ANCHORARRAY(A62)),"")} -> 60 | G62: {=IFERROR(_xlfn.XLOOKUP(contract_no&"-"&_xlfn.ANCHORARRAY(A62),log_prices!B:B,log_prices!I:I,,0),"")} -> 55.36 | H62: {=IFERROR(_xlfn.ANCHORARRAY(E62)*_xlfn.ANCHORARRAY(G62),"")} -> 0 | I62: {=IFERROR(_xlfn.ANCHORARRAY(F62)*_xlfn.ANCHORARRAY(G62),"")} -> 3321.6 | N62: 69
A63: 56 | B63: SERVICE - 55CB633 - Site-hour | C63: hour | D63: 797 | E63: 0 | F63: 797 | G63: 5.536 | H63: 0 | I63: 4412.192 | N63: 71
A64: 57 | B64: SERVICE - 55CB633 - Site-single | C64: single | D64: 345 | E64: 0 | F64: 345 | G64: 55.36 | H64: 0 | I64: 19099.2 | N64: 72
A65: 59 | B65: SERVICE - 77ET143 - Site-single | C65: single | D65: 85 | E65: 0 | F65: 85 | G65: 55.36 | H65: 0 | I65: 4705.6 | N65: 73
A66: 60 | B66: SERVICE - 77GM723 - Site-hour | C66: hour | D66: 81 | E66: 0 | F66: 81 | G66: 5.536 | H66: 0 | I66: 448.416 | N66: 74
A67: 61 | B67: SERVICE - 77GM723 - Site-single | C67: single | D67: 28 | E67: 0 | F67: 28 | G67: 55.36 | H67: 0 | I67: 1550.08 | N67: 75
A68: 62 | B68: SERVICE - 77GR998 - Site-double | C68: double | D68: 17 | E68: 0 | F68: 17 | G68: 91.339286 | H68: 0 | I68: 1552.7679 | N68: 76
A69: 63 | B69: SERVICE - 77GR998 - Site_v1-double | C69: double | D69: 243 | E69: 0 | F69: 243 | G69: 99.642857 | H69: 0 | I69: 24213.214 | N69: 77
A70: 65 | B70: SERVICE - 77GR998 - Site-single | C70: single | D70: 3 | E70: 0 | F70: 3 | G70: 55.357143 | H70: 0 | I70: 166.07143 | N70: 78
A71: 67 | B71: SERVICE - 77PV619 - Procurement-single | C71: single | D71: 120 | E71: 0 | F71: 120 | G71: 40 | H71: 0 | I71: 4800 | N71: 79
A72: 68 | B72: SERVICE - 77QE133 - Baku-hour | C72: hour | D72: 40 | E72: 0 | F72: 40 | G72: 7.333 | H72: 0 | I72: 293.32 | N72: 80
A73: 69 | B73: SERVICE - 77QE133 - Baku-single | C73: single | D73: 135 | E73: 0 | F73: 135 | G73: 73.33 | H73: 0 | I73: 9899.55 | N73: 81
A74: 71 | B74: SERVICE - 77RN868 - Baku-single | C74: single | D74: 41 | E74: 0 | F74: 41 | G74: 73.33 | H74: 0 | I74: 3006.53 | N74: 82
... A111: 110 | B111: SERVICE - 99OR961 - Site-hour | C111: hour | D111: 295 | E111: 0 | F111: 295 | G111: 5.536 | H111: 0 | I111: 1633.12 | N111: 122
N112: 123
A113: ="PAGE TOTAL (AZN)"&CHAR(10)&"SƏHİFƏNİN CƏMİ (AZN)" -> PAGE TOTAL (AZN) SƏHİFƏNİN CƏMİ (AZN) | H113: {=SUM(_xlfn._xlws.FILTER(H61:H112,H61:H112>0))} -> #VALUE! | I113: {=SUM(_xlfn._xlws.FILTER(I61:I112,I61:I112>0))} -> 559194.79 | N113: 124
N114: 125
A115: =A59 -> NAR TRANSPORT SERVICES MMC | C115: =_xlfn.LET(_xlpm.r,_xlfn.XLOOKUP(contract_no,log_contracts!B:B,log_contracts!G:G),IF(_xlpm.r=0,"",_xlpm.r)) -> İbrahim Kemik | E115: MEHMET TEVFİK ÇELİKKOL | H115: =H59 -> Mehmet Özgün DEDEKARGINOĞLU | N115: 180
A116: Subcontractor Subpodratçı | C116: Department Chief Bölmə Şefi | E116: Contract and Progress Payment Chief Ödəniş Sertifikatı Üzrə Məsul şəxs | H116: =H60 -> Technical Office Cheif Texniki Şöbə Şefi | N116: 181
A117: =IF(A118="","","PREVIOUS PAGE TOTAL (AZN)"&CHAR(10)&"ƏVVƏLKİ SƏHİFƏNİN CƏMİ (AZN)") -> PREVIOUS PAGE TOTAL (AZN) ƏVVƏLKİ SƏHİFƏNİN CƏMİ (AZN) | H117: =H113 -> #VALUE! | I117: =I113 -> 559194.79 | N117: 182
A118: {=IFERROR(_xlfn.DROP(_xlfn.ANCHORARRAY(N1),100),"")} -> 111 | B118: {=IFERROR(_xlfn.XLOOKUP(contract_no&"-"&_xlfn.ANCHORARRAY(A118),log_prices!B:B,log_prices!F:F,,0),"")} -> SERVICE - 99TV366 - Site-hour | C118: {=IFERROR(_xlfn.XLOOKUP(contract_no&"-"&_xlfn.ANCHORARRAY(A118),log_prices!B:B,log_prices!G:G,,0),"")} -> hour | D118: {=IFERROR(SUMIFS(quantities!G:G,quantities!D:D,contract_no,quantities!E:E,"<"&ipc_no,quantities!J:J,_xlfn.ANCHORARRAY(A118)),"")} -> 21 | E118: {=_xlfn.ANCHORARRAY(F118)-_xlfn.ANCHORARRAY(D118)} -> 0 | F118: {=IFERROR(SUMIFS(quantities!G:G,quantities!D:D,contract_no,quantities!E:E,"<="&ipc_no,quantities!J:J,_xlfn.ANCHORARRAY(A118)),"")} -> 21 | G118: {=IFERROR(_xlfn.XLOOKUP(contract_no&"-"&_xlfn.ANCHORARRAY(A118),log_prices!B:B,log_prices!I:I,,0),"")} -> 5.536 | H118: {=IFERROR(_xlfn.ANCHORARRAY(E118)*_xlfn.ANCHORARRAY(G118),"")} -> 0 | I118: {=IFERROR(_xlfn.ANCHORARRAY(F118)*_xlfn.ANCHORARRAY(G118),"")} -> 116.256 | N118: 184
A119: 112 | B119: SERVICE - 99TV366 - Site-single | C119: single | D119: 14 | E119: 0 | F119: 14 | G119: 55.36 | H119: 0 | I119: 775.04 | N119: 185
A120: 113 | B120: SERVICE - 99UK314 - Aeroport-hour | C120: hour | D120: 593 | E120: 0 | F120: 593 | G120: 5.893 | H120: 0 | I120: 3494.549 | N120: 186
A121: 114 | B121: SERVICE - 99UK314 - Aeroport-single | C121: single | D121: 177 | E121: 0 | F121: 177 | G121: 58.93 | H121: 0 | I121: 10430.61 | N121: 188
A122: 115 | B122: WAGON - 99LM412 - Site-hour | C122: hour | D122: 697.8 | E122: 0 | F122: 697.8 | G122: 5.5357143 | H122: 0 | I122: 3862.8214 | N122: 189
A123: 116 | B123: WAGON - 99LM412 - Site-single | C123: single | D123: 336 | E123: 0 | F123: 336 | G123: 55.357143 | H123: 0 | I123: 18600 | N123: 190
A124: 118 | B124: GARBAGE TRUCK - 77VL420 - Camp-single | C124: single | D124: 180 | E124: 0 | F124: 180 | G124: 275 | H124: 0 | I124: 49500 | N124: 191
A125: 119 | B125: SERVICE - 57BV285 - Site-single | C125: single | D125: 103 | E125: 0 | F125: 103 | G125: 62.5 | H125: 0 | I125: 6437.5 | N125: 192
A126: 120 | B126: SERVICE - 57BV285 - Site-hour | C126: hour | D126: 116 | E126: 0 | F126: 116 | G126: 6.25 | H126: 0 | I126: 725 | N126: 193
A127: 121 | B127: SERVICE - 90UX686 - Site-single | C127: single | D127: 104 | E127: 0 | F127: 104 | G127: 62.5 | H127: 0 | I127: 6500 | N127: 194
A128: 122 | B128: SERVICE - 90UX686 - Site-hour | C128: hour | D128: 188 | E128: 0 | F128: 188 | G128: 6.25 | H128: 0 | I128: 1175 | N128: 196
A129: 123 | B129: SERVICE - 99DT131 - Site-single | C129: single | D129: 110 | E129: 0 | F129: 110 | G129: 55.36 | H129: 0 | I129: 6089.6 | N129: 197
A130: 124 | B130: SERVICE - 99DT131 - Site-hour | C130: hour | D130: 100 | E130: 0 | F130: 100 | G130: 5.536 | H130: 0 | I130: 553.6 | N130: 198
... A138: 188 | B138: SERVICE - 10ON175 - hour | C138: single | D138: 56 | E138: 0 | F138: 56 | G138: 62.5 | H138: 0 | I138: 3500 | N138: 208
A139: 189 | B139: SERVICE - 10ON175 - single | C139: hour | D139: 40 | E139: 0 | F139: 40 | G139: 6.25 | H139: 0 | I139: 250 | N139: M-1
A140: 190 | B140: SERVICE - 27BZ361 - hour | C140: single | D140: 44 | E140: 0 | F140: 44 | G140: 55.357143 | H140: 0 | I140: 2435.7143 | N140: R-1
A141: 191 | B141: SERVICE - 27BZ361 - single | C141: hour | D141: 50 | E141: 0 | F141: 50 | G141: 5.5357143 | H141: 0 | I141: 276.78571 | N141: R-2
A142: 192 | B142: SERVICE - 10ZU722 - hour | C142: single | D142: 44 | E142: 0 | F142: 44 | G142: 62.5 | H142: 0 | I142: 2750 | N142: R-3
A143: 193 | B143: SERVICE - 10ZU722 - single | C143: hour | D143: 64 | E143: 0 | F143: 64 | G143: 6.25 | H143: 0 | I143: 400 | N143: R-4
A144: 194 | B144: SERVICE - 77PV319 - single | C144: single | D144: 45 | E144: 0 | F144: 45 | G144: 50 | H144: 0 | I144: 2250
A145: 196 | B145: SERVICE - 38BG860 - single | C145: single | D145: 41 | E145: 0 | F145: 41 | G145: 55.357143 | H145: 0 | I145: 2269.6429
A146: 197 | B146: SERVICE - 38BG860 - hour | C146: hour | D146: 20 | E146: 0 | F146: 20 | G146: 5.5357143 | H146: 0 | I146: 110.71429
A147: 198 | B147: SERVICE - 77PV659 - hour | C147: single | D147: 35 | E147: 0 | F147: 35 | G147: 85 | H147: 0 | I147: 2975 | K147: =SUM(H117:H155) -> #VALUE!
A148: 200 | B148: SERVICE - Pickup - 77DK884 - hour | C148: single | D148: 40 | E148: 0 | F148: 40 | G148: 89.285714 | H148: 0 | I148: 3571.4286 | K148: {=H149:H150} -> 4660.7143
A149: 202 | B149: Aerial Platform - ISUZU -90GG153 - single | C149: single | D149: 29 | E149: 29 | F149: 58 | G149: 160.71429 | H149: 4660.7143 | I149: 9321.4286 | K149: 241.07143
A150: 203 | B150: Aerial Platform - ISUZU -90GG153 - hour | C150: hour | D150: 3 | E150: 15 | F150: 18 | G150: 16.071429 | H150: 241.07143 | I150: 289.28571 | K150: =K147-SUM(_xlfn.ANCHORARRAY(K148)) -> #VALUE!
A151: 204 | B151: SERVICE - 53BD239 - single | C151: single | D151: 20 | E151: 0 | F151: 20 | G151: 62.5 | H151: 0 | I151: 1250
A152: 205 | B152: SERVICE - 53BD239 - hour | C152: hour | D152: 16 | E152: 0 | F152: 16 | G152: 6.25 | H152: 0 | I152: 100
A153: 206 | B153: SERVICE - 99GN495 - single | C153: single | D153: 14 | E153: 0 | F153: 14 | G153: 62.5 | H153: 0 | I153: 875
A154: 207 | B154: SERVICE - 99GN495 - hour | C154: hour | D154: 2 | E154: 0 | F154: 2 | G154: 6.25 | H154: 0 | I154: 12.5
A155: 208 | B155: SERVICE - 10OG142 - single | C155: single | D155: 14 | E155: 0 | F155: 14 | G155: 62.5 | H155: 0 | I155: 875
A156: M-1 | B156: Diesel Payment (15 lt - 18 lt / 100 km)-lt | C156: lt | D156: 142405.89 | E156: 0.1 | F156: 142405.99 | G156: 1 | H156: 0.1 | I156: 142405.99
A157: R-1 | B157: Retention - Fuel Reduction | C157: lt | D157: 120279.55 | E157: 0.1 | F157: 120279.65 | G157: -1 | H157: -0.1 | I157: -120279.65
A158: R-2 | B158: Retention - HSE Penalty Deduction (OHS) | C158: AZN | D158: 100 | E158: 0 | F158: 100 | G158: -1 | H158: 0 | I158: -100
A159: R-3 | B159: Retention - Mistakes for 8&9&10-25-single day | C159: single | D159: 58 | E159: 0 | F159: 58 | G159: -55.36 | H159: 0 | I159: -3210.88
A160: R-4 | B160: Retention - Mistakes for 8&9&10-25 - hour | C160: hour | D160: 150.999 | E160: 0 | F160: 150.999 | G160: -5.536 | H160: 0 | I160: -835.93046
A163: ="TOTAL PAYMENT (AZN)"&CHAR(10)&"CƏMİ ÖDƏMƏ (AZN)" -> TOTAL PAYMENT (AZN) CƏMİ ÖDƏMƏ (AZN) | H163: {=SUM(_xlfn._xlws.FILTER(H117:H162,H117:H162>0))} -> #VALUE! | I163: {=SUM(_xlfn._xlws.FILTER(I117:I162,I117:I162>0))} -> 859098.47
A164: ="TOTAL RETENTION (AZN)"&CHAR(10)&"CƏMİ ÇIXILMA (AZN)" -> TOTAL RETENTION (AZN) CƏMİ ÇIXILMA (AZN) | H164: {=SUM(IFERROR(_xlfn._xlws.FILTER(H6:H56,H6:H56<0),0),IFERROR(_xlfn._xlws.FILTER(H62:H112,H62:H112<0),0),IFERROR(_xlfn._xlws.FILTER(H118:H162,H118:H162<0),0))} -> -0.1 | I164: {=SUM(IFERROR(_xlfn._xlws.FILTER(I6:I56,I6:I56<0),0),IFERROR(_xlfn._xlws.FILTER(I62:I112,I62:I112<0),0),IFERROR(_xlfn._xlws.FILTER(I118:I162,I118:I162<0),0))} -> -124426.47
A165: ="TOTAL (AZN)"&CHAR(10)&"CƏMİ (AZN)" -> TOTAL (AZN) CƏMİ (AZN) | H165: =SUM(H163:H164) -> #VALUE! | I165: =SUM(I163:I164) -> 734672
A167: =A59 -> NAR TRANSPORT SERVICES MMC | C167: =_xlfn.LET(_xlpm.r,_xlfn.XLOOKUP(contract_no,log_contracts!B:B,log_contracts!G:G),IF(_xlpm.r=0,"",_xlpm.r)) -> İbrahim Kemik | E167: =E59 -> MEHMET TEVFİK ÇELİKKOL | H167: =H59 -> Mehmet Özgün DEDEKARGINOĞLU
A168: =A60 -> Subcontractor Subpodratçı | C168: =C60 -> Department Chief Bölmə Şefi | E168: =E60 -> Contract and Progress Payment Chief Ödəniş Sertifikatı Üzrə Məsul şəxs | H168: =H60 -> Technical Office Cheif Texniki Şöbə Şefi

Sheet view_daily_records
A1: {=_xlfn.LET( _xlpm.ipcData,_xlfn._xlws.SORT(_xlfn._xlws.FILTER(log_daily_records!B:AR,(log_daily_records!E:E=contract_no)*(log_daily_records!F:F=ipc_no)),3), _xlpm.plateNos,_xlfn.LET(_xlpm.r, _xlfn.UNIQUE(_xlfn.TAKE(_xlpm.ipcData,,3)),_xlfn.HSTACK(INDEX(_xlpm.r,,3), DATE(INDEX(_xlpm.r,,1), INDEX(_xlpm.r,,2), 1))), _xlpm.ph,_xlfn.LAMBDA(_xlpm.r,_xlpm.c,_xlfn.MAKEARRAY(_xlpm.r,_xlpm.c,_xlfn.LAMBDA(_xlpm.rl,_xlpm.cl,""))), _xlpm.makeBlock, _xlfn.LAMBDA(_xlpm.plateNo,_xlpm.monthYear, _xlfn.LET( _xlpm.data, _xlfn._xlws.FILTER(_xlpm.ipcData,(INDEX(_xlpm.ipcData,,3)=_xlpm.plateNo)*(INDEX(_xlpm.ipcData,,1)=YEAR(_xlpm.monthYear))*(INDEX(_xlpm.ipcData,,2)=MONTH(_xlpm.monthYear))), _xlfn.VSTACK( _xlfn.HSTACK(_xlfn.IMAGE("https://www.kolin.com.tr/Templates/Default/assets/img/logo.png","LOGO",1),_xlpm.ph(1,5),ipc_no), _xlfn.HSTACK("Plate number:",_xlpm.plateNo,"","Contract no: ","KLN-SPP2-"&_xlfn.XLOOKUP(contract_no,log_contracts!B:B,log_contracts!C:C)&"-"&TEXT(contract_no,"000"),"Date:",TEXT(_xlpm.monthYear,"mmm yy")), _xlfn.HSTACK(_xlpm.ph(1,7)), _xlfn.HSTACK("Date ","Start time","End time ","Time diff.","Start km","End km","Km diff."), _xlfn.IFNA(_xlfn.LET( _xlpm.getDataByType, _xlfn.LAMBDA(_xlpm.type, _xlfn.LET(_xlpm.r,IFERROR(_xlfn.TAKE(_xlfn.DROP(TRANSPOSE(_xlfn._xlws.FILTER(_xlpm.data, INDEX(_xlpm.data,,6)=_xlpm.type)),6),31),""),IF(_xlpm.r=0,"",_xlpm.r)) ), _xlpm.timeStart,_xlpm.getDataByType("time-start"), _xlpm.timeEnd,_xlpm.getDataByType("time-end"), _xlpm.kmStart,_xlpm.getDataByType("km-start"), _xlpm.kmEnd,_xlpm.getDataByType("km-end"), _xlfn.HSTACK( TEXT(_xlpm.monthYear-1+_xlfn.SEQUENCE(DAY(EOMONTH(_xlpm.monthYear,0))),"dd-mm-yyyy"), _xlpm.timeStart, _xlpm.timeEnd, _xlfn.LET(_xlpm.r, IFERROR((_xlpm.timeEnd-_xlpm.timeStart)*24-11,0), IF(_xlpm.r<=0,"",ROUND(_xlpm.r,0))), _xlpm.kmStart, _xlpm.kmEnd, _xlfn.LET(_xlpm.r, IFERROR((_xlpm.kmEnd-_xlpm.kmStart),0), IF(_xlpm.r=0,"",_xlpm.r)) ) ),""), _xlfn.LET( _xlpm.getTotal, _xlfn.LAMBDA(_xlpm.type,_xlpm.index, _xlfn.LET( _xlpm.r, IFERROR(INDEX(_xlfn._xlws.FILTER(_xlpm.data, INDEX(_xlpm.data,,6)=_xlpm.type),_xlpm.index),""), IF(_xlpm.r=0,"",_xlpm.r) ) ), _xlpm.single, _xlpm.getTotal("time-end",38), _xlpm.double, _xlpm.getTotal("time-end",39), _xlpm.hour,_xlpm.getTotal("time-end",40), _xlpm.km,_xlpm.getTotal("km-end",41), _xlfn.VSTACK( _xlfn.HSTACK("",IF(_xlpm.single="","","Total single"),IF(_xlpm.double="","","Total double"),IF(_xlpm.hour="","","Total hour"),IF(_xlpm.km="","","Total fuel"),"",""), _xlfn.HSTACK("",ROUND(_xlpm.single,1),_xlpm.double,_xlpm.hour,_xlpm.km,"",""), _xlpm.ph(1,7) ) ), _xlfn.HSTACK("","Subcontractor","","","Confirmed by","",""), _xlfn.HSTACK("",_xlfn.XLOOKUP(contract_no,log_contracts!B:B,log_contracts!E:E,,0),"","",_xlfn.TEXTJOIN(CHAR(10),TRUE,_xlfn.XLOOKUP(_xlpm.plateNo,log_prices!M:M,log_prices!O:O,,0)),"",""), _xlfn.HSTACK("","______________","","","______________","",""), _xlfn.HSTACK(_xlpm.ph(1,7)) ) ) ), _xlfn.REDUCE( "", _xlfn.SEQUENCE(ROWS(_xlpm.plateNos)), _xlfn.LAMBDA(_xlpm.acc,_xlpm.idx, _xlfn.LET( _xlpm.p, INDEX(_xlpm.plateNos, _xlpm.idx, 1), _xlpm.m, INDEX(_xlpm.plateNos, _xlpm.idx, 2), _xlpm.blk, _xlpm.makeBlock(_xlpm.p,_xlpm.m), IF(_xlpm.idx=1, _xlpm.blk, _xlfn.VSTACK(_xlpm.acc, _xlpm.blk)) ) ) ) )} -> #VALUE! | G1: 14 | I1: {=ROWS(_xlfn.UNIQUE(_xlfn._xlws.FILTER(log_daily_records!B:D,(log_daily_records!E:E=contract_no)*(log_daily_records!F:F=ipc_no))))} -> 1
A2: Plate number: | B2: 90GG153 | D2: Contract no: | E2: KLN-SPP2-AA-031 | F2: Date: | G2: Mar 26
A4: Date | B4: Start time | C4: End time | D4: Time diff. | E4: Start km | F4: End km | G4: Km diff.
A5: 01-03-2026 | B5: 0.33333333 | C5: 0.75
A6: 02-03-2026 | B6: 0.33333333 | C6: 0.75
A7: 03-03-2026 | B7: 0.33333333 | C7: 0.875 | D7: 2
A8: 04-03-2026 | B8: 0.33333333 | C8: 0.75
A9: 05-03-2026 | B9: 0.33333333 | C9: 0.75
A10: 06-03-2026 | B10: 0.33333333 | C10: 0.875 | D10: 2
A11: 07-03-2026 | B11: 0.33333333 | C11: 0.75
A12: 08-03-2026 | B12: 0.33333333 | C12: 0.75
A13: 09-03-2026 | B13: 0.33333333 | C13: 0.75
A14: 10-03-2026 | B14: 0.33333333 | C14: 0.875 | D14: 2
A15: 11-03-2026 | B15: 0.33333333 | C15: 0.75
A16: 12-03-2026 | B16: 0.33333333 | C16: 0.75
A17: 13-03-2026 | B17: 0.33333333 | C17: 0.875 | D17: 2
A18: 14-03-2026 | B18: 0.33333333 | C18: 0.75
A19: 15-03-2026 | B19: 0.33333333 | C19: 0.75
A20: 16-03-2026 | B20: 0.33333333 | C20: 0.75
A21: 17-03-2026 | B21: 0.33333333 | C21: 0.75
A22: 18-03-2026 | B22: 0.33333333 | C22: 0.75
A23: 19-03-2026 | B23: 0.33333333 | C23: 0.75
A24: 20-03-2026
A25: 21-03-2026
A26: 22-03-2026
A27: 23-03-2026
A28: 24-03-2026 | B28: 0.33333333 | C28: 0.75
A29: 25-03-2026 | B29: 0.33333333 | C29: 0.75
A30: 26-03-2026 | B30: 0.33333333 | C30: 0.75
A31: 27-03-2026 | B31: 0.33333333 | C31: 0.75
A32: 28-03-2026 | B32: 0.33333333 | C32: 0.75
A33: 29-03-2026 | B33: 0.33333333 | C33: 0.75
A34: 30-03-2026 | B34: 0.33333333 | C34: 0.875 | D34: 2
A35: 31-03-2026 | B35: 0.33333333 | C35: 0.75
B36: Total single | D36: Total hour
B37: 29 | D37: 15
B39: Subcontractor | E39: Confirmed by
B40: NAR TRANSPORT SERVICES MMC | E40: İrfan Karakaya
B41: ______________ | E41: ______________

Sheet view_monthly_records
D1: =view__cover!K1 -> KLN-SPP2-AA-031
A2: # | B2: Month | C2: IPC no | D2: Quantity | E2: Amount
A3: {=_xlfn.LET( _xlpm.data, _xlfn._xlws.SORT( _xlfn.LET( _xlpm.d, _xlfn._xlws.FILTER( log_monthly_records!B:M, (log_monthly_records!D:D=contract_no)*(log_monthly_records!E:E<=ipc_no)*(log_monthly_records!G:G<>0) ), _xlfn.HSTACK( DATE(INDEX(_xlpm.d,,1),INDEX(_xlpm.d,,2),1), INDEX(_xlpm.d,,4), INDEX(_xlpm.d,,6), INDEX(_xlpm.d,,12)*INDEX(_xlpm.d,,6), _xlfn.IFNA( SUBSTITUTE( INDEX(_xlpm.d,,11), " Hiz"&_xlfn.TEXTAFTER(INDEX(_xlpm.d,,11), " Hiz" ), "" ), INDEX(_xlpm.d,,11) ) ) ), 5 ), _xlfn.DROP( _xlfn.IFNA( _xlfn.REDUCE( "", _xlfn.LET( _xlpm.descs, _xlfn.UNIQUE(INDEX(_xlpm.data,,5)), _xlfn.VSTACK( _xlfn._xlws.FILTER( _xlpm.descs, LEFT(_xlpm.descs,9)<>"Retention" ), "Retention" ) ), _xlfn.LAMBDA(_xlpm.acc,_xlpm.cur, _xlfn.LET(_xlpm.x,_xlfn.TAKE( _xlfn._xlws.FILTER( _xlpm.data, LEFT(INDEX(_xlpm.data,,5),LEN(_xlpm.cur))=_xlpm.cur ),, 4 ),_xlfn.VSTACK( _xlpm.acc, _xlfn.HSTACK("",_xlpm.cur,"","",SUM(INDEX(_xlpm.x,,4))), _xlfn.HSTACK(_xlfn.SEQUENCE(ROWS(_xlpm.x)),_xlpm.x) )) ) ), "" ), 1 ) )} | B3: Mazot Ödemesi (15 lt - 18 lt / 100 km)-lt | E3: 142405.99
A4: 1 | B4: 45689 | C4: 1 | D4: 2956 | E4: 2956
A5: 2 | B5: 45717 | C5: 2 | D5: 11129.91 | E5: 11129.91
A6: 3 | B6: 45748 | C6: 3 | D6: 7666.74 | E6: 7666.74
A7: 4 | B7: 45778 | C7: 4 | D7: 7701.45 | E7: 7701.45
A8: 5 | B8: 45809 | C8: 5 | D8: 8670.24 | E8: 8670.24
A9: 6 | B9: 45839 | C9: 6 | D9: 7430.74 | E9: 7430.74
A10: 7 | B10: 45870 | C10: 7 | D10: 10262.76 | E10: 10262.76
A11: 8 | B11: 45901 | C11: 8 | D11: 11888.04 | E11: 11888.04
A12: 9 | B12: 45931 | C12: 9 | D12: 12646.8 | E12: 12646.8
A13: 10 | B13: 45962 | C13: 10 | D13: 12886.441 | E13: 12886.441
A14: 11 | B14: 45992 | C14: 11 | D14: 15693.78 | E14: 15693.78
A15: 12 | B15: 46023 | C15: 12 | D15: 16631.703 | E15: 16631.703
... A17: 14 | B17: 46082 | C17: 14 | D17: 0.1 | E17: 0.1
B18: SERVIS - 10RN527 - Sahə-saat | E18: 835.936
A19: 1 | B19: 45870 | C19: 7 | D19: 64 | E19: 354.304
A20: 2 | B20: 45901 | C20: 8 | D20: 67 | E20: 370.912
A21: 3 | B21: 45931 | C21: 9 | D21: 20 | E21: 110.72
B22: SERVIS - 10RN527 - Sahə-tək | E22: 3210.88
A23: 1 | B23: 45870 | C23: 7 | D23: 27 | E23: 1494.72
A24: 2 | B24: 45901 | C24: 8 | D24: 30 | E24: 1660.8
A25: 3 | B25: 45931 | C25: 9 | D25: 1 | E25: 55.36
B26: Retention | E26: -124426.47
A27: 1 | B27: 45689 | C27: 1 | D27: 2956 | E27: -2956
A28: 2 | B28: 45717 | C28: 2 | D28: 9319 | E28: -9319
A29: 3 | B29: 45748 | C29: 3 | D29: 6009 | E29: -6009
A30: 4 | B30: 45778 | C30: 4 | D30: 6357 | E30: -6357
A31: 5 | B31: 45809 | C31: 5 | D31: 6873.235 | E31: -6873.235
A32: 6 | B32: 45839 | C32: 6 | D32: 7221 | E32: -7221
A33: 7 | B33: 45870 | C33: 7 | D33: 8379.42 | E33: -8379.42
A34: 8 | B34: 45901 | C34: 8 | D34: 9645 | E34: -9645
A35: 9 | B35: 45931 | C35: 9 | D35: 10987 | E35: -10987
A36: 10 | B36: 45962 | C36: 10 | D36: 11358 | E36: -11358
A37: 11 | B37: 45992 | C37: 11 | D37: 13674.9 | E37: -13674.9
A38: 12 | B38: 46023 | C38: 12 | D38: 14029.1 | E38: -14029.1
... A43: 17 | B43: 45717 | C43: 2 | D43: 100 | E43: -100

Sheet view_fuel
F1: =view__cover!K1 -> KLN-SPP2-AA-031 | H1: =view__cover!K2 -> 14
A2: # | B2: Qeydiyyat nömrə nişanı | C2: Məsafə | D2: Litres per 100km | E2: Heablanmış miqdar A | F2: Hesablanmış məbləğ (AZN) | G2: Verilmiş yanacaq miqdarı B | H2: Verilmiş yanacaq məbləği (AZN) | I2: Diff. A-B
A3: {=_xlfn.LET( _xlpm.pnos,_xlfn._xlws.SORT(_xlfn.UNIQUE(_xlfn._xlws.FILTER(log_daily_records!D:D,(log_daily_records!E:E=contract_no)*(log_daily_records!F:F=ipc_no)))), _xlpm.distance,SUMIFS(log_daily_records!AS:AS,log_daily_records!D:D,_xlpm.pnos,log_daily_records!E:E,contract_no,log_daily_records!F:F,ipc_no), _xlpm.qs,SUMIFS(log_daily_records!AP:AP,log_daily_records!D:D,_xlpm.pnos,log_daily_records!E:E,contract_no,log_daily_records!F:F,ipc_no), _xlpm.provided,SUMIFS(log_fuel_provision!D:D,log_fuel_provision!C:C,_xlpm.pnos,log_fuel_provision!A:A,">="&ipc_date_start,log_fuel_provision!A:A,"<="&ipc_date_end), _xlpm.providedAmount,SUMIFS(log_fuel_provision!E:E,log_fuel_provision!C:C,_xlpm.pnos,log_fuel_provision!A:A,">="&ipc_date_start,log_fuel_provision!A:A,"<="&ipc_date_end), _xlfn.VSTACK( _xlfn.LET( _xlpm.d, _xlfn.HSTACK( _xlfn.SEQUENCE(ROWS(_xlpm.pnos)), _xlpm.pnos, _xlpm.distance, _xlfn.LET( _xlpm.r, MATCH(2,1/(log_daily_records!D:D<>""),1), _xlpm.d, log_daily_records!D2:INDEX(log_daily_records!D:D,_xlpm.r), _xlpm.e, log_daily_records!E2:INDEX(log_daily_records!E:E,_xlpm.r), _xlpm.F, log_daily_records!F2:INDEX(log_daily_records!F:F,_xlpm.r), _xlpm.G, log_daily_records!G2:INDEX(log_daily_records!G:G,_xlpm.r), _xlpm.AQ,log_daily_records!AQ2:INDEX(log_daily_records!AQ:AQ,_xlpm.r), _xlfn.MAP(_xlpm.pnos,_xlfn.LAMBDA(_xlpm.pn,_xlfn.XLOOKUP(1,(_xlpm.d=_xlpm.pn)*(_xlpm.e=contract_no)*(_xlpm.F=ipc_no)*(_xlpm.G="km-end"),_xlpm.AQ,"",0))) ), _xlpm.qs, _xlpm.qs*1.1, IF(_xlpm.qs=0,"",_xlpm.provided), IF(_xlpm.qs=0,"",_xlpm.providedAmount), _xlpm.qs-_xlpm.provided ), _xlfn.VSTACK( _xlfn._xlws.FILTER(_xlpm.d,INDEX(_xlpm.d,,4)<>""), _xlfn.HSTACK("","","","","",SUM(INDEX(_xlpm.d,,6)),"",SUM(INDEX(_xlpm.d,,8)),"") ) ), _xlfn.HSTACK("","","","","","","","",""), _xlfn.HSTACK("","Subcontractor","","","","","Confirmed by","",""), _xlfn.HSTACK("",_xlfn.XLOOKUP(contract_no,log_contracts!B:B,log_contracts!E:E,,0),"","","","",_xlfn.TEXTJOIN(CHAR(10),TRUE,_xlfn.XLOOKUP(contract_no,log_contracts!B:B,log_contracts!G:G)),"",""), _xlfn.HSTACK("","______________","","","","","______________","","") ) )} -> #VALUE!
K4: =F4-H4 -> 0

Sheet log_monthly_records
A1: # | B1: year | C1: month | D1: contract no | E1: ipc no | F1: plate no | G1: quantity | H1: price type | I1: notes | J1: price no | K1: Price no select | L1: price description | M1: Price
A2: {=_xlfn.SEQUENCE(ROWS(_xlfn._TRO_TRAILING(C:C))-1)} -> 1 | B2: 2024 | C2: 12 | D2: 11 | E2: 1 | G2: 1 | J2: 1 | K2: 1 | L2: Aylıq Ücret | M2: 5500
A3: 2 | B3: 2024 | C3: 12 | D3: 11 | E3: 1 | G3: 8 | J3: 2 | K3: 2 | L3: Elave Ücret | M3: 200
A4: 3 | B4: 2024 | C4: 12 | D4: 11 | E4: 1 | G4: 12 | J4: 3 | K4: 3 | L4: Armatür Test (Tensile st., Yield st., Elangation) | M4: 100
A5: 4 | B5: 2025 | C5: 2 | D5: 11 | E5: 2 | G5: 1 | J5: 1 | K5: 1 | L5: Aylıq Ücret | M5: 5500
A6: 5 | B6: 2025 | C6: 2 | D6: 11 | E6: 2 | G6: 3.1 | J6: 2 | K6: 2 | L6: Elave Ücret | M6: 200
A7: 6 | B7: 2025 | C7: 2 | D7: 11 | E7: 2 | G7: 18 | J7: 3 | K7: 3 | L7: Armatür Test (Tensile st., Yield st., Elangation) | M7: 100
A8: 7 | B8: 2025 | C8: 2 | D8: 11 | E8: 2 | G8: 1 | J8: 4 | K8: 4 | L8: Su Testi | M8: 300
A9: 8 | B9: 2025 | C9: 2 | D9: 11 | E9: 2 | G9: 1 | J9: 5 | K9: 5 | L9: Kaynak Testi | M9: 540
A10: 9 | B10: 2025 | C10: 3 | D10: 11 | E10: 3 | G10: 1 | J10: 1 | K10: 1 | L10: Aylıq Ücret | M10: 5500
A11: 10 | B11: 2025 | C11: 3 | D11: 11 | E11: 3 | G11: 13 | J11: 2 | K11: 2 | L11: Elave Ücret | M11: 200
A12: 11 | B12: 2025 | C12: 3 | D12: 11 | E12: 3 | G12: 14 | J12: 3 | K12: 3 | L12: Armatür Test (Tensile st., Yield st., Elangation) | M12: 100
A13: 12 | B13: 2025 | C13: 3 | D13: 11 | E13: 3 | G13: 1 | J13: 6 | K13: 6 | L13: Ultrasonic Pulse Echo (Betonarme) | M13: 1000
A14: 13 | B14: 2025 | C14: 3 | D14: 11 | E14: 3 | G14: 4 | J14: 7 | K14: 7 | L14: Armatür Test (Bend) | M14: 110
... A99: 98 | B99: 2025 | C99: 11 | D99: 30 | E99: 11 | G99: 1 | J99: 4 | K99: 4 | L99: AMBULANCE - 99JE233 | M99: 5500
A100: 99 | B100: 2025 | C100: 2 | D100: 31 | E100: 1 | G100: 2956 | J100: M-1 | K100: M-1 | L100: Mazot Ödemesi (15 lt - 18 lt / 100 km)-lt | M100: 1
A101: 100 | B101: 2025 | C101: 2 | D101: 31 | E101: 1 | G101: 2956 | J101: R-1 | K101: R-1 | L101: Retention - Fuel Reduction | M101: -1
A102: 101 | B102: 2025 | C102: 3 | D102: 31 | E102: 2 | G102: =SUMIFS(log_daily_records!AP:AP,log_daily_records!E:E,D102,log_daily_records!F:F,E102) -> 11129.91 | J102: M-1 | K102: M-1 | L102: Mazot Ödemesi (15 lt - 18 lt / 100 km)-lt | M102: 1
A103: 102 | B103: 2025 | C103: 3 | D103: 31 | E103: 2 | G103: 9319 | J103: R-1 | K103: R-1 | L103: Retention - Fuel Reduction | M103: -1
A104: 103 | B104: 2025 | C104: 3 | D104: 31 | E104: 2 | G104: 100 | J104: R-2 | K104: R-2 | L104: Retention - SƏTƏMM Cərimə Kesintisi (İSG) | M104: -1
A105: 104 | B105: 2025 | C105: 4 | D105: 31 | E105: 3 | G105: =SUMIFS(log_daily_records!AP:AP,log_daily_records!E:E,D105,log_daily_records!F:F,E105) -> 7666.74 | J105: M-1 | K105: M-1 | L105: Mazot Ödemesi (15 lt - 18 lt / 100 km)-lt | M105: 1
A106: 105 | B106: 2025 | C106: 4 | D106: 31 | E106: 3 | G106: 6009 | J106: R-1 | K106: R-1 | L106: Retention - Fuel Reduction | M106: -1
A107: 106 | B107: 2025 | C107: 5 | D107: 31 | E107: 4 | G107: =SUMIFS(log_daily_records!AP:AP,log_daily_records!E:E,D107,log_daily_records!F:F,E107) -> 7701.45 | J107: M-1 | K107: M-1 | L107: Mazot Ödemesi (15 lt - 18 lt / 100 km)-lt | M107: 1
A108: 107 | B108: 2025 | C108: 5 | D108: 31 | E108: 4 | G108: 6357 | J108: R-1 | K108: R-1 | L108: Retention - Fuel Reduction | M108: -1
A109: 108 | B109: 2025 | C109: 6 | D109: 31 | E109: 5 | G109: =SUMIFS(log_daily_records!AP:AP,log_daily_records!E:E,D109,log_daily_records!F:F,E109) -> 8670.24 | J109: M-1 | K109: M-1 | L109: Mazot Ödemesi (15 lt - 18 lt / 100 km)-lt | M109: 1
A110: 109 | B110: 2025 | C110: 6 | D110: 31 | E110: 5 | G110: 6873.235 | J110: R-1 | K110: R-1 | L110: Retention - Fuel Reduction | M110: -1
A111: 110 | B111: 2025 | C111: 7 | D111: 31 | E111: 6 | G111: =SUMIFS(log_daily_records!AP:AP,log_daily_records!E:E,D111,log_daily_records!F:F,E111)-751.13 -> 7430.74 | I111: added 751.5 from June 2025 | J111: M-1 | K111: M-1 | L111: Mazot Ödemesi (15 lt - 18 lt / 100 km)-lt | M111: 1
A112: 111 | B112: 2025 | C112: 7 | D112: 31 | E112: 6 | G112: 7221 | J112: R-1 | K112: R-1 | L112: Retention - Fuel Reduction | M112: -1
A113: 112 | B113: 2025 | C113: 8 | D113: 31 | E113: 7 | F113: 10RN527 | G113: 27 | J113: 31 | K113: 31 | L113: SERVIS - 10RN527 - Sahə-tək | M113: 55.36
A114: 113 | B114: 2025 | C114: 8 | D114: 31 | E114: 7 | F114: 10RN527 | G114: 64 | J114: 29 | K114: 29 | L114: SERVIS - 10RN527 - Sahə-saat | M114: 5.536
A115: 114 | B115: 2025 | C115: 8 | D115: 31 | E115: 7 | G115: =SUMIFS(log_daily_records!AP:AP,log_daily_records!E:E,D115,log_daily_records!F:F,E115)+140 -> 10262.76 | I115: added 140 from July 2025 | J115: M-1 | K115: M-1 | L115: Mazot Ödemesi (15 lt - 18 lt / 100 km)-lt | M115: 1
A116: 115 | B116: 2025 | C116: 8 | D116: 31 | E116: 7 | G116: 8379.42 | J116: R-1 | K116: R-1 | L116: Retention - Fuel Reduction | M116: -1
A117: 116 | B117: 2025 | C117: 9 | D117: 31 | E117: 8 | F117: 10RN527 | G117: 30 | H117: single | J117: 31 | K117: 31 | L117: SERVIS - 10RN527 - Sahə-tək | M117: 55.36
A118: 117 | B118: 2025 | C118: 9 | D118: 31 | E118: 8 | F118: 10RN527 | G118: 67 | H118: hour | J118: 29 | K118: 29 | L118: SERVIS - 10RN527 - Sahə-saat | M118: 5.536
A119: 118 | B119: 2025 | C119: 9 | D119: 31 | E119: 8 | G119: =SUMIFS(log_daily_records!AP:AP,log_daily_records!E:E,D119,log_daily_records!F:F,E119) -> 11888.04 | J119: M-1 | K119: M-1 | L119: Mazot Ödemesi (15 lt - 18 lt / 100 km)-lt | M119: 1
A120: 119 | B120: 2025 | C120: 9 | D120: 31 | E120: 8 | G120: 9645 | J120: R-1 | K120: R-1 | L120: Retention - Fuel Reduction | M120: -1
A121: 120 | B121: 2025 | C121: 10 | D121: 31 | E121: 9 | F121: 10RN527 | G121: 1 | H121: single | J121: 31 | K121: 31 | L121: SERVIS - 10RN527 - Sahə-tək | M121: 55.36
A122: 121 | B122: 2025 | C122: 10 | D122: 31 | E122: 9 | F122: 10RN527 | G122: 20 | H122: hour | I122: mistakenly calculated | J122: 29 | K122: 29 | L122: SERVIS - 10RN527 - Sahə-saat | M122: 5.536
A123: 122 | B123: 2025 | C123: 10 | D123: 31 | E123: 9 | G123: =SUMIFS(log_daily_records!AP:AP,log_daily_records!E:E,D123,log_daily_records!F:F,E123) -> 12646.8 | J123: M-1 | K123: M-1 | L123: Mazot Ödemesi (15 lt - 18 lt / 100 km)-lt | M123: 1
A124: 123 | B124: 2025 | C124: 10 | D124: 31 | E124: 9 | G124: 10987 | J124: R-1 | K124: R-1 | L124: Retention - Fuel Reduction | M124: -1
A125: 124 | B125: 2025 | C125: 11 | D125: 31 | E125: 10 | G125: =SUMIFS(log_daily_records!AP:AP,log_daily_records!E:E,D125,log_daily_records!F:F,E125) -> 12886.441 | J125: M-1 | K125: M-1 | L125: Mazot Ödemesi (15 lt - 18 lt / 100 km)-lt | M125: 1
A126: 125 | B126: 2025 | C126: 11 | D126: 31 | E126: 10 | G126: 11358 | J126: R-1 | K126: R-1 | L126: Retention - Fuel Reduction | M126: -1
A127: 126 | B127: 2025 | C127: 11 | D127: 31 | E127: 10 | G127: 58 | J127: R-3 | K127: R-3 | L127: Retention - Mistakes for 8&9&10-25-single day | M127: -55.36
A128: 127 | B128: 2025 | C128: 11 | D128: 31 | E128: 10 | G128: 150.999 | J128: R-4 | K128: R-4 | L128: Retention - Mistakes for 8&9&10-25 - hour | M128: -5.536
A129: 128 | B129: 2024 | C129: 9 | D129: 33 | E129: 4 | G129: 19225 | J129: 1 | K129: 1 | L129: Kahvaltı Hizmeti Verimesi | M129: 1.5
A130: 129 | B130: 2024 | C130: 9 | D130: 33 | E130: 4 | G130: 25773 | J130: 2 | K130: 2 | L130: Öğle Yemeği Hizmeti Verilmesi | M130: 4.7
A131: 130 | B131: 2024 | C131: 9 | D131: 33 | E131: 4 | G131: 21414 | J131: 3 | K131: 3 | L131: Akşam Yemeği Hizmeti Verilmesi | M131: 4.7
A132: 131 | B132: 2024 | C132: 9 | D132: 33 | E132: 4 | G132: 3363 | J132: 5 | K132: 5 | L132: Kumanya Hizmeti Verilmesi | M132: 3.85
A133: 132 | B133: 2025 | C133: 1 | D133: 33 | E133: 5 | G133: 13344 | J133: 1 | K133: 1 | L133: Kahvaltı Hizmeti Verimesi | M133: 1.5
A134: 133 | B134: 2025 | C134: 1 | D134: 33 | E134: 5 | G134: 18963 | J134: 2 | K134: 2 | L134: Öğle Yemeği Hizmeti Verilmesi | M134: 4.7
A135: 134 | B135: 2025 | C135: 1 | D135: 33 | E135: 5 | G135: 15716 | J135: 3 | K135: 3 | L135: Akşam Yemeği Hizmeti Verilmesi | M135: 4.7
A136: 135 | B136: 2025 | C136: 1 | D136: 33 | E136: 5 | G136: 1736 | J136: 5 | K136: 5 | L136: Kumanya Hizmeti Verilmesi | M136: 3.85
A137: 136 | B137: 2025 | C137: 2 | D137: 33 | E137: 6 | G137: -13344 | J137: 1 | K137: 1 | L137: Kahvaltı Hizmeti Verimesi | M137: 1.5
A138: 137 | B138: 2025 | C138: 2 | D138: 33 | E138: 6 | G138: -18963 | J138: 2 | K138: 2 | L138: Öğle Yemeği Hizmeti Verilmesi | M138: 4.7
A139: 138 | B139: 2025 | C139: 2 | D139: 33 | E139: 6 | G139: -15716 | J139: 3 | K139: 3 | L139: Akşam Yemeği Hizmeti Verilmesi | M139: 4.7
A140: 139 | B140: 2025 | C140: 2 | D140: 33 | E140: 6 | G140: -1736 | J140: 5 | K140: 5 | L140: Kumanya Hizmeti Verilmesi | M140: 3.85
... A152: 151 | B152: 2025 | C152: 4 | D152: 33 | E152: 8 | G152: 5637 | J152: 11 | K152: 11 | L152: Kumanya Hizmeti Verilmesi_v1 | M152: 3.5
A153: 152 | B153: 2025 | C153: 4 | D153: 33 | E153: 8 | G153: 4 | J153: R-1 | K153: R-1 | L153: Retention - First Aid Training | M153: -80
A154: 153 | B154: 2025 | C154: 4 | D154: 33 | E154: 8 | G154: 4 | J154: R-2 | K154: R-2 | L154: Retention - First Fire Training | M154: -80
A155: 154 | B155: 2025 | C155: 5 | D155: 33 | E155: 9 | G155: -71872 | J155: 7 | K155: 7 | L155: Kahvaltı Hizmeti Verimesi_v1 | M155: 1.45
A156: 155 | B156: 2025 | C156: 5 | D156: 33 | E156: 9 | G156: -102630 | J156: 8 | K156: 8 | L156: Öğle Yemeği Hizmeti Verilmesi_v1 | M156: 4.2
A157: 156 | B157: 2025 | C157: 5 | D157: 33 | E157: 9 | G157: -90623 | J157: 9 | K157: 9 | L157: Akşam Yemeği Hizmeti Verilmesi_v1 | M157: 4.2
A158: 157 | B158: 2025 | C158: 5 | D158: 33 | E158: 9 | G158: -11560 | J158: 11 | K158: 11 | L158: Kumanya Hizmeti Verilmesi_v1 | M158: 3.5
A159: 158 | B159: 2025 | C159: 5 | D159: 33 | E159: 9 | G159: 101270 | J159: 12 | K159: 12 | L159: Kahvaltı Hizmeti Verimesi_v2 | M159: 1.56
A160: 159 | B160: 2025 | C160: 5 | D160: 33 | E160: 9 | G160: 137486 | J160: 13 | K160: 13 | L160: Öğle Yemeği Hizmeti Verilmesi_v2 | M160: 4.53
A161: 160 | B161: 2025 | C161: 5 | D161: 33 | E161: 9 | G161: 118849 | J161: 14 | K161: 14 | L161: Akşam Yemeği Hizmeti Verilmesi_v2 | M161: 4.53
A162: 161 | B162: 2025 | C162: 5 | D162: 33 | E162: 9 | G162: 3311 | J162: 15 | K162: 15 | L162: Gece Yemeği Hizmeti Verilmesi_v2 | M162: 4.53
A163: 162 | B163: 2025 | C163: 5 | D163: 33 | E163: 9 | G163: 13886 | J163: 16 | K163: 16 | L163: Kumanya Hizmeti Verilmesi_v2 | M163: 3.77
A164: 163 | B164: 2025 | C164: 5 | D164: 33 | E164: 9 | G164: 1 | J164: R-3 | K164: R-3 | L164: Retention - Hygiene Non-Compliance Penalty | M164: -680
A165: 164 | B165: 2025 | C165: 6 | D165: 33 | E165: 10 | G165: 28551 | J165: 12 | K165: 12 | L165: Kahvaltı Hizmeti Verimesi_v2 | M165: 1.56
A166: 165 | B166: 2025 | C166: 6 | D166: 33 | E166: 10 | G166: 33698 | J166: 13 | K166: 13 | L166: Öğle Yemeği Hizmeti Verilmesi_v2 | M166: 4.53
A167: 166 | B167: 2025 | C167: 6 | D167: 33 | E167: 10 | G167: 30708 | J167: 14 | K167: 14 | L167: Akşam Yemeği Hizmeti Verilmesi_v2 | M167: 4.53
A168: 167 | B168: 2025 | C168: 6 | D168: 33 | E168: 10 | G168: 3422 | J168: 15 | K168: 15 | L168: Gece Yemeği Hizmeti Verilmesi_v2 | M168: 4.53
A169: 168 | B169: 2025 | C169: 6 | D169: 33 | E169: 10 | G169: 1781 | J169: 16 | K169: 16 | L169: Kumanya Hizmeti Verilmesi_v2 | M169: 3.77
A170: 169 | B170: 2025 | C170: 7 | D170: 33 | E170: 11 | G170: 35230 | J170: 12 | K170: 12 | L170: Kahvaltı Hizmeti Verimesi_v2 | M170: 1.56
A171: 170 | B171: 2025 | C171: 7 | D171: 33 | E171: 11 | G171: 40659 | J171: 13 | K171: 13 | L171: Öğle Yemeği Hizmeti Verilmesi_v2 | M171: 4.53
A172: 171 | B172: 2025 | C172: 7 | D172: 33 | E172: 11 | G172: 37822 | J172: 14 | K172: 14 | L172: Akşam Yemeği Hizmeti Verilmesi_v2 | M172: 4.53
A173: 172 | B173: 2025 | C173: 7 | D173: 33 | E173: 11 | G173: 3943 | J173: 15 | K173: 15 | L173: Gece Yemeği Hizmeti Verilmesi_v2 | M173: 4.53
A174: 173 | B174: 2025 | C174: 7 | D174: 33 | E174: 11 | G174: 2485 | J174: 16 | K174: 16 | L174: Kumanya Hizmeti Verilmesi_v2 | M174: 3.77
A175: 174 | B175: 2025 | C175: 8 | D175: 33 | E175: 12 | G175: 43128 | J175: 12 | K175: 12 | L175: Kahvaltı Hizmeti Verimesi_v2 | M175: 1.56
A176: 175 | B176: 2025 | C176: 8 | D176: 33 | E176: 12 | G176: 46474 | J176: 13 | K176: 13 | L176: Öğle Yemeği Hizmeti Verilmesi_v2 | M176: 4.53
... A184: 183 | B184: 2025 | C184: 9 | D184: 33 | E184: 13 | G184: 4971 | J184: 16 | K184: 16 | L184: Kumanya Hizmeti Verilmesi_v2 | M184: 3.77
A185: 184 | B185: 2025 | C185: 9 | D185: 33 | E185: 13 | G185: 5.15 | J185: R-4 | K185: R-4 | L185: Retention - Unsatisfactory meal quality | M185: -1
A186: 185 | B186: 2025 | C186: 10 | D186: 33 | E186: 14 | G186: 51154 | J186: 12 | K186: 12 | L186: Kahvaltı Hizmeti Verimesi_v2 | M186: 1.56
A187: 186 | B187: 2025 | C187: 10 | D187: 33 | E187: 14 | G187: 56012 | J187: 13 | K187: 13 | L187: Öğle Yemeği Hizmeti Verilmesi_v2 | M187: 4.53
A188: 187 | B188: 2025 | C188: 10 | D188: 33 | E188: 14 | G188: 52993 | J188: 14 | K188: 14 | L188: Akşam Yemeği Hizmeti Verilmesi_v2 | M188: 4.53
A189: 188 | B189: 2025 | C189: 10 | D189: 33 | E189: 14 | G189: 3837 | J189: 15 | K189: 15 | L189: Gece Yemeği Hizmeti Verilmesi_v2 | M189: 4.53
A190: 189 | B190: 2025 | C190: 10 | D190: 33 | E190: 14 | G190: 4454 | J190: 16 | K190: 16 | L190: Kumanya Hizmeti Verilmesi_v2 | M190: 3.77
A191: 190 | B191: 2025 | C191: 11 | D191: 33 | E191: 15 | G191: 49730 | J191: 12 | K191: 12 | L191: Kahvaltı Hizmeti Verimesi_v2 | M191: 1.56
A192: 191 | B192: 2025 | C192: 11 | D192: 33 | E192: 15 | G192: 56306 | J192: 13 | K192: 13 | L192: Öğle Yemeği Hizmeti Verilmesi_v2 | M192: 4.53
A193: 192 | B193: 2025 | C193: 11 | D193: 33 | E193: 15 | G193: 52246 | J193: 14 | K193: 14 | L193: Akşam Yemeği Hizmeti Verilmesi_v2 | M193: 4.53
A194: 193 | B194: 2025 | C194: 11 | D194: 33 | E194: 15 | G194: 3707 | J194: 15 | K194: 15 | L194: Gece Yemeği Hizmeti Verilmesi_v2 | M194: 4.53
A195: 194 | B195: 2025 | C195: 11 | D195: 33 | E195: 15 | G195: 3149 | J195: 16 | K195: 16 | L195: Kumanya Hizmeti Verilmesi_v2 | M195: 3.77
A196: 195 | B196: 2025 | C196: 6 | D196: 91 | E196: 1 | F196: 90VJ454 | G196: =1+5/30 -> 1.1666667 | I196: 6&7 2025 | J196: 1 | K196: 1 | L196: 90 VJ 454 - 53-12 Ş-DƏ ATS-3613 yanacaq çəni-tək | M196: 3500
A197: 196 | B197: 2025 | C197: 8 | D197: 91 | E197: 2 | F197: 90VJ454 | G197: 1 | J197: 1 | K197: 1 | L197: 90 VJ 454 - 53-12 Ş-DƏ ATS-3613 yanacaq çəni-tək | M197: 3500
A198: 197 | B198: 2025 | C198: 9 | D198: 91 | E198: 3 | F198: 90VJ454 | G198: 1 | J198: 1 | K198: 1 | L198: 90 VJ 454 - 53-12 Ş-DƏ ATS-3613 yanacaq çəni-tək | M198: 3500
A199: 198 | B199: 2025 | C199: 10 | D199: 91 | E199: 4 | F199: 90VJ454 | G199: 1 | J199: 1 | K199: 1 | L199: 90 VJ 454 - 53-12 Ş-DƏ ATS-3613 yanacaq çəni-tək | M199: 3500
A200: 199 | B200: 2025 | C200: 11 | D200: 91 | E200: 5 | F200: 90VJ454 | G200: 1 | J200: 1 | K200: 1 | L200: 90 VJ 454 - 53-12 Ş-DƏ ATS-3613 yanacaq çəni-tək | M200: 3500
A201: 200 | B201: 2025 | C201: 9 | D201: 98 | E201: 3 | F201: 50BD416 | G201: 250 | J201: R-1 | K201: R-1 | L201: Retention - Fuel Reduction | M201: -1
A202: 201 | B202: 2025 | C202: 10 | D202: 98 | E202: 4 | F202: 50BD416 | G202: -250 | J202: R-2 | K202: R-2 | L202: Retention - Fuel Reduction (Yanlış ödəniş) | M202: -1
...

Sheet log_daily_records
A1: # =LET(hourRow,COUNTA($A:$A)+2,start,INDIRECT("H"&ROW()-1&":AL"&ROW()-1),IF(start="","",start+10/24+IFERROR(INDIRECT("H"&hourRow&":AL"&hourRow),0)/24)) | B1: year | C1: month | D1: plateno | E1: conctract no | F1: ipc no | G1: type | H1: 1 | I1: 2 | J1: 3 | K1: 4 | L1: 5 | M1: 6 | N1: 7 | O1: 8 | P1: 9 | Q1: 10 | R1: 11 | S1: 12 | T1: 13 | U1: 14 | V1: 15 | W1: 16 | X1: 17 | Y1: 18 | Z1: 19 | AA1: 20 | AB1: 21 | AC1: 22 | AD1: 23 | AE1: 24 | AF1: 25 | AG1: 26 | AH1: 27 | AI1: 28 | AJ1: 29 | AK1: 30 | AL1: 31 | AM1: Single | AN1: Double | AO1: Hours | AP1: Calc. fuel | AQ1: 100km/lt | AR1: Notes | AS1: Diff. dist.
A2: 1 | B2: 2025 | C2: 1 | D2: 99AS882 | E2: 30 | F2: 1 | G2: time-start | AC2: 0.29166667 | AD2: 0.29166667 | AE2: 0.29166667 | AF2: 0.29166667 | AG2: 0.29166667 | AH2: 0.29166667 | AI2: 0.29166667 | AJ2: 0.29166667 | AK2: 0.29166667 | AL2: 0.29166667
A3: 2 | B3: 2025 | C3: 1 | D3: 99AS882 | E3: 30 | F3: 1 | G3: time-end | AC3: 0.75 | AD3: 0.75 | AE3: 0.75 | AF3: 0.75 | AG3: 0.79166667 | AH3: 0.79166667 | AI3: 0.75 | AJ3: 0.75 | AK3: 0.75 | AL3: 0.75 | AM3: 10
A4: 3 | B4: 2025 | C4: 2 | D4: 99AS882 | E4: 30 | F4: 2 | G4: time-start | H4: 0.29166667 | I4: 0.29166667 | J4: 0.29166667 | K4: 0.29166667 | L4: 0.29166667 | M4: 0.29166667 | N4: 0.29166667 | O4: 0.29166667 | P4: 0.29166667 | Q4: 0.29166667 | R4: 0.29166667 | S4: 0.29166667 | T4: 0.29166667 | U4: 0.29166667 | V4: 0.29166667 | W4: 0.29166667 | X4: 0.29166667 | Y4: 0.29166667 | Z4: 0.29166667 | AA4: 0.29166667 | AB4: 0.29166667 | AC4: 0.29166667 | AD4: 0.29166667 | AE4: 0.29166667 | AF4: 0.29166667 | AG4: 0.29166667 | AH4: 0.29166667 | AI4: 0.29166667
A5: 4 | B5: 2025 | C5: 2 | D5: 99AS882 | E5: 30 | F5: 2 | G5: time-end | H5: 0.75 | I5: 0.75 | J5: 0.75 | K5: 0.75 | L5: 0.75 | M5: 0.75 | N5: 0.75 | O5: 0.75 | P5: 0.75 | Q5: 0.75 | R5: 0.75 | S5: 0.75 | T5: 0.75 | U5: 0.75 | V5: 0.75 | W5: 0.75 | X5: 0.75 | Y5: 0.75 | Z5: 0.75 | AA5: 0.75 | AB5: 0.75 | AC5: 0.75 | AD5: 0.75 | AE5: 0.75 | AF5: 0.75 | AG5: 0.79166667 | AH5: 0.79166667 | AI5: 0.75 | AM5: 30
A6: 5 | B6: 2025 | C6: 2 | D6: 99JE233 | E6: 30 | F6: 2 | G6: time-start | H6: 0.29166667 | I6: 0.29166667 | J6: 0.29166667 | K6: 0.29166667 | L6: 0.29166667 | M6: 0.29166667 | N6: 0.29166667 | O6: 0.29166667 | P6: 0.29166667 | Q6: 0.29166667 | R6: 0.29166667 | S6: 0.29166667 | T6: 0.29166667 | U6: 0.29166667 | V6: 0.29166667 | W6: 0.29166667 | X6: 0.29166667 | Y6: 0.29166667 | Z6: 0.29166667 | AA6: 0.29166667 | AB6: 0.29166667 | AC6: 0.29166667 | AD6: 0.29166667 | AE6: 0.29166667 | AF6: 0.29166667 | AG6: 0.29166667 | AH6: 0.29166667 | AI6: 0.29166667
A7: 6 | B7: 2025 | C7: 2 | D7: 99JE233 | E7: 30 | F7: 2 | G7: time-end | H7: 0.75 | I7: 0.75 | J7: 0.75 | K7: 0.75 | L7: 0.75 | M7: 0.75 | N7: 0.75 | O7: 0.75 | P7: 0.75 | Q7: 0.75 | R7: 0.75 | S7: 0.75 | T7: 0.75 | U7: 0.75 | V7: 0.75 | W7: 0.75 | X7: 0.75 | Y7: 0.75 | Z7: 0.75 | AA7: 0.75 | AB7: 0.75 | AC7: 0.75 | AD7: 0.75 | AE7: 0.75 | AF7: 0.75 | AG7: 0.79166667 | AH7: 0.79166667 | AI7: 0.75 | AM7: 30
A8: 7 | B8: 2025 | C8: 1 | D8: 99LT168 | E8: 31 | F8: 1 | G8: time-start | AE8: 0.29166667 | AF8: 0.29166667 | AG8: 0.29166667 | AH8: 0.29166667 | AI8: 0.29166667 | AJ8: 0.29166667 | AK8: 0.29166667 | AL8: 0.29166667
A9: 8 | B9: 2025 | C9: 1 | D9: 99LT168 | E9: 31 | F9: 1 | G9: time-end | AE9: 0.75 | AF9: 0.75 | AG9: 0.75 | AH9: 0.75 | AI9: 0.75 | AJ9: 0.75 | AK9: 0.75 | AL9: 0.75 | AM9: 8
A10: 9 | B10: 2025 | C10: 2 | D10: 99LT168 | E10: 31 | F10: 1 | G10: time-start | H10: 0.29166667 | I10: 0.29166667 | J10: 0.29166667 | K10: 0.29166667 | L10: 0.29166667 | M10: 0.29166667 | N10: 0.29166667 | O10: 0.29166667 | P10: 0.29166667 | Q10: 0.29166667 | R10: 0.29166667 | S10: 0.29166667 | T10: 0.29166667 | U10: 0.29166667 | V10: 0.29166667 | W10: 0.29166667 | X10: 0.29166667 | Y10: 0.29166667 | Z10: 0.29166667 | AA10: 0.29166667 | AB10: 0.29166667 | AC10: 0.29166667 | AD10: 0.29166667 | AE10: 0.29166667 | AF10: 0.29166667 | AG10: 0.29166667 | AH10: 0.29166667 | AI10: 0.29166667
A11: 10 | B11: 2025 | C11: 2 | D11: 99LT168 | E11: 31 | F11: 1 | G11: time-end | H11: 0.75 | I11: 0.75 | J11: 0.75 | K11: 0.75 | L11: 0.75 | M11: 0.75 | N11: 0.75 | O11: 0.75 | P11: 0.75 | Q11: 0.75 | R11: 0.75 | S11: 0.75 | T11: 0.75 | U11: 0.75 | V11: 0.75 | W11: 0.75 | X11: 0.75 | Y11: 0.75 | Z11: 0.75 | AA11: 0.75 | AB11: 0.75 | AC11: 0.75 | AD11: 0.75 | AE11: 0.75 | AF11: 0.75 | AG11: 0.79166667 | AH11: 0.79166667 | AI11: 0.75 | AM11: 28 | AO11: 2
A12: 11 | B12: 2025 | C12: 1 | D12: 99HZ395 | E12: 31 | F12: 1 | G12: time-start | AJ12: 0.29166667 | AK12: 0.29166667 | AL12: 0.29166667
A13: 12 | B13: 2025 | C13: 1 | D13: 99HZ395 | E13: 31 | F13: 1 | G13: time-end | AJ13: 0.75 | AK13: 0.75 | AL13: 0.75 | AM13: 3
A14: 13 | B14: 2025 | C14: 2 | D14: 99HZ395 | E14: 31 | F14: 1 | G14: time-start | H14: 0.29166667 | I14: 0.29166667 | J14: 0.29166667 | K14: 0.29166667 | L14: 0.29166667 | M14: 0.29166667 | N14: 0.29166667 | O14: 0.29166667 | P14: 0.29166667 | Q14: 0.29166667 | R14: 0.29166667 | S14: 0.29166667 | T14: 0.29166667 | U14: 0.29166667 | V14: 0.29166667 | W14: 0.29166667 | X14: 0.29166667 | Y14: 0.29166667 | Z14: 0.29166667 | AA14: 0.29166667 | AB14: 0.29166667 | AC14: 0.29166667 | AD14: 0.29166667 | AE14: 0.29166667 | AF14: 0.29166667 | AG14: 0.29166667 | AH14: 0.29166667 | AI14: 0.29166667
A15: 14 | B15: 2025 | C15: 2 | D15: 99HZ395 | E15: 31 | F15: 1 | G15: time-end | H15: 0.75 | I15: 0.75 | J15: 0.75 | K15: 0.75 | L15: 0.75 | M15: 0.75 | N15: 0.75 | O15: 0.75 | P15: 0.75 | Q15: 0.75 | R15: 0.75 | S15: 0.75 | T15: 0.75 | U15: 0.75 | V15: 0.75 | W15: 0.75 | X15: 0.75 | Y15: 0.75 | Z15: 0.75 | AA15: 0.75 | AB15: 0.75 | AC15: 0.75 | AD15: 0.75 | AE15: 0.75 | AF15: 0.75 | AG15: 0.75 | AH15: 0.75 | AI15: 0.75 | AM15: 28
A16: 15 | B16: 2025 | C16: 2 | D16: 99FB123 | E16: 31 | F16: 1 | G16: time-start | M16: 0.29166667 | N16: 0.29166667 | O16: 0.29166667 | P16: 0.29166667 | Q16: 0.29166667 | R16: 0.29166667
A17: 16 | B17: 2025 | C17: 2 | D17: 99FB123 | E17: 31 | F17: 1 | G17: time-end | M17: 0.75 | N17: 0.75 | O17: 0.75 | P17: 0.75 | Q17: 0.75 | R17: 0.75 | AM17: 6
A18: 17 | B18: 2025 | C18: 2 | D18: 90OV187 | E18: 31 | F18: 1 | G18: time-start | S18: 0.29166667 | T18: 0.29166667 | U18: 0.29166667 | V18: 0.29166667 | W18: 0.29166667 | X18: 0.29166667 | Y18: 0.29166667 | Z18: 0.29166667 | AA18: 0.29166667 | AB18: 0.29166667 | AC18: 0.29166667 | AD18: 0.29166667 | AE18: 0.29166667 | AF18: 0.29166667 | AG18: 0.29166667 | AH18: 0.29166667 | AI18: 0.29166667
A19: 18 | B19: 2025 | C19: 2 | D19: 90OV187 | E19: 31 | F19: 1 | G19: time-end | S19: 0.75 | T19: 0.75 | U19: 0.75 | V19: 0.75 | W19: 0.75 | X19: 0.75 | Y19: 0.75 | Z19: 0.75 | AA19: 0.75 | AB19: 0.75 | AC19: 0.75 | AD19: 0.75 | AE19: 0.75 | AF19: 0.75 | AG19: 0.75 | AH19: 0.75 | AI19: 0.75 | AM19: 17
A20: 19 | B20: 2025 | C20: 2 | D20: 77UG347 | E20: 31 | F20: 1 | G20: time-start | H20: 0.29166667 | I20: 0.29166667 | J20: 0.29166667 | K20: 0.29166667 | AK20: 0.29166667 | AL20: 0.29166667
A21: 20 | B21: 2025 | C21: 2 | D21: 77UG347 | E21: 31 | F21: 1 | G21: time-end | H21: 0.75 | I21: 0.75 | J21: 0.75 | K21: 0.75 | AK21: 0.75 | AL21: 0.75 | AM21: 6
A22: 21 | B22: 2025 | C22: 2 | D22: 90ZP408 | E22: 31 | F22: 1 | G22: time-start | K22: 0.29166667 | L22: 0.29166667 | M22: 0.29166667 | N22: 0.29166667 | O22: 0.29166667 | P22: 0.29166667 | X22: 0.29166667 | Y22: 0.29166667 | Z22: 0.29166667 | AA22: 0.29166667 | AB22: 0.29166667 | AC22: 0.29166667 | AE22: 0.29166667 | AF22: 0.29166667 | AG22: 0.29166667 | AH22: 0.29166667 | AI22: 0.29166667
A23: 22 | B23: 2025 | C23: 2 | D23: 90ZP408 | E23: 31 | F23: 1 | G23: time-end | K23: 0.79166667 | L23: 0.79166667 | M23: 0.79166667 | N23: 0.79166667 | O23: 0.79166667 | P23: 0.79166667 | X23: 0.79166667 | Y23: 0.79166667 | Z23: 0.79166667 | AA23: 0.79166667 | AB23: 0.79166667 | AC23: 0.79166667 | AE23: 0.79166667 | AF23: 0.79166667 | AG23: 0.79166667 | AH23: 0.79166667 | AI23: 0.79166667 | AM23: 17 | AO23: 17
A24: 23 | B24: 2025 | C24: 2 | D24: 66CC029 | E24: 31 | F24: 1 | G24: time-start | Q24: 0.29166667 | R24: 0.29166667 | S24: 0.29166667 | T24: 0.29166667 | U24: 0.29166667 | V24: 0.29166667 | W24: 0.29166667 | X24: 0.29166667 | Y24: 0.29166667 | Z24: 0.29166667 | AA24: 0.29166667 | AB24: 0.29166667 | AC24: 0.29166667 | AD24: 0.29166667 | AE24: 0.29166667 | AF24: 0.29166667 | AG24: 0.29166667 | AH24: 0.29166667 | AI24: 0.29166667
A25: 24 | B25: 2025 | C25: 2 | D25: 66CC029 | E25: 31 | F25: 1 | G25: time-end | Q25: 0.79166667 | R25: 0.79166667 | S25: 0.79166667 | T25: 0.79166667 | U25: 0.79166667 | V25: 0.79166667 | W25: 0.79166667 | X25: 0.79166667 | Y25: 0.79166667 | Z25: 0.79166667 | AA25: 0.79166667 | AB25: 0.79166667 | AC25: 0.79166667 | AD25: 0.79166667 | AE25: 0.79166667 | AF25: 0.79166667 | AG25: 0.79166667 | AH25: 0.79166667 | AI25: 0.79166667 | AM25: 19 | AO25: 19
A26: 25 | B26: 2025 | C26: 2 | D26: 77QK725 | E26: 31 | F26: 1 | G26: time-start | AC26: 0.29166667 | AD26: 0.29166667 | AE26: 0.29166667 | AF26: 0.29166667 | AG26: 0.29166667 | AH26: 0.29166667 | AI26: 0.29166667
A27: 26 | B27: 2025 | C27: 2 | D27: 77QK725 | E27: 31 | F27: 1 | G27: time-end | AC27: 0.75 | AD27: 0.75 | AE27: 0.75 | AF27: 0.75 | AG27: 0.75 | AH27: 0.75 | AI27: 0.75 | AM27: 7
A28: 27 | B28: 2025 | C28: 2 | D28: 77AT386 | E28: 31 | F28: 1 | G28: time-start | AA28: 0.29166667 | AB28: 0.29166667 | AC28: 0.29166667 | AD28: 0.29166667 | AE28: 0.29166667 | AF28: 0.29166667 | AG28: 0.29166667 | AH28: 0.29166667 | AI28: 0.29166667
A29: 28 | B29: 2025 | C29: 2 | D29: 77AT386 | E29: 31 | F29: 1 | G29: time-end | AA29: 0.75 | AB29: 0.75 | AC29: 0.75 | AD29: 0.75 | AE29: 0.75 | AF29: 0.75 | AG29: 0.75 | AH29: 0.75 | AI29: 0.75 | AM29: 9
A30: 29 | B30: 2025 | C30: 3 | D30: 99LT168 | E30: 31 | F30: 2 | G30: time-start | J30: 0.29166667 | K30: 0.29166667 | L30: 0.29166667 | M30: 0.29166667 | N30: 0.29166667 | O30: 0.29166667 | Q30: 0.29166667 | R30: 0.29166667 | S30: 0.29166667 | T30: 0.29166667 | U30: 0.29166667 | V30: 0.29166667 | X30: 0.29166667 | Y30: 0.29166667 | Z30: 0.29166667 | AE30: 0.29166667 | AF30: 0.29166667 | AG30: 0.29166667 | AH30: 0.29166667 | AI30: 0.29166667 | AJ30: 0.29166667
A31: 30 | B31: 2025 | C31: 3 | D31: 99LT168 | E31: 31 | F31: 2 | G31: time-end | J31: 0.75 | K31: 0.75 | L31: 0.75 | M31: 0.75 | N31: 0.75 | O31: 0.75 | Q31: 0.75 | R31: 0.75 | S31: 0.75 | T31: 0.75 | U31: 0.75 | V31: 0.75 | X31: 0.75 | Y31: 0.75 | Z31: 0.75 | AE31: 0.75 | AF31: 0.75 | AG31: 0.75 | AH31: 0.75 | AI31: 0.75 | AJ31: 0.75 | AM31: 21
A32: 31 | B32: 2025 | C32: 3 | D32: 99LT168 | E32: 31 | F32: 2 | G32: km-start | J32: 219057 | K32: 219368 | L32: 219608 | M32: 219832 | N32: 220225 | O32: 220150 | Q32: 220868 | R32: 221134 | S32: 221355 | T32: 221572 | U32: 221882 | V32: 222106 | X32: 222358 | Y32: 222609 | Z32: 222962 | AE32: 224762 | AF32: 224988 | AG32: 225232 | AH32: 225450 | AI32: 225714 | AJ32: 225934
A33: 32 | B33: 2025 | C33: 3 | D33: 99LT168 | E33: 31 | F33: 2 | G33: km-end | J33: 219318 | K33: 219583 | L33: 219832 | M33: 220225 | N33: 220450 | O33: 220678 | Q33: 221090 | R33: 221355 | S33: 221572 | T33: 221882 | U33: 222106 | V33: 222312 | X33: 222608 | Y33: 222832 | Z33: 223187 | AE33: 224988 | AF33: 225232 | AG33: 225449 | AH33: 225674 | AI33: 225931 | AJ33: 226148 | AP33: 951.48 | AQ33: 18 | AS33: 5286
A34: 33 | B34: 2025 | C34: 3 | D34: 90OV187 | E34: 31 | F34: 2 | G34: time-start | H34: 0.29166667 | I34: 0.29166667 | J34: 0.29166667 | K34: 0.29166667 | L34: 0.29166667 | M34: 0.29166667 | N34: 0.29166667 | O34: 0.29166667 | P34: 0.29166667 | Q34: 0.29166667 | R34: 0.29166667 | S34: 0.29166667 | T34: 0.29166667 | U34: 0.29166667 | V34: 0.29166667 | W34: 0.29166667 | X34: 0.29166667 | Y34: 0.29166667 | Z34: 0.29166667 | AA34: 0.29166667 | AB34: 0.29166667 | AC34: 0.29166667 | AD34: 0.29166667 | AE34: 0.29166667 | AF34: 0.29166667 | AG34: 0.29166667 | AH34: 0.29166667 | AI34: 0.29166667 | AJ34: 0.29166667 | AK34: 0.29166667
A35: 34 | B35: 2025 | C35: 3 | D35: 90OV187 | E35: 31 | F35: 2 | G35: time-end | H35: 0.75 | I35: 0.75 | J35: 0.75 | K35: 0.75 | L35: 0.75 | M35: 0.75 | N35: 0.75 | O35: 0.75 | P35: 0.75 | Q35: 0.75 | R35: 0.75 | S35: 0.75 | T35: 0.75 | U35: 0.75 | V35: 0.83333333 | W35: 0.85416667 | X35: 0.85416667 | Y35: 0.79166667 | Z35: 0.79166667 | AA35: 0.83333333 | AB35: 0.91666667 | AC35: 1.0416667 | AD35: 1.0416667 | AE35: 0.83333333 | AF35: 1 | AG35: 0.83333333 | AH35: 0.875 | AI35: 0.83333333 | AJ35: 0.83333333 | AK35: 0.875 | AM35: 30 | AO35: 49
A36: 35 | B36: 2025 | C36: 3 | D36: 90OV187 | E36: 31 | F36: 2 | G36: km-start | H36: 515805 | I36: 515985 | J36: 516085 | K36: 516251 | L36: 516411 | M36: 516611 | N36: 516766 | O36: 517040 | P36: 517235 | Q36: 517511 | R36: 517660 | S36: 517832 | T36: 517964 | U36: 518215 | V36: 518499 | W36: 518604 | X36: 518814 | Y36: 518957 | Z36: 519297 | AA36: 519520 | AB36: 519684 | AC36: 519831 | AD36: 520010 | AE36: 520267 | AF36: 520433 | AG36: 520631 | AH36: 520844 | AI36: 521090 | AJ36: 521466 | AK36: 521815
A37: 36 | B37: 2025 | C37: 3 | D37: 90OV187 | E37: 31 | F37: 2 | G37: km-end | H37: 515962 | I37: 516085 | J37: 516251 | K37: 516411 | L37: 516611 | M37: 516766 | N37: 517040 | O37: 517192 | P37: 517511 | Q37: 517660 | R37: 517832 | S37: 517964 | T37: 518215 | U37: 518499 | V37: 518604 | W37: 518806 | X37: 518955 | Y37: 519184 | Z37: 519516 | AA37: 519684 | AB37: 519831 | AC37: 520010 | AD37: 520267 | AE37: 520401 | AF37: 520622 | AG37: 520837 | AH37: 521067 | AI37: 521421 | AJ37: 521812 | AK37: 522058 | AP37: 1069.38 | AQ37: 18 | AS37: 5941
A38: 37 | B38: 2025 | C38: 3 | D38: 99HZ395 | E38: 31 | F38: 2 | G38: time-start | J38: 0.29166667 | K38: 0.29166667 | L38: 0.29166667 | M38: 0.29166667 | N38: 0.29166667 | O38: 0.29166667 | P38: 0.29166667 | Q38: 0.29166667 | R38: 0.29166667 | S38: 0.29166667 | T38: 0.29166667 | U38: 0.29166667 | V38: 0.29166667 | X38: 0.29166667 | Y38: 0.29166667 | Z38: 0.29166667 | AC38: 0.29166667 | AD38: 0.29166667 | AE38: 0.29166667 | AF38: 0.29166667 | AG38: 0.29166667 | AH38: 0.29166667 | AI38: 0.29166667 | AJ38: 0.29166667 | AL38: 0.29166667
A39: 38 | B39: 2025 | C39: 3 | D39: 99HZ395 | E39: 31 | F39: 2 | G39: time-end | J39: 0.75 | K39: 0.75 | L39: 0.75 | M39: 0.75 | N39: 0.75 | O39: 0.75 | P39: 0.75 | Q39: 0.75 | R39: 0.75 | S39: 0.75 | T39: 0.75 | U39: 0.75 | V39: 0.75 | X39: 0.75 | Y39: 0.75 | Z39: 0.75 | AC39: 0.75 | AD39: 0.75 | AE39: 0.75 | AF39: 0.75 | AG39: 0.75 | AH39: 0.75 | AI39: 0.75 | AJ39: 0.75 | AL39: 0.75 | AM39: 25
A40: 39 | B40: 2025 | C40: 3 | D40: 99HZ395 | E40: 31 | F40: 2 | G40: km-start | J40: 775300 | K40: 775503 | L40: 775655 | M40: 775789 | N40: 775942 | O40: 776086 | P40: 776235 | Q40: 776460 | R40: 776656 | S40: 776898 | T40: 777064 | U40: 777269 | V40: 777397 | X40: 777578 | Y40: 777742 | Z40: 777879 | AC40: 778197 | AD40: 778309 | AE40: 778440 | AF40: 778585 | AG40: 778729 | AH40: 778925 | AI40: 779068 | AJ40: 779265 | AL40: 779535
A41: 40 | B41: 2025 | C41: 3 | D41: 99HZ395 | E41: 31 | F41: 2 | G41: km-end | J41: 775503 | K41: 775655 | L41: 775789 | M41: 775942 | N41: 776086 | O41: 776235 | P41: 776460 | Q41: 776656 | R41: 776898 | S41: 777064 | T41: 777269 | U41: 777397 | V41: 777578 | X41: 777742 | Y41: 777879 | Z41: 778147 | AC41: 778309 | AD41: 778440 | AE41: 778585 | AF41: 778729 | AG41: 778925 | AH41: 779068 | AI41: 779265 | AJ41: 779535 | AL41: 779650 | AP41: 774 | AQ41: 18 | AS41: 4300
A42: 41 | B42: 2025 | C42: 3 | D42: 90ZP408 | E42: 31 | F42: 2 | G42: time-start | J42: 0.29166667 | K42: 0.29166667 | L42: 0.29166667 | M42: 0.29166667 | N42: 0.29166667 | O42: 0.29166667 | P42: 0.29166667 | Q42: 0.29166667 | R42: 0.29166667 | S42: 0.29166667 | T42: 0.29166667 | U42: 0.29166667 | V42: 0.29166667 | W42: 0.29166667 | X42: 0.29166667 | Y42: 0.29166667 | AC42: 0.29166667 | AD42: 0.29166667 | AE42: 0.29166667 | AF42: 0.29166667 | AG42: 0.29166667 | AH42: 0.29166667 | AI42: 0.29166667 | AJ42: 0.29166667
A43: 42 | B43: 2025 | C43: 3 | D43: 90ZP408 | E43: 31 | F43: 2 | G43: time-end | J43: 0.75 | K43: 0.75 | L43: 0.75 | M43: 0.75 | N43: 0.75 | O43: 0.75 | P43: 0.75 | Q43: 0.75 | R43: 0.75 | S43: 0.75 | T43: 0.75 | U43: 0.75 | V43: 0.75 | W43: 0.75 | X43: 0.75 | Y43: 0.75 | AC43: 0.75 | AD43: 0.75 | AE43: 0.75 | AF43: 0.75 | AG43: 0.75 | AH43: 0.75 | AI43: 0.75 | AJ43: 0.75 | AM43: 24
A44: 43 | B44: 2025 | C44: 3 | D44: 90ZP408 | E44: 31 | F44: 2 | G44: km-start | J44: 241191 | K44: 241208 | L44: 241227 | M44: 241265 | N44: 241350 | O44: 241403 | P44: 241480 | Q44: 241505 | R44: 241890 | S44: 241990 | T44: 251311 | U44: 251586 | V44: 251800 | W44: 251875 | X44: 251950 | Y44: 252025 | AC44: 252325 | AD44: 252400 | AE44: 252475 | AF44: 252550 | AG44: 252625 | AH44: 252700 | AI44: 252775 | AJ44: 252850
A45: 44 | B45: 2025 | C45: 3 | D45: 90ZP408 | E45: 31 | F45: 2 | G45: km-end | J45: 241208 | K45: 241227 | L45: 241265 | M45: 241350 | N45: 241403 | O45: 241480 | P45: 241505 | Q45: 241890 | R45: 241990 | S45: 242090 | T45: 251586 | U45: 251800 | V45: 251875 | W45: 251950 | X45: 252025 | Y45: 252100 | AC45: 252400 | AD45: 252475 | AE45: 252550 | AF45: 252625 | AG45: 252700 | AH45: 252775 | AI45: 252850 | AJ45: 252925 | AP45: 343.2 | AQ45: 15 | AS45: 2288
A46: 45 | B46: 2025 | C46: 3 | D46: 66CC029 | E46: 31 | F46: 2 | G46: time-start | H46: 0.29166667 | I46: 0.29166667 | J46: 0.29166667 | K46: 0.29166667 | L46: 0.29166667 | M46: 0.29166667 | N46: 0.29166667 | O46: 0.29166667 | P46: 0.29166667 | Q46: 0.29166667 | R46: 0.29166667 | U46: 0.29166667 | V46: 0.29166667 | W46: 0.29166667 | X46: 0.29166667 | Z46: 0.29166667 | AC46: 0.29166667 | AD46: 0.29166667 | AE46: 0.29166667 | AF46: 0.29166667 | AG46: 0.29166667 | AH46: 0.29166667 | AI46: 0.29166667 | AJ46: 0.29166667 | AL46: 0.29166667
A47: 46 | B47: 2025 | C47: 3 | D47: 66CC029 | E47: 31 | F47: 2 | G47: time-end | H47: 0.75 | I47: 0.75 | J47: 0.75 | K47: 0.75 | L47: 0.75 | M47: 0.75 | N47: 0.75 | O47: 0.75 | P47: 0.75 | Q47: 0.75 | R47: 0.75 | U47: 0.75 | V47: 0.75 | W47: 0.75 | X47: 0.75 | Z47: 0.75 | AC47: 0.75 | AD47: 0.75 | AE47: 0.75 | AF47: 0.75 | AG47: 0.75 | AH47: 0.75 | AI47: 0.75 | AJ47: 0.75 | AL47: 0.75 | AM47: 25
A48: 47 | B48: 2025 | C48: 3 | D48: 66CC029 | E48: 31 | F48: 2 | G48: km-start | H48: 10203 | I48: 10203 | J48: 10203 | K48: 10203 | L48: 10203 | M48: 10203 | N48: 10203 | O48: 10203 | P48: 10203 | Q48: 10203 | R48: 10203 | U48: 10449 | V48: 10484 | W48: 10571 | X48: 10745 | Z48: 10898 | AC48: 11250 | AD48: 11300 | AE48: 11328 | AF48: 11357 | AG48: 11490 | AH48: 11550 | AI48: 11604 | AJ48: 11665 | AL48: 11948
A49: 48 | B49: 2025 | C49: 3 | D49: 66CC029 | E49: 31 | F49: 2 | G49: km-end | H49: 10203 | I49: 10203 | J49: 10203 | K49: 10203 | L49: 10203 | M49: 10203 | N49: 10203 | O49: 10203 | P49: 10203 | Q49: 10203 | R49: 10203 | U49: 10484 | V49: 10571 | W49: 10745 | X49: 10898 | Z49: 10950 | AC49: 11300 | AD49: 11328 | AE49: 11357 | AF49: 11490 | AG49: 11550 | AH49: 11604 | AI49: 11665 | AJ49: 11687 | AL49: 11959 | AP49: 142.35 | AQ49: 15 | AS49: 949
A50: 49 | B50: 2025 | C50: 3 | D50: 77QK725 | E50: 31 | F50: 2 | G50: time-start | H50: 0.29166667 | J50: 0.29166667 | K50: 0.29166667 | L50: 0.29166667 | M50: 0.29166667 | N50: 0.29166667 | O50: 0.29166667 | Q50: 0.29166667 | R50: 0.29166667 | S50: 0.29166667 | T50: 0.29166667 | U50: 0.29166667 | V50: 0.29166667 | W50: 0.29166667 | X50: 0.29166667 | Y50: 0.29166667 | AC50: 0.29166667 | AD50: 0.29166667 | AE50: 0.29166667 | AF50: 0.29166667 | AG50: 0.29166667 | AH50: 0.29166667 | AI50: 0.29166667 | AJ50: 0.29166667
A51: 50 | B51: 2025 | C51: 3 | D51: 77QK725 | E51: 31 | F51: 2 | G51: time-end | H51: 0.75 | J51: 0.75 | K51: 0.75 | L51: 0.75 | M51: 0.75 | N51: 0.75 | O51: 0.75 | Q51: 0.75 | R51: 0.75 | S51: 0.75 | T51: 0.75 | U51: 0.75 | V51: 0.75 | W51: 0.75 | X51: 0.75 | Y51: 0.75 | AC51: 0.75 | AD51: 0.75 | AE51: 0.75 | AF51: 0.75 | AG51: 0.75 | AH51: 0.75 | AI51: 0.75 | AJ51: 0.75 | AM51: 24
A52: 51 | B52: 2025 | C52: 3 | D52: 77QK725 | E52: 31 | F52: 2 | G52: km-start | H52: 350454 | J52: 350469 | K52: 350484 | L52: 350499 | M52: 350506 | N52: 350521 | O52: 350529 | Q52: 350551 | R52: 350551 | S52: 350551 | T52: 350551 | U52: 350551 | V52: 350551 | W52: 350551 | X52: 350551 | Y52: 350551 | AC52: 350669 | AD52: 350679 | AE52: 350709 | AF52: 350717 | AG52: 350738 | AH52: 350775 | AI52: 350781 | AJ52: 350818
A53: 52 | B53: 2025 | C53: 3 | D53: 77QK725 | E53: 31 | F53: 2 | G53: km-end | H53: 350469 | J53: 350484 | K53: 350499 | L53: 350506 | M53: 350521 | N53: 350529 | O53: 350551 | Q53: 350562 | R53: 350570 | S53: 350585 | T53: 350611 | U53: 350616 | V53: 350621 | W53: 350637 | X53: 350645 | Y53: 350669 | AC53: 350679 | AD53: 350709 | AE53: 350717 | AF53: 350738 | AG53: 350775 | AH53: 350781 | AI53: 350818 | AJ53: 350842
A54: 53 | B54: 2025 | C54: 3 | D54: 77AT386 | E54: 31 | F54: 2 | G54: time-start | H54: 0.29166667 | I54: 0.29166667 | J54: 0.29166667 | K54: 0.29166667 | L54: 0.29166667 | M54: 0.29166667 | N54: 0.29166667 | O54: 0.29166667 | P54: 0.29166667 | Q54: 0.29166667 | R54: 0.29166667 | S54: 0.29166667 | T54: 0.29166667 | U54: 0.29166667 | V54: 0.29166667 | W54: 0.29166667 | X54: 0.29166667 | Y54: 0.29166667 | Z54: 0.29166667 | AA54: 0.29166667 | AB54: 0.29166667 | AC54: 0.29166667 | AD54: 0.29166667 | AE54: 0.29166667 | AF54: 0.29166667 | AG54: 0.29166667 | AH54: 0.29166667 | AI54: 0.29166667 | AJ54: 0.29166667 | AK54: 0.29166667 | AL54: 0.29166667
A55: 54 | B55: 2025 | C55: 3 | D55: 77AT386 | E55: 31 | F55: 2 | G55: time-end | H55: 0.75 | I55: 0.75 | J55: 0.75 | K55: 0.75 | L55: 0.75 | M55: 0.75 | N55: 0.75 | O55: 0.75 | P55: 0.75 | Q55: 0.75 | R55: 0.75 | S55: 0.75 | T55: 0.75 | U55: 0.75 | V55: 0.75 | W55: 0.75 | X55: 0.75 | Y55: 0.75 | Z55: 0.75 | AA55: 0.75 | AB55: 0.75 | AC55: 0.75 | AD55: 0.75 | AE55: 0.75 | AF55: 0.75 | AG55: 0.75 | AH55: 0.75 | AI55: 0.75 | AJ55: 0.75 | AK55: 0.75 | AL55: 0.75 | AM55: 31
A56: 55 | B56: 2025 | C56: 3 | D56: 90SL686 | E56: 31 | F56: 2 | G56: time-start | H56: 0.29166667 | I56: 0.29166667 | J56: 0.29166667 | K56: 0.29166667 | L56: 0.29166667 | M56: 0.29166667 | N56: 0.29166667 | O56: 0.29166667 | P56: 0.29166667 | Q56: 0.29166667 | R56: 0.29166667 | S56: 0.29166667 | T56: 0.29166667 | U56: 0.29166667 | V56: 0.29166667 | W56: 0.29166667 | X56: 0.29166667 | Y56: 0.29166667 | Z56: 0.29166667 | AA56: 0.29166667 | AB56: 0.29166667 | AC56: 0.29166667 | AD56: 0.29166667 | AE56: 0.29166667 | AF56: 0.29166667 | AG56: 0.29166667 | AH56: 0.29166667 | AI56: 0.29166667 | AJ56: 0.29166667 | AL56: 0.29166667
A57: 56 | B57: 2025 | C57: 3 | D57: 90SL686 | E57: 31 | F57: 2 | G57: time-end | H57: 0.75 | I57: 0.75 | J57: 0.91666667 | K57: 1 | L57: 0.75 | M57: 0.75 | N57: 0.875 | O57: 1.1666667 | P57: 0.75 | Q57: 0.91666667 | R57: 0.75 | S57: 1.0833333 | T57: 0.875 | U57: 1 | V57: 0.91666667 | W57: 0.75 | X57: 0.75 | Y57: 1.1666667 | Z57: 1.0833333 | AA57: 1.1666667 | AB57: 1.0833333 | AC57: 0.91666667 | AD57: 0.75 | AE57: 0.83333333 | AF57: 0.91666667 | AG57: 1 | AH57: 0.75 | AI57: 0.91666667 | AJ57: 0.75 | AL57: 0.75 | AM57: 30 | AO57: 104
A58: 57 | B58: 2025 | C58: 3 | D58: 90SL686 | E58: 31 | F58: 2 | G58: km-start | H58: 347643 | I58: 347751 | J58: 347949 | K58: 348412 | L58: 348711 | M58: 348914 | N58: 349023 | O58: 349549 | P58: 349846 | Q58: 350047 | R58: 350650 | S58: 351005 | T58: 351513 | U58: 351958 | V58: 352406 | W58: 352699 | X58: 352862 | Y58: 353097 | Z58: 353860 | AA58: 354213 | AB58: 354552 | AC58: 354687 | AD58: 355019 | AE58: 355244 | AF58: 355563 | AG58: 355911 | AH58: 356185 | AI58: 356466 | AJ58: 356709 | AL58: 356931
A59: 58 | B59: 2025 | C59: 3 | D59: 90SL686 | E59: 31 | F59: 2 | G59: km-end | H59: 347696 | I59: 347916 | J59: 348333 | K59: 348664 | L59: 348863 | M59: 348973 | N59: 349300 | O59: 349799 | P59: 349997 | Q59: 350600 | R59: 350974 | S59: 351463 | T59: 351668 | U59: 352173 | V59: 352651 | W59: 352813 | X59: 353042 | Y59: 353671 | Z59: 353989 | AA59: 354506 | AB59: 354666 | AC59: 354958 | AD59: 355192 | AE59: 355504 | AF59: 355802 | AG59: 356132 | AH59: 356405 | AI59: 356671 | AJ59: 356868 | AL59: 357170 | AP59: 1275.12 | AQ59: 18 | AS59: 7084
A60: 59 | B60: 2025 | C60: 3 | D60: 55CB633 | E60: 31 | F60: 2 | G60: time-start | H60: 0.29166667 | J60: 0.29166667 | K60: 0.29166667 | L60: 0.29166667 | M60: 0.29166667 | N60: 0.29166667 | O60: 0.29166667 | P60: 0.29166667 | Q60: 0.29166667 | R60: 0.29166667 | S60: 0.29166667 | T60: 0.29166667 | U60: 0.29166667 | V60: 0.29166667 | W60: 0.29166667 | X60: 0.29166667 | Y60: 0.29166667 | AC60: 0.29166667 | AD60: 0.29166667 | AE60: 0.29166667 | AF60: 0.29166667 | AG60: 0.29166667 | AH60: 0.29166667 | AI60: 0.29166667 | AJ60: 0.29166667
A61: 60 | B61: 2025 | C61: 3 | D61: 55CB633 | E61: 31 | F61: 2 | G61: time-end | H61: 0.75 | J61: 0.875 | K61: 0.875 | L61: 0.75 | M61: 0.83333333 | N61: 0.75 | O61: 0.83333333 | P61: 0.75 | Q61: 0.83333333 | R61: 0.79166667 | S61: 0.75 | T61: 0.83333333 | U61: 0.79166667 | V61: 0.83333333 | W61: 0.75 | X61: 0.91666667 | Y61: 0.83333333 | AC61: 0.83333333 | AD61: 0.75 | AE61: 0.75 | AF61: 0.83333333 | AG61: 1.0833333 | AH61: 0.75 | AI61: 0.75 | AJ61: 0.75 | AM61: 25 | AO61: 36
A62: 61 | B62: 2025 | C62: 3 | D62: 55CB633 | E62: 31 | F62: 2 | G62: km-start | H62: 803060 | J62: 803233 | K62: 803288 | L62: 803367 | M62: 803396 | N62: 803512 | O62: 803609 | P62: 803742 | Q62: 803804 | R62: 803911 | S62: 804019 | T62: 804092 | U62: 804186 | V62: 804252 | W62: 804368 | X62: 804436 | Y62: 804511 | AC62: 804685 | AD62: 804794 | AE62: 804856 | AF62: 804953 | AG62: 805039 | AH62: 805124 | AI62: 805209 | AJ62: 805361
A63: 62 | B63: 2025 | C63: 3 | D63: 55CB633 | E63: 31 | F63: 2 | G63: km-end | H63: 803201 | J63: 803288 | K63: 803367 | L63: 803396 | M63: 803512 | N63: 803609 | O63: 803742 | P63: 803804 | Q63: 803911 | R63: 804019 | S63: 804092 | T63: 804186 | U63: 804252 | V63: 804368 | W63: 804436 | X63: 804511 | Y63: 804605 | AC63: 804794 | AD63: 804856 | AE63: 804953 | AF63: 805039 | AG63: 805124 | AH63: 805209 | AI63: 805361 | AJ63: 805572 | AP63: 360 | AQ63: 15 | AS63: 2400
A64: 63 | B64: 2025 | C64: 3 | D64: 77GM723 | E64: 31 | F64: 2 | G64: time-start | H64: 0.29166667 | J64: 0.29166667 | K64: 0.29166667 | L64: 0.29166667 | M64: 0.29166667 | N64: 0.29166667 | O64: 0.29166667 | P64: 0.29166667 | Q64: 0.29166667 | R64: 0.29166667 | S64: 0.29166667 | T64: 0.29166667 | U64: 0.29166667 | V64: 0.29166667 | W64: 0.29166667 | X64: 0.29166667 | Y64: 0.29166667 | Z64: 0.29166667 | AB64: 0.29166667 | AC64: 0.29166667 | AD64: 0.29166667 | AE64: 0.29166667 | AF64: 0.29166667 | AG64: 0.29166667 | AH64: 0.29166667 | AI64: 0.29166667 | AJ64: 0.29166667 | AL64: 0.29166667
A65: 64 | B65: 2025 | C65: 3 | D65: 77GM723 | E65: 31 | F65: 2 | G65: time-end | H65: 0.875 | J65: 0.875 | K65: 0.875 | L65: 0.875 | M65: 0.875 | N65: 0.875 | O65: 0.875 | P65: 0.875 | Q65: 0.875 | R65: 0.875 | S65: 0.875 | T65: 0.875 | U65: 0.875 | V65: 0.875 | W65: 0.875 | X65: 0.875 | Y65: 0.875 | Z65: 0.875 | AB65: 0.875 | AC65: 0.875 | AD65: 0.875 | AE65: 0.875 | AF65: 0.875 | AG65: 0.875 | AH65: 0.875 | AI65: 0.875 | AJ65: 0.875 | AL65: 0.75 | AM65: 28 | AO65: 81
A66: 65 | B66: 2025 | C66: 3 | D66: 77GM723 | E66: 31 | F66: 2 | G66: km-start | H66: 89287 | J66: 89531 | K66: 89765 | L66: 90040 | M66: 90246 | N66: 90457 | O66: 90750 | P66: 91010 | Q66: 91279 | R66: 91548 | S66: 91817 | T66: 92104 | U66: 92383 | V66: 92678 | W66: 92971 | X66: 93250 | Y66: 93532 | Z66: 93826 | AB66: 94003 | AC66: 94234 | AD66: 94523 | AE66: 94810 | AF66: 95086 | AG66: 95376 | AH66: 95666 | AI66: 95943 | AJ66: 96209 | AL66: 96597
A67: 66 | B67: 2025 | C67: 3 | D67: 77GM723 | E67: 31 | F67: 2 | G67: km-end | H67: 89531 | J67: 89765 | K67: 90040 | L67: 90246 | M67: 90457 | N67: 90750 | O67: 91010 | P67: 91279 | Q67: 91548 | R67: 91817 | S67: 92104 | T67: 92383 | U67: 92678 | V67: 92971 | W67: 93250 | X67: 93532 | Y67: 93826 | Z67: 94003 | AB67: 94234 | AC67: 94523 | AD67: 94810 | AE67: 95086 | AF67: 95376 | AG67: 95666 | AH67: 95943 | AI67: 96209 | AJ67: 96488 | AL67: 96768 | AP67: 1105.8 | AQ67: 15 | AS67: 7372
A68: 67 | B68: 2025 | C68: 3 | D68: 99DX531 | E68: 31 | F68: 2 | G68: time-start | H68: 0.29166667 | J68: 0.29166667 | K68: 0.29166667 | L68: 0.29166667 | M68: 0.29166667 | N68: 0.29166667 | O68: 0.29166667 | P68: 0.29166667 | Q68: 0.29166667 | R68: 0.29166667 | S68: 0.29166667 | T68: 0.29166667 | U68: 0.29166667 | V68: 0.29166667 | W68: 0.29166667 | X68: 0.29166667 | Y68: 0.29166667 | AC68: 0.29166667 | AD68: 0.29166667 | AE68: 0.29166667 | AF68: 0.29166667 | AG68: 0.29166667 | AH68: 0.29166667 | AI68: 0.29166667 | AJ68: 0.29166667 | AK68: 0.29166667 | AL68: 0.29166667
A69: 68 | B69: 2025 | C69: 3 | D69: 99DX531 | E69: 31 | F69: 2 | G69: time-end | H69: 0.83333333 | J69: 0.83333333 | K69: 0.91666667 | L69: 0.75 | M69: 0.91666667 | N69: 1.0833333 | O69: 0.83333333 | P69: 1 | Q69: 0.75 | R69: 0.79166667 | S69: 1 | T69: 0.75 | U69: 0.75 | V69: 0.75 | W69: 0.75 | X69: 0.75 | Y69: 0.75 | AC69: 0.75 | AD69: 0.75 | AE69: 0.75 | AF69: 0.75 | AG69: 0.75 | AH69: 0.75 | AI69: 0.75 | AJ69: 0.75 | AK69: 0.75 | AL69: 0.75 | AM69: 27 | AO69: 35
A70: 69 | B70: 2025 | C70: 3 | D70: 99DX531 | E70: 31 | F70: 2 | G70: km-start | H70: 705098 | J70: 705380 | K70: 705380 | L70: 705538 | M70: 705640 | N70: 705750 | O70: 705870 | P70: 705973 | Q70: 706110 | R70: 706220 | S70: 706319 | T70: 706420 | U70: 706536 | V70: 706680 | W70: 706810 | X70: 706923 | Y70: 707050 | AC70: 707620 | AD70: 707738 | AE70: 707870 | AF70: 708010 | AG70: 708132 | AH70: 708263 | AI70: 708389 | AJ70: 708520 | AK70: 708635 | AL70: 708790
A71: 70 | B71: 2025 | C71: 3 | D71: 99DX531 | E71: 31 | F71: 2 | G71: km-end | H71: 705227 | J71: 705380 | K71: 705538 | L71: 705640 | M71: 705750 | N71: 705870 | O71: 705973 | P71: 706110 | Q71: 706220 | R71: 706319 | S71: 706420 | T71: 706536 | U71: 706680 | V71: 706810 | W71: 706923 | X71: 707050 | Y71: 707286 | AC71: 707738 | AD71: 707870 | AE71: 708010 | AF71: 708132 | AG71: 708263 | AH71: 708389 | AI71: 708520 | AJ71: 708635 | AK71: 708790 | AL71: 708889 | AP71: 495.6 | AQ71: 15 | AS71: 3304
A72: 71 | B72: 2025 | C72: 3 | D72: 15BZ942 | E72: 31 | F72: 2 | G72: time-start | H72: 0.29166667 | I72: 0.29166667 | J72: 0.29166667 | K72: 0.29166667 | L72: 0.29166667 | M72: 0.29166667 | N72: 0.29166667 | O72: 0.29166667 | P72: 0.29166667 | Q72: 0.29166667 | R72: 0.29166667 | S72: 0.29166667 | T72: 0.29166667 | U72: 0.29166667 | V72: 0.29166667 | W72: 0.29166667 | X72: 0.29166667 | Y72: 0.29166667 | AA72: 0.29166667 | AB72: 0.29166667 | AC72: 0.29166667 | AD72: 0.29166667 | AE72: 0.29166667 | AF72: 0.29166667 | AG72: 0.29166667 | AH72: 0.29166667 | AI72: 0.29166667 | AJ72: 0.29166667 | AK72: 0.29166667
A73: 72 | B73: 2025 | C73: 3 | D73: 15BZ942 | E73: 31 | F73: 2 | G73: time-end | H73: 0.75 | I73: 0.75 | J73: 0.75 | K73: 0.75 | L73: 0.75 | M73: 0.75 | N73: 0.75 | O73: 1 | P73: 0.75 | Q73: 0.75 | R73: 0.875 | S73: 0.75 | T73: 0.75 | U73: 0.75 | V73: 0.75 | W73: 0.875 | X73: 0.75 | Y73: 0.75 | AA73: 0.75 | AB73: 0.75 | AC73: 0.875 | AD73: 0.75 | AE73: 0.875 | AF73: 0.75 | AG73: 1 | AH73: 0.875 | AI73: 0.75 | AJ73: 0.75 | AK73: 0.75 | AM73: 29 | AO73: 27
A74: 73 | B74: 2025 | C74: 3 | D74: 15BZ942 | E74: 31 | F74: 2 | G74: km-start | H74: 57765 | I74: 57846 | J74: 57976 | K74: 58164 | L74: 58373 | M74: 58481 | N74: 58641 | O74: 58817 | P74: 58966 | Q74: 59110 | R74: 59274 | S74: 59442 | T74: 59612 | U74: 59723 | V74: 59993 | W74: 60145 | X74: 60235 | Y74: 60409 | AA74: 60929 | AB74: 61062 | AC74: 61185 | AD74: 61258 | AE74: 61351 | AF74: 61497 | AG74: 61588 | AH74: 61669 | AI74: 61826 | AJ74: 62069 | AK74: 62206
A75: 74 | B75: 2025 | C75: 3 | D75: 15BZ942 | E75: 31 | F75: 2 | G75: km-end | H75: 57832 | I75: 57975 | J75: 58141 | K75: 58345 | L75: 58479 | M75: 58639 | N75: 58814 | O75: 58964 | P75: 59069 | Q75: 59271 | R75: 59438 | S75: 59604 | T75: 59675 | U75: 59991 | V75: 60102 | W75: 60234 | X75: 60344 | Y75: 60552 | AA75: 61060 | AB75: 61184 | AC75: 61258 | AD75: 61350 | AE75: 61496 | AF75: 61586 | AG75: 61667 | AH75: 61824 | AI75: 62067 | AJ75: 62205 | AK75: 62380 | AP75: 590.1 | AQ75: 15 | AS75: 3934
A76: 75 | B76: 2025 | C76: 3 | D76: 99BT339 | E76: 31 | F76: 2 | G76: time-start | H76: 0.29166667 | I76: 0.29166667 | J76: 0.29166667 | K76: 0.29166667 | L76: 0.29166667 | M76: 0.29166667 | N76: 0.29166667 | O76: 0.29166667 | P76: 0.29166667 | Q76: 0.29166667 | R76: 0.29166667 | S76: 0.29166667 | T76: 0.29166667 | U76: 0.29166667 | V76: 0.29166667 | W76: 0.29166667 | X76: 0.29166667 | Y76: 0.29166667 | AC76: 0.29166667 | AD76: 0.29166667 | AE76: 0.29166667 | AF76: 0.29166667 | AG76: 0.29166667 | AH76: 0.29166667 | AI76: 0.29166667 | AJ76: 0.29166667
A77: 76 | B77: 2025 | C77: 3 | D77: 99BT339 | E77: 31 | F77: 2 | G77: time-end | H77: 0.83333333 | I77: 0.83333333 | J77: 0.75 | K77: 0.83333333 | L77: 0.75 | M77: 0.83333333 | N77: 0.75 | O77: 0.83333333 | P77: 0.83333333 | Q77: 0.75 | R77: 0.83333333 | S77: 0.75 | T77: 0.75 | U77: 0.83333333 | V77: 0.75 | W77: 0.83333333 | X77: 0.83333333 | Y77: 0.75 | AC77: 0.75 | AD77: 0.83333333 | AE77: 0.75 | AF77: 0.83333333 | AG77: 0.75 | AH77: 0.83333333 | AI77: 0.83333333 | AJ77: 0.75 | AM77: 26 | AO77: 28
A78: 77 | B78: 2025 | C78: 3 | D78: 99BT339 | E78: 31 | F78: 2 | G78: km-start | H78: 343570 | I78: 343894 | J78: 344051 | K78: 344204 | L78: 344338 | M78: 344423 | N78: 344524 | O78: 344645 | P78: 344682 | Q78: 344745 | R78: 344781 | S78: 344832 | T78: 344861 | U78: 344899 | V78: 344935 | W78: 344965 | X78: 345001 | Y78: 345056 | AC78: 345591 | AD78: 345719 | AE78: 345862 | AF78: 346005 | AG78: 346132 | AH78: 346292 | AI78: 346420 | AJ78: 346554
A79: 78 | B79: 2025 | C79: 3 | D79: 99BT339 | E79: 31 | F79: 2 | G79: km-end | H79: 343754 | I79: 344048 | J79: 344202 | K79: 344338 | L79: 344422 | M79: 344524 | N79: 344620 | O79: 344682 | P79: 344745 | Q79: 344779 | R79: 344832 | S79: 344861 | T79: 344899 | U79: 344935 | V79: 344965 | W79: 345001 | X79: 345056 | Y79: 345241 | AC79: 345718 | AD79: 345848 | AE79: 346005 | AF79: 346132 | AG79: 346280 | AH79: 346420 | AI79: 346554 | AJ79: 346678 | AP79: 383.7 | AQ79: 15 | AS79: 2558
A80: 79 | B80: 2025 | C80: 3 | D80: 77ET143 | E80: 31 | F80: 2 | G80: time-start | H80: 0.29166667 | J80: 0.29166667 | K80: 0.29166667 | L80: 0.29166667 | M80: 0.29166667 | N80: 0.29166667 | O80: 0.29166667 | P80: 0.29166667 | Q80: 0.29166667 | R80: 0.29166667 | S80: 0.29166667 | T80: 0.29166667 | U80: 0.29166667 | V80: 0.29166667 | W80: 0.29166667 | X80: 0.29166667 | Y80: 0.29166667 | AC80: 0.29166667 | AD80: 0.29166667 | AE80: 0.29166667 | AF80: 0.29166667 | AG80: 0.29166667 | AH80: 0.29166667 | AI80: 0.29166667 | AJ80: 0.29166667
A81: 80 | B81: 2025 | C81: 3 | D81: 77ET143 | E81: 31 | F81: 2 | G81: time-end | H81: 0.75 | J81: 0.75 | K81: 0.75 | L81: 0.75 | M81: 0.75 | N81: 0.75 | O81: 0.75 | P81: 0.75 | Q81: 0.75 | R81: 0.75 | S81: 0.75 | T81: 0.75 | U81: 0.75 | V81: 0.75 | W81: 0.75 | X81: 0.75 | Y81: 0.75 | AC81: 0.75 | AD81: 0.75 | AE81: 0.75 | AF81: 0.75 | AG81: 0.75 | AH81: 0.75 | AI81: 0.75 | AJ81: 0.75 | AM81: 25
A82: 81 | B82: 2025 | C82: 3 | D82: 77ET143 | E82: 31 | F82: 2 | G82: km-start | H82: 880125 | J82: 880287 | K82: 880394 | L82: 880480 | M82: 880550 | N82: 880664 | O82: 880771 | P82: 880831 | Q82: 881002 | R82: 881050 | S82: 881085 | T82: 881149 | U82: 881223 | V82: 881301 | W82: 881376 | X82: 881481 | Y82: 881530 | AC82: 881608 | AD82: 881688 | AE82: 881766 | AF82: 881811 | AG82: 881860 | AH82: 881916 | AI82: 881982 | AJ82: 882055
A83: 82 | B83: 2025 | C83: 3 | D83: 77ET143 | E83: 31 | F83: 2 | G83: km-end | H83: 880245 | J83: 880394 | K83: 880480 | L83: 880550 | M83: 880664 | N83: 880771 | O83: 880831 | P83: 880929 | Q83: 881050 | R83: 881085 | S83: 881149 | T83: 881223 | U83: 881301 | V83: 881376 | W83: 881481 | X83: 881530 | Y83: 881574 | AC83: 881688 | AD83: 881766 | AE83: 881811 | AF83: 881860 | AG83: 881916 | AH83: 881982 | AI83: 882055 | AJ83: 882130 | AP83: 278.4 | AQ83: 15 | AS83: 1856
A84: 83 | B84: 2025 | C84: 3 | D84: 50DK730 | E84: 31 | F84: 2 | G84: time-start | H84: 0.29166667 | I84: 0.29166667 | J84: 0.29166667 | K84: 0.29166667 | L84: 0.29166667 | M84: 0.29166667 | N84: 0.29166667 | O84: 0.29166667 | P84: 0.29166667 | Q84: 0.29166667 | R84: 0.29166667 | S84: 0.29166667 | T84: 0.29166667 | U84: 0.29166667 | V84: 0.29166667 | W84: 0.29166667 | X84: 0.29166667 | Y84: 0.29166667 | AA84: 0.29166667 | AC84: 0.29166667 | AD84: 0.29166667 | AE84: 0.29166667 | AF84: 0.29166667 | AG84: 0.29166667 | AH84: 0.29166667 | AI84: 0.29166667 | AJ84: 0.29166667 | AK84: 0.29166667
A85: 84 | B85: 2025 | C85: 3 | D85: 50DK730 | E85: 31 | F85: 2 | G85: time-end | H85: 0.875 | I85: 0.875 | J85: 0.875 | K85: 0.875 | L85: 0.875 | M85: 0.875 | N85: 0.875 | O85: 0.875 | P85: 0.875 | Q85: 0.875 | R85: 0.875 | S85: 0.875 | T85: 0.875 | U85: 0.875 | V85: 0.875 | W85: 0.875 | X85: 0.875 | Y85: 0.875 | AA85: 0.875 | AC85: 0.875 | AD85: 0.875 | AE85: 0.875 | AF85: 0.875 | AG85: 0.875 | AH85: 0.875 | AI85: 0.875 | AJ85: 0.875 | AK85: 0.79166667 | AM85: 28 | AO85: 82
A86: 85 | B86: 2025 | C86: 3 | D86: 50DK730 | E86: 31 | F86: 2 | G86: km-start | H86: 87703 | I86: 87951 | J86: 88163 | K86: 88331 | L86: 88613 | M86: 88835 | N86: 89080 | O86: 89321 | P86: 89597 | Q86: 89848 | R86: 90102 | S86: 90343 | T86: 90553 | U86: 90788 | V86: 91035 | W86: 91310 | X86: 91630 | Y86: 91973 | AA86: 92342 | AC86: 93012 | AD86: 93246 | AE86: 93570 | AF86: 93804 | AG86: 94053 | AH86: 94303 | AI86: 94541 | AJ86: 94809 | AK86: 95046
A87: 86 | B87: 2025 | C87: 3 | D87: 50DK730 | E87: 31 | F87: 2 | G87: km-end | H87: 87951 | I87: 88163 | J87: 88331 | K87: 88613 | L87: 88835 | M87: 89080 | N87: 89321 | O87: 89597 | P87: 89848 | Q87: 90102 | R87: 90343 | S87: 90553 | T87: 90788 | U87: 91035 | V87: 91310 | W87: 91630 | X87: 91973 | Y87: 92312 | AA87: 92774 | AC87: 93246 | AD87: 93570 | AE87: 93804 | AF87: 94053 | AG87: 94303 | AH87: 94541 | AI87: 94809 | AJ87: 95046 | AK87: 95332 | AP87: 1104.15 | AQ87: 15 | AS87: 7361
A88: 87 | B88: 2025 | C88: 3 | D88: 99MN472 | E88: 31 | F88: 2 | G88: time-start | H88: 0.29166667 | I88: 0.29166667 | J88: 0.29166667 | K88: 0.29166667 | L88: 0.29166667 | M88: 0.29166667 | N88: 0.29166667 | O88: 0.29166667 | P88: 0.29166667 | Q88: 0.29166667 | R88: 0.29166667 | S88: 0.29166667 | T88: 0.29166667 | U88: 0.29166667 | V88: 0.29166667 | W88: 0.29166667 | X88: 0.29166667 | Y88: 0.29166667 | AA88: 0.29166667 | AB88: 0.29166667 | AC88: 0.29166667 | AD88: 0.29166667 | AE88: 0.29166667 | AF88: 0.29166667 | AG88: 0.29166667 | AH88: 0.29166667 | AI88: 0.29166667 | AJ88: 0.29166667 | AL88: 0.29166667
A89: 88 | B89: 2025 | C89: 3 | D89: 99MN472 | E89: 31 | F89: 2 | G89: time-end | H89: 0.83333333 | I89: 0.83333333 | J89: 0.83333333 | K89: 0.83333333 | L89: 0.83333333 | M89: 0.83333333 | N89: 0.83333333 | O89: 0.83333333 | P89: 0.83333333 | Q89: 0.83333333 | R89: 0.83333333 | S89: 0.83333333 | T89: 0.83333333 | U89: 0.83333333 | V89: 0.83333333 | W89: 0.83333333 | X89: 0.83333333 | Y89: 0.83333333 | AA89: 0.75 | AB89: 0.875 | AC89: 0.83333333 | AD89: 0.83333333 | AE89: 0.83333333 | AF89: 0.83333333 | AG89: 0.83333333 | AH89: 0.83333333 | AI89: 0.83333333 | AJ89: 0.83333333 | AL89: 0.75 | AM89: 29 | AO89: 55
A90: 89 | B90: 2025 | C90: 3 | D90: 99MN472 | E90: 31 | F90: 2 | G90: km-start | H90: 303032 | I90: 303135 | J90: 303268 | K90: 303498 | L90: 303623 | M90: 303750 | N90: 303956 | O90: 304091 | P90: 304262 | Q90: 304459 | R90: 304574 | S90: 304747 | T90: 304861 | U90: 305021 | V90: 305172 | W90: 305359 | X90: 305548 | Y90: 305660 | AA90: 305944 | AB90: 306200 | AC90: 306325 | AD90: 306485 | AE90: 306595 | AF90: 306809 | AG90: 306941 | AH90: 307115 | AI90: 307229 | AJ90: 307427 | AL90: 307776
A91: 90 | B91: 2025 | C91: 3 | D91: 99MN472 | E91: 31 | F91: 2 | G91: km-end | H91: 303135 | I91: 303268 | J91: 303498 | K91: 303623 | L91: 303750 | M91: 303956 | N91: 304091 | O91: 304262 | P91: 304459 | Q91: 304574 | R91: 304747 | S91: 304861 | T91: 305021 | U91: 305172 | V91: 305359 | W91: 305548 | X91: 305660 | Y91: 305785 | AA91: 306054 | AB91: 306325 | AC91: 306485 | AD91: 306595 | AE91: 306809 | AF91: 306941 | AG91: 307115 | AH91: 307229 | AI91: 307427 | AJ91: 307537 | AL91: 307886 | AP91: 646.5 | AQ91: 15 | AS91: 4310
A92: 91 | B92: 2025 | C92: 3 | D92: 52BK688 | E92: 31 | F92: 2 | G92: time-start | L92: 0.29166667 | M92: 0.29166667 | N92: 0.29166667 | O92: 0.29166667 | P92: 0.29166667 | Q92: 0.29166667 | R92: 0.29166667 | S92: 0.29166667 | T92: 0.29166667 | U92: 0.29166667 | V92: 0.29166667 | W92: 0.29166667 | X92: 0.29166667 | Y92: 0.29166667 | Z92: 0.29166667 | AB92: 0.29166667 | AC92: 0.29166667 | AD92: 0.29166667 | AE92: 0.29166667 | AF92: 0.29166667 | AG92: 0.29166667 | AH92: 0.29166667 | AI92: 0.29166667 | AJ92: 0.29166667 | AL92: 0.29166667
A93: 92 | B93: 2025 | C93: 3 | D93: 52BK688 | E93: 31 | F93: 2 | G93: time-end | L93: 0.75 | M93: 0.75 | N93: 0.75 | O93: 0.75 | P93: 0.75 | Q93: 0.75 | R93: 0.75 | S93: 0.75 | T93: 0.75 | U93: 0.75 | V93: 0.75 | W93: 0.75 | X93: 0.75 | Y93: 0.75 | Z93: 0.75 | AB93: 0.75 | AC93: 0.75 | AD93: 0.75 | AE93: 0.75 | AF93: 0.75 | AG93: 0.75 | AH93: 0.75 | AI93: 0.75 | AJ93: 0.75 | AL93: 0.75 | AM93: 25
A94: 93 | B94: 2025 | C94: 3 | D94: 52BK688 | E94: 31 | F94: 2 | G94: km-start | L94: 816508 | M94: 816732 | N94: 816959 | O94: 817190 | P94: 817397 | Q94: 817631 | R94: 817857 | S94: 818095 | T94: 818337 | U94: 818560 | V94: 818744 | W94: 818968 | X94: 819195 | Y94: 819426 | Z94: 819647 | AB94: 819952 | AC94: 820125 | AD94: 820267 | AE94: 820419 | AF94: 820645 | AG94: 820858 | AH94: 821082 | AI94: 821301 | AJ94: 821524 | AL94: 821830
A95: 94 | B95: 2025 | C95: 3 | D95: 52BK688 | E95: 31 | F95: 2 | G95: km-end | L95: 816732 | M95: 816959 | N95: 817190 | O95: 817397 | P95: 817631 | Q95: 817857 | R95: 818095 | S95: 818337 | T95: 818560 | U95: 818744 | V95: 818968 | W95: 819195 | X95: 819426 | Y95: 819647 | Z95: 819828 | AB95: 820125 | AC95: 820267 | AD95: 820419 | AE95: 820645 | AF95: 820858 | AG95: 821082 | AH95: 821301 | AI95: 821524 | AJ95: 821728 | AL95: 821994 | AP95: 789 | AQ95: 15 | AS95: 5260
A96: 95 | B96: 2025 | C96: 3 | D96: 10RN527 | E96: 31 | F96: 2 | G96: time-start | Q96: 0.29166667 | R96: 0.29166667 | S96: 0.29166667 | T96: 0.29166667 | U96: 0.29166667 | V96: 0.29166667 | W96: 0.29166667 | X96: 0.29166667 | Y96: 0.29166667 | AC96: 0.29166667 | AD96: 0.29166667 | AE96: 0.29166667 | AF96: 0.29166667 | AG96: 0.29166667 | AH96: 0.29166667 | AI96: 0.29166667 | AJ96: 0.29166667 | AK96: 0.29166667
A97: 96 | B97: 2025 | C97: 3 | D97: 10RN527 | E97: 31 | F97: 2 | G97: time-end | Q97: 0.75 | R97: 0.75 | S97: 0.75 | T97: 0.75 | U97: 0.75 | V97: 0.875 | W97: 0.83333333 | X97: 0.79166667 | Y97: 0.83333333 | AC97: 0.875 | AD97: 0.83333333 | AE97: 0.75 | AF97: 1.0416667 | AG97: 1.0416667 | AH97: 1.0416667 | AI97: 0.75 | AJ97: 0.75 | AK97: 0.75 | AM97: 18 | AO97: 34
A98: 97 | B98: 2025 | C98: 3 | D98: 10RN527 | E98: 31 | F98: 2 | G98: km-start | Q98: 358552 | R98: 358630 | S98: 358715 | T98: 358803 | U98: 358853 | V98: 358922 | W98: 359017 | X98: 359125 | Y98: 359289 | AC98: 359481 | AD98: 359675 | AE98: 359818 | AF98: 359894 | AG98: 359976 | AH98: 360089 | AI98: 360237 | AJ98: 360374 | AK98: 360496
A99: 98 | B99: 2025 | C99: 3 | D99: 10RN527 | E99: 31 | F99: 2 | G99: km-end | Q99: 358630 | R99: 358715 | S99: 358803 | T99: 358853 | U99: 358922 | V99: 359017 | W99: 359125 | X99: 359289 | Y99: 359481 | AC99: 359675 | AD99: 359818 | AE99: 359894 | AF99: 359976 | AG99: 360089 | AH99: 360237 | AI99: 360374 | AJ99: 360496 | AK99: 360605 | AP99: 307.95 | AQ99: 15 | AS99: 2053
A100: 99 | B100: 2025 | C100: 3 | D100: 77RN868 | E100: 31 | F100: 2 | G100: time-start | T100: 0.29166667 | U100: 0.29166667 | V100: 0.29166667 | W100: 0.29166667 | X100: 0.29166667 | Y100: 0.29166667 | AG100: 0.29166667 | AH100: 0.29166667 | AI100: 0.29166667 | AJ100: 0.29166667
...

Sheet log_ipcs
A1: # | B1: ID | C1: contract no | D1: no | E1: start | F1: end | G1: Name | H1: Calculated | I1: Deduction | J1: IPC log | K1: Diff | M1: actual
A2: {=_xlfn.SEQUENCE(COUNTA(B:B)-1)} -> 1 | B2: {=_xlfn.DROP(_xlfn.UNIQUE(TEXT(_xlfn._TRO_TRAILING(quantities!D:D),"000")&"-"&TEXT(_xlfn._TRO_TRAILING(quantities!E:E),"000")),1)} -> 030-001 | C2: {=_xlfn.NUMBERVALUE(LEFT(_xlfn.ANCHORARRAY(B2),FIND("-",_xlfn.ANCHORARRAY(B2))-1))} -> 30 | D2: {=_xlfn.NUMBERVALUE(MID(_xlfn.ANCHORARRAY(B2),FIND("-",_xlfn.ANCHORARRAY(B2))+1,4))} -> 1 | E2: {=_xlfn.XLOOKUP(B2,old_ipc_dates!F:F,old_ipc_dates!B:B,IF(D2=1,_xlfn.XLOOKUP(C2,log_contracts!B:B,log_contracts!D:D,,0),_xlfn.XLOOKUP(1,($C1:C$18=C2)*($D1:D$18=D2-1),$F1:F$18+1,,0)),0)} -> 45658 | F2: =_xlfn.XLOOKUP(B2,old_ipc_dates!F:F,old_ipc_dates!C:C,EOMONTH(E2,0),0) -> 45688 | G2: {=_xlfn.XLOOKUP(_xlfn.ANCHORARRAY(C2),log_contracts!B:B,log_contracts!E:E,,0)} -> NAR TRANSPORT SERVICES MMC | H2: {=SUM(_xlfn._xlws.FILTER(_xlfn._TRO_TRAILING(quantities!L:L),(_xlfn._TRO_TRAILING(quantities!D:D)=C2)*(_xlfn._TRO_TRAILING(quantities!E:E)=D2)))} -> 1833.3333 | J2: =SUMIFS( INDIRECT("'[S2 Subcon IPC Log.xlsx]Subcon IPC Log'!"&"$O:$O"), INDIRECT("'[S2 Subcon IPC Log.xlsx]Subcon IPC Log'!"&"$C:$C"), "KLN-SPP2-"&_xlfn.XLOOKUP(C2,log_contracts!B:B,log_contracts!C:C)&"-"&TEXT(C2,"000"), INDIRECT("'[S2 Subcon IPC Log.xlsx]Subcon IPC Log'!"&"$D:$D"), "<="&D2) -> #REF! | K2: {=ROUND(_xlfn.DROP(_xlfn._TRO_TRAILING(H:H)-_xlfn._TRO_TRAILING(J:J),1),0)} -> #REF!
A3: 2 | B3: 031-001 | C3: 31 | D3: 1 | E3: {=_xlfn.XLOOKUP(B3,old_ipc_dates!F:F,old_ipc_dates!B:B,IF(D3=1,_xlfn.XLOOKUP(C3,log_contracts!B:B,log_contracts!D:D,,0),_xlfn.XLOOKUP(1,($C2:C$18=C3)*($D2:D$18=D3-1),$F2:F$18+1,,0)),0)} -> 45693 | F3: =_xlfn.XLOOKUP(B3,old_ipc_dates!F:F,old_ipc_dates!C:C,EOMONTH(E3,0),0) -> 45716 | G3: NAR TRANSPORT SERVICES MMC | H3: {=SUM(_xlfn._xlws.FILTER(_xlfn._TRO_TRAILING(quantities!L:L),(_xlfn._TRO_TRAILING(quantities!D:D)=C3)*(_xlfn._TRO_TRAILING(quantities!E:E)=D3)))} -> 11283.422 | J3: =SUMIFS( INDIRECT("'[S2 Subcon IPC Log.xlsx]Subcon IPC Log'!"&"$O:$O"), INDIRECT("'[S2 Subcon IPC Log.xlsx]Subcon IPC Log'!"&"$C:$C"), "KLN-SPP2-"&_xlfn.XLOOKUP(C3,log_contracts!B:B,log_contracts!C:C)&"-"&TEXT(C3,"000"), INDIRECT("'[S2 Subcon IPC Log.xlsx]Subcon IPC Log'!"&"$D:$D"), D3) -> #REF! | K3: #REF!
A4: 3 | B4: 046-001 | C4: 46 | D4: 1 | E4: {=_xlfn.XLOOKUP(B4,old_ipc_dates!F:F,old_ipc_dates!B:B,IF(D4=1,_xlfn.XLOOKUP(C4,log_contracts!B:B,log_contracts!D:D,,0),_xlfn.XLOOKUP(1,($C3:C$18=C4)*($D3:D$18=D4-1),$F3:F$18+1,,0)),0)} -> 45778 | F4: =_xlfn.XLOOKUP(B4,old_ipc_dates!F:F,old_ipc_dates!C:C,EOMONTH(E4,0),0) -> 45808 | G4: HARDCORE CONSTRUCTION AND EQUIPMENT | H4: {=SUM(_xlfn._xlws.FILTER(_xlfn._TRO_TRAILING(quantities!L:L),(_xlfn._TRO_TRAILING(quantities!D:D)=C4)*(_xlfn._TRO_TRAILING(quantities!E:E)=D4)))} -> 1714.2857 | J4: =SUMIFS( INDIRECT("'[S2 Subcon IPC Log.xlsx]Subcon IPC Log'!"&"$O:$O"), INDIRECT("'[S2 Subcon IPC Log.xlsx]Subcon IPC Log'!"&"$C:$C"), "KLN-SPP2-"&_xlfn.XLOOKUP(C4,log_contracts!B:B,log_contracts!C:C)&"-"&TEXT(C4,"000"), INDIRECT("'[S2 Subcon IPC Log.xlsx]Subcon IPC Log'!"&"$D:$D"), D4) -> #REF! | K4: #REF!
A5: 4 | B5: 050-001 | C5: 50 | D5: 1 | E5: {=_xlfn.XLOOKUP(B5,old_ipc_dates!F:F,old_ipc_dates!B:B,IF(D5=1,_xlfn.XLOOKUP(C5,log_contracts!B:B,log_contracts!D:D,,0),_xlfn.XLOOKUP(1,($C4:C$18=C5)*($D4:D$18=D5-1),$F4:F$18+1,,0)),0)} -> 45809 | F5: =_xlfn.XLOOKUP(B5,old_ipc_dates!F:F,old_ipc_dates!C:C,EOMONTH(E5,0),0) -> 45838 | G5: LOFT CONSTRUCTION | H5: {=SUM(_xlfn._xlws.FILTER(_xlfn._TRO_TRAILING(quantities!L:L),(_xlfn._TRO_TRAILING(quantities!D:D)=C5)*(_xlfn._TRO_TRAILING(quantities!E:E)=D5)))} -> 8750 | J5: =SUMIFS( INDIRECT("'[S2 Subcon IPC Log.xlsx]Subcon IPC Log'!"&"$O:$O"), INDIRECT("'[S2 Subcon IPC Log.xlsx]Subcon IPC Log'!"&"$C:$C"), "KLN-SPP2-"&_xlfn.XLOOKUP(C5,log_contracts!B:B,log_contracts!C:C)&"-"&TEXT(C5,"000"), INDIRECT("'[S2 Subcon IPC Log.xlsx]Subcon IPC Log'!"&"$D:$D"), D5) -> #REF! | K5: #REF!
A6: 5 | B6: 051-001 | C6: 51 | D6: 1 | E6: {=_xlfn.XLOOKUP(B6,old_ipc_dates!F:F,old_ipc_dates!B:B,IF(D6=1,_xlfn.XLOOKUP(C6,log_contracts!B:B,log_contracts!D:D,,0),_xlfn.XLOOKUP(1,($C5:C$18=C6)*($D5:D$18=D6-1),$F5:F$18+1,,0)),0)} -> 45761 | F6: =_xlfn.XLOOKUP(B6,old_ipc_dates!F:F,old_ipc_dates!C:C,EOMONTH(E6,0),0) -> 45777 | G6: INTERMAK GROUP MMC | H6: {=SUM(_xlfn._xlws.FILTER(_xlfn._TRO_TRAILING(quantities!L:L),(_xlfn._TRO_TRAILING(quantities!D:D)=C6)*(_xlfn._TRO_TRAILING(quantities!E:E)=D6)))} -> 3700 | J6: =SUMIFS( INDIRECT("'[S2 Subcon IPC Log.xlsx]Subcon IPC Log'!"&"$O:$O"), INDIRECT("'[S2 Subcon IPC Log.xlsx]Subcon IPC Log'!"&"$C:$C"), "KLN-SPP2-"&_xlfn.XLOOKUP(C6,log_contracts!B:B,log_contracts!C:C)&"-"&TEXT(C6,"000"), INDIRECT("'[S2 Subcon IPC Log.xlsx]Subcon IPC Log'!"&"$D:$D"), D6) -> #REF! | K6: #REF!
A7: 6 | B7: 052-001 | C7: 52 | D7: 1 | E7: {=_xlfn.XLOOKUP(B7,old_ipc_dates!F:F,old_ipc_dates!B:B,IF(D7=1,_xlfn.XLOOKUP(C7,log_contracts!B:B,log_contracts!D:D,,0),_xlfn.XLOOKUP(1,($C6:C$18=C7)*($D6:D$18=D7-1),$F6:F$18+1,,0)),0)} -> 45762 | F7: =_xlfn.XLOOKUP(B7,old_ipc_dates!F:F,old_ipc_dates!C:C,EOMONTH(E7,0),0) -> 45777 | G7: DTS MMC | H7: {=SUM(_xlfn._xlws.FILTER(_xlfn._TRO_TRAILING(quantities!L:L),(_xlfn._TRO_TRAILING(quantities!D:D)=C7)*(_xlfn._TRO_TRAILING(quantities!E:E)=D7)))} -> 6262.5 | J7: =SUMIFS( INDIRECT("'[S2 Subcon IPC Log.xlsx]Subcon IPC Log'!"&"$O:$O"), INDIRECT("'[S2 Subcon IPC Log.xlsx]Subcon IPC Log'!"&"$C:$C"), "KLN-SPP2-"&_xlfn.XLOOKUP(C7,log_contracts!B:B,log_contracts!C:C)&"-"&TEXT(C7,"000"), INDIRECT("'[S2 Subcon IPC Log.xlsx]Subcon IPC Log'!"&"$D:$D"), D7) -> #REF! | K7: #REF!
A8: 7 | B8: 065-001 | C8: 65 | D8: 1 | E8: {=_xlfn.XLOOKUP(B8,old_ipc_dates!F:F,old_ipc_dates!B:B,IF(D8=1,_xlfn.XLOOKUP(C8,log_contracts!B:B,log_contracts!D:D,,0),_xlfn.XLOOKUP(1,($C7:C$18=C8)*($D7:D$18=D8-1),$F7:F$18+1,,0)),0)} -> 45778 | F8: =_xlfn.XLOOKUP(B8,old_ipc_dates!F:F,old_ipc_dates!C:C,EOMONTH(E8,0),0) -> 45808 | G8: ETIBAR MAMMADOV | H8: {=SUM(_xlfn._xlws.FILTER(_xlfn._TRO_TRAILING(quantities!L:L),(_xlfn._TRO_TRAILING(quantities!D:D)=C8)*(_xlfn._TRO_TRAILING(quantities!E:E)=D8)))} -> 8446.3343 | J8: =SUMIFS( INDIRECT("'[S2 Subcon IPC Log.xlsx]Subcon IPC Log'!"&"$O:$O"), INDIRECT("'[S2 Subcon IPC Log.xlsx]Subcon IPC Log'!"&"$C:$C"), "KLN-SPP2-"&_xlfn.XLOOKUP(C8,log_contracts!B:B,log_contracts!C:C)&"-"&TEXT(C8,"000"), INDIRECT("'[S2 Subcon IPC Log.xlsx]Subcon IPC Log'!"&"$D:$D"), D8) -> #REF! | K8: #REF!
A9: 8 | B9: 085-001 | C9: 85 | D9: 1 | E9: {=_xlfn.XLOOKUP(B9,old_ipc_dates!F:F,old_ipc_dates!B:B,IF(D9=1,_xlfn.XLOOKUP(C9,log_contracts!B:B,log_contracts!D:D,,0),_xlfn.XLOOKUP(1,($C8:C$18=C9)*($D8:D$18=D9-1),$F8:F$18+1,,0)),0)} -> 45824 | F9: =_xlfn.XLOOKUP(B9,old_ipc_dates!F:F,old_ipc_dates!C:C,EOMONTH(E9,0),0) -> 45838 | G9: BABEK ALBANDOV | H9: {=SUM(_xlfn._xlws.FILTER(_xlfn._TRO_TRAILING(quantities!L:L),(_xlfn._TRO_TRAILING(quantities!D:D)=C9)*(_xlfn._TRO_TRAILING(quantities!E:E)=D9)))} -> 7857.168 | J9: =SUMIFS( INDIRECT("'[S2 Subcon IPC Log.xlsx]Subcon IPC Log'!"&"$O:$O"), INDIRECT("'[S2 Subcon IPC Log.xlsx]Subcon IPC Log'!"&"$C:$C"), "KLN-SPP2-"&_xlfn.XLOOKUP(C9,log_contracts!B:B,log_contracts!C:C)&"-"&TEXT(C9,"000"), INDIRECT("'[S2 Subcon IPC Log.xlsx]Subcon IPC Log'!"&"$D:$D"), D9) -> #REF! | K9: #REF!
A10: 9 | B10: 094-001 | C10: 94 | D10: 1 | E10: {=_xlfn.XLOOKUP(B10,old_ipc_dates!F:F,old_ipc_dates!B:B,IF(D10=1,_xlfn.XLOOKUP(C10,log_contracts!B:B,log_contracts!D:D,,0),_xlfn.XLOOKUP(1,($C9:C$18=C10)*($D9:D$18=D10-1),$F9:F$18+1,,0)),0)} -> 45809 | F10: =_xlfn.XLOOKUP(B10,old_ipc_dates!F:F,old_ipc_dates!C:C,EOMONTH(E10,0),0) -> 45838 | G10: XANIM ABDULLAYEVA | H10: {=SUM(_xlfn._xlws.FILTER(_xlfn._TRO_TRAILING(quantities!L:L),(_xlfn._TRO_TRAILING(quantities!D:D)=C10)*(_xlfn._TRO_TRAILING(quantities!E:E)=D10)))} -> 3500 | J10: =SUMIFS( INDIRECT("'[S2 Subcon IPC Log.xlsx]Subcon IPC Log'!"&"$O:$O"), INDIRECT("'[S2 Subcon IPC Log.xlsx]Subcon IPC Log'!"&"$C:$C"), "KLN-SPP2-"&_xlfn.XLOOKUP(C10,log_contracts!B:B,log_contracts!C:C)&"-"&TEXT(C10,"000"), INDIRECT("'[S2 Subcon IPC Log.xlsx]Subcon IPC Log'!"&"$D:$D"), D10) -> #REF! | K10: #REF!
A11: 10 | B11: 095-001 | C11: 95 | D11: 1 | E11: {=_xlfn.XLOOKUP(B11,old_ipc_dates!F:F,old_ipc_dates!B:B,IF(D11=1,_xlfn.XLOOKUP(C11,log_contracts!B:B,log_contracts!D:D,,0),_xlfn.XLOOKUP(1,($C10:C$18=C11)*($D10:D$18=D11-1),$F10:F$18+1,,0)),0)} -> 45851 | F11: =_xlfn.XLOOKUP(B11,old_ipc_dates!F:F,old_ipc_dates!C:C,EOMONTH(E11,0),0) -> 45869 | G11: IBRAHIM XALILOV | H11: {=SUM(_xlfn._xlws.FILTER(_xlfn._TRO_TRAILING(quantities!L:L),(_xlfn._TRO_TRAILING(quantities!D:D)=C11)*(_xlfn._TRO_TRAILING(quantities!E:E)=D11)))} -> 4714.215 | J11: =SUMIFS( INDIRECT("'[S2 Subcon IPC Log.xlsx]Subcon IPC Log'!"&"$O:$O"), INDIRECT("'[S2 Subcon IPC Log.xlsx]Subcon IPC Log'!"&"$C:$C"), "KLN-SPP2-"&_xlfn.XLOOKUP(C11,log_contracts!B:B,log_contracts!C:C)&"-"&TEXT(C11,"000"), INDIRECT("'[S2 Subcon IPC Log.xlsx]Subcon IPC Log'!"&"$D:$D"), D11) -> #REF! | K11: #REF!
A12: 11 | B12: 098-001 | C12: 98 | D12: 1 | E12: {=_xlfn.XLOOKUP(B12,old_ipc_dates!F:F,old_ipc_dates!B:B,IF(D12=1,_xlfn.XLOOKUP(C12,log_contracts!B:B,log_contracts!D:D,,0),_xlfn.XLOOKUP(1,($C11:C$18=C12)*($D11:D$18=D12-1),$F11:F$18+1,,0)),0)} -> 45858 | F12: =_xlfn.XLOOKUP(B12,old_ipc_dates!F:F,old_ipc_dates!C:C,EOMONTH(E12,0),0) -> 45869 | G12: HACIAGA KERIMOV | H12: {=SUM(_xlfn._xlws.FILTER(_xlfn._TRO_TRAILING(quantities!L:L),(_xlfn._TRO_TRAILING(quantities!D:D)=C12)*(_xlfn._TRO_TRAILING(quantities!E:E)=D12)))} -> 1285.68 | J12: =SUMIFS( INDIRECT("'[S2 Subcon IPC Log.xlsx]Subcon IPC Log'!"&"$O:$O"), INDIRECT("'[S2 Subcon IPC Log.xlsx]Subcon IPC Log'!"&"$C:$C"), "KLN-SPP2-"&_xlfn.XLOOKUP(C12,log_contracts!B:B,log_contracts!C:C)&"-"&TEXT(C12,"000"), INDIRECT("'[S2 Subcon IPC Log.xlsx]Subcon IPC Log'!"&"$D:$D"), D12) -> #REF! | K12: #REF!
A13: 12 | B13: 099-001 | C13: 99 | D13: 1 | E13: {=_xlfn.XLOOKUP(B13,old_ipc_dates!F:F,old_ipc_dates!B:B,IF(D13=1,_xlfn.XLOOKUP(C13,log_contracts!B:B,log_contracts!D:D,,0),_xlfn.XLOOKUP(1,($C12:C$18=C13)*($D12:D$18=D13-1),$F12:F$18+1,,0)),0)} -> 45859 | F13: =_xlfn.XLOOKUP(B13,old_ipc_dates!F:F,old_ipc_dates!C:C,EOMONTH(E13,0),0) -> 45869 | G13: YUSIF MAHARRAMOV | H13: {=SUM(_xlfn._xlws.FILTER(_xlfn._TRO_TRAILING(quantities!L:L),(_xlfn._TRO_TRAILING(quantities!D:D)=C13)*(_xlfn._TRO_TRAILING(quantities!E:E)=D13)))} -> 1250 | J13: =SUMIFS( INDIRECT("'[S2 Subcon IPC Log.xlsx]Subcon IPC Log'!"&"$O:$O"), INDIRECT("'[S2 Subcon IPC Log.xlsx]Subcon IPC Log'!"&"$C:$C"), "KLN-SPP2-"&_xlfn.XLOOKUP(C13,log_contracts!B:B,log_contracts!C:C)&"-"&TEXT(C13,"000"), INDIRECT("'[S2 Subcon IPC Log.xlsx]Subcon IPC Log'!"&"$D:$D"), D13) -> #REF! | K13: #REF!
A14: 13 | B14: 100-001 | C14: 100 | D14: 1 | E14: {=_xlfn.XLOOKUP(B14,old_ipc_dates!F:F,old_ipc_dates!B:B,IF(D14=1,_xlfn.XLOOKUP(C14,log_contracts!B:B,log_contracts!D:D,,0),_xlfn.XLOOKUP(1,($C13:C$18=C14)*($D13:D$18=D14-1),$F13:F$18+1,,0)),0)} -> 45861 | F14: =_xlfn.XLOOKUP(B14,old_ipc_dates!F:F,old_ipc_dates!C:C,EOMONTH(E14,0),0) -> 45869 | G14: RUSLAN HUSEYNOV | H14: {=SUM(_xlfn._xlws.FILTER(_xlfn._TRO_TRAILING(quantities!L:L),(_xlfn._TRO_TRAILING(quantities!D:D)=C14)*(_xlfn._TRO_TRAILING(quantities!E:E)=D14)))} -> 1767.8571 | J14: =SUMIFS( INDIRECT("'[S2 Subcon IPC Log.xlsx]Subcon IPC Log'!"&"$O:$O"), INDIRECT("'[S2 Subcon IPC Log.xlsx]Subcon IPC Log'!"&"$C:$C"), "KLN-SPP2-"&_xlfn.XLOOKUP(C14,log_contracts!B:B,log_contracts!C:C)&"-"&TEXT(C14,"000"), INDIRECT("'[S2 Subcon IPC Log.xlsx]Subcon IPC Log'!"&"$D:$D"), D14) -> #REF! | K14: #REF!
... A19: 18 | B19: 163-001 | C19: 163 | D19: 1 | E19: {=_xlfn.XLOOKUP(B19,old_ipc_dates!F:F,old_ipc_dates!B:B,IF(D19=1,_xlfn.XLOOKUP(C19,log_contracts!B:B,log_contracts!D:D,,0),_xlfn.XLOOKUP(1,($C18:C$18=C19)*($D18:D$18=D19-1),$F18:F$18+1,,0)),0)} -> 46035 | F19: =_xlfn.XLOOKUP(B19,old_ipc_dates!F:F,old_ipc_dates!C:C,EOMONTH(E19,0),0) -> 46053 | G19: Əsgərov Yaşar | H19: {=SUM(_xlfn._xlws.FILTER(_xlfn._TRO_TRAILING(quantities!L:L),(_xlfn._TRO_TRAILING(quantities!D:D)=C19)*(_xlfn._TRO_TRAILING(quantities!E:E)=D19)))} -> 2375 | J19: =SUMIFS( INDIRECT("'[S2 Subcon IPC Log.xlsx]Subcon IPC Log'!"&"$O:$O"), INDIRECT("'[S2 Subcon IPC Log.xlsx]Subcon IPC Log'!"&"$C:$C"), "KLN-SPP2-"&_xlfn.XLOOKUP(C19,log_contracts!B:B,log_contracts!C:C)&"-"&TEXT(C19,"000"), INDIRECT("'[S2 Subcon IPC Log.xlsx]Subcon IPC Log'!"&"$D:$D"), D19) -> #REF! | K19: #REF!
A20: 19 | B20: 164-001 | C20: 164 | D20: 1 | E20: {=_xlfn.XLOOKUP(B20,old_ipc_dates!F:F,old_ipc_dates!B:B,IF(D20=1,_xlfn.XLOOKUP(C20,log_contracts!B:B,log_contracts!D:D,,0),_xlfn.XLOOKUP(1,($C$18:C19=C20)*($D$18:D19=D20-1),$F$18:F19+1,,0)),0)} -> 46035 | F20: =_xlfn.XLOOKUP(B20,old_ipc_dates!F:F,old_ipc_dates!C:C,EOMONTH(E20,0),0) -> 46053 | G20: Əliyev Fizuli | H20: {=SUM(_xlfn._xlws.FILTER(_xlfn._TRO_TRAILING(quantities!L:L),(_xlfn._TRO_TRAILING(quantities!D:D)=C20)*(_xlfn._TRO_TRAILING(quantities!E:E)=D20)))} -> 6875 | J20: =SUMIFS( INDIRECT("'[S2 Subcon IPC Log.xlsx]Subcon IPC Log'!"&"$O:$O"), INDIRECT("'[S2 Subcon IPC Log.xlsx]Subcon IPC Log'!"&"$C:$C"), "KLN-SPP2-"&_xlfn.XLOOKUP(C20,log_contracts!B:B,log_contracts!C:C)&"-"&TEXT(C20,"000"), INDIRECT("'[S2 Subcon IPC Log.xlsx]Subcon IPC Log'!"&"$D:$D"), D20) -> #REF! | K20: #REF!
A21: 20 | B21: 172-001 | C21: 172 | D21: 1 | E21: {=_xlfn.XLOOKUP(B21,old_ipc_dates!F:F,old_ipc_dates!B:B,IF(D21=1,_xlfn.XLOOKUP(C21,log_contracts!B:B,log_contracts!D:D,,0),_xlfn.XLOOKUP(1,($C$18:C20=C21)*($D$18:D20=D21-1),$F$18:F20+1,,0)),0)} -> 46034 | F21: =_xlfn.XLOOKUP(B21,old_ipc_dates!F:F,old_ipc_dates!C:C,EOMONTH(E21,0),0) -> 46053 | G21: Mahmudov Rüstəm | H21: {=SUM(_xlfn._xlws.FILTER(_xlfn._TRO_TRAILING(quantities!L:L),(_xlfn._TRO_TRAILING(quantities!D:D)=C21)*(_xlfn._TRO_TRAILING(quantities!E:E)=D21)))} -> 3732.1429 | J21: =SUMIFS( INDIRECT("'[S2 Subcon IPC Log.xlsx]Subcon IPC Log'!"&"$O:$O"), INDIRECT("'[S2 Subcon IPC Log.xlsx]Subcon IPC Log'!"&"$C:$C"), "KLN-SPP2-"&_xlfn.XLOOKUP(C21,log_contracts!B:B,log_contracts!C:C)&"-"&TEXT(C21,"000"), INDIRECT("'[S2 Subcon IPC Log.xlsx]Subcon IPC Log'!"&"$D:$D"), D21) -> #REF! | K21: #REF!
A22: 21 | B22: 173-001 | C22: 173 | D22: 1 | E22: {=_xlfn.XLOOKUP(B22,old_ipc_dates!F:F,old_ipc_dates!B:B,IF(D22=1,_xlfn.XLOOKUP(C22,log_contracts!B:B,log_contracts!D:D,,0),_xlfn.XLOOKUP(1,($C$18:C21=C22)*($D$18:D21=D22-1),$F$18:F21+1,,0)),0)} -> 46054 | F22: =_xlfn.XLOOKUP(B22,old_ipc_dates!F:F,old_ipc_dates!C:C,EOMONTH(E22,0),0) -> 46081 | G22: Hüseynov Pərviz | H22: {=SUM(_xlfn._xlws.FILTER(_xlfn._TRO_TRAILING(quantities!L:L),(_xlfn._TRO_TRAILING(quantities!D:D)=C22)*(_xlfn._TRO_TRAILING(quantities!E:E)=D22)))} -> 10357.143 | J22: =SUMIFS( INDIRECT("'[S2 Subcon IPC Log.xlsx]Subcon IPC Log'!"&"$O:$O"), INDIRECT("'[S2 Subcon IPC Log.xlsx]Subcon IPC Log'!"&"$C:$C"), "KLN-SPP2-"&_xlfn.XLOOKUP(C22,log_contracts!B:B,log_contracts!C:C)&"-"&TEXT(C22,"000"), INDIRECT("'[S2 Subcon IPC Log.xlsx]Subcon IPC Log'!"&"$D:$D"), D22) -> #REF! | K22: #REF!
A23: 22 | B23: 179-001 | C23: 179 | D23: 1 | E23: {=_xlfn.XLOOKUP(B23,old_ipc_dates!F:F,old_ipc_dates!B:B,IF(D23=1,_xlfn.XLOOKUP(C23,log_contracts!B:B,log_contracts!D:D,,0),_xlfn.XLOOKUP(1,($C$18:C22=C23)*($D$18:D22=D23-1),$F$18:F22+1,,0)),0)} -> 46077 | F23: =_xlfn.XLOOKUP(B23,old_ipc_dates!F:F,old_ipc_dates!C:C,EOMONTH(E23,0),0) -> 46081 | G23: INFRACON MMC | H23: {=SUM(_xlfn._xlws.FILTER(_xlfn._TRO_TRAILING(quantities!L:L),(_xlfn._TRO_TRAILING(quantities!D:D)=C23)*(_xlfn._TRO_TRAILING(quantities!E:E)=D23)))} -> 4107.1429 | J23: =SUMIFS( INDIRECT("'[S2 Subcon IPC Log.xlsx]Subcon IPC Log'!"&"$O:$O"), INDIRECT("'[S2 Subcon IPC Log.xlsx]Subcon IPC Log'!"&"$C:$C"), "KLN-SPP2-"&_xlfn.XLOOKUP(C23,log_contracts!B:B,log_contracts!C:C)&"-"&TEXT(C23,"000"), INDIRECT("'[S2 Subcon IPC Log.xlsx]Subcon IPC Log'!"&"$D:$D"), D23) -> #REF! | K23: #REF!
A24: 23 | B24: 182-001 | C24: 182 | D24: 1 | E24: {=_xlfn.XLOOKUP(B24,old_ipc_dates!F:F,old_ipc_dates!B:B,IF(D24=1,_xlfn.XLOOKUP(C24,log_contracts!B:B,log_contracts!D:D,,0),_xlfn.XLOOKUP(1,($C$18:C23=C24)*($D$18:D23=D24-1),$F$18:F23+1,,0)),0)} -> 46075 | F24: =_xlfn.XLOOKUP(B24,old_ipc_dates!F:F,old_ipc_dates!C:C,EOMONTH(E24,0),0) -> 46081 | G24: Rüstəmov Sakit | H24: {=SUM(_xlfn._xlws.FILTER(_xlfn._TRO_TRAILING(quantities!L:L),(_xlfn._TRO_TRAILING(quantities!D:D)=C24)*(_xlfn._TRO_TRAILING(quantities!E:E)=D24)))} -> 2285.7143 | J24: =SUMIFS( INDIRECT("'[S2 Subcon IPC Log.xlsx]Subcon IPC Log'!"&"$O:$O"), INDIRECT("'[S2 Subcon IPC Log.xlsx]Subcon IPC Log'!"&"$C:$C"), "KLN-SPP2-"&_xlfn.XLOOKUP(C24,log_contracts!B:B,log_contracts!C:C)&"-"&TEXT(C24,"000"), INDIRECT("'[S2 Subcon IPC Log.xlsx]Subcon IPC Log'!"&"$D:$D"), D24) -> #REF! | K24: #REF!
A25: 24 | B25: 030-002 | C25: 30 | D25: 2 | E25: {=_xlfn.XLOOKUP(B25,old_ipc_dates!F:F,old_ipc_dates!B:B,IF(D25=1,_xlfn.XLOOKUP(C25,log_contracts!B:B,log_contracts!D:D,,0),_xlfn.XLOOKUP(1,($C$18:C24=C25)*($D$18:D24=D25-1),$F$18:F24+1,,0)),0)} -> 45689 | F25: =_xlfn.XLOOKUP(B25,old_ipc_dates!F:F,old_ipc_dates!C:C,EOMONTH(E25,0),0) -> 45716 | G25: NAR TRANSPORT SERVICES MMC | H25: {=SUM(_xlfn._xlws.FILTER(_xlfn._TRO_TRAILING(quantities!L:L),(_xlfn._TRO_TRAILING(quantities!D:D)=C25)*(_xlfn._TRO_TRAILING(quantities!E:E)=D25)))} -> 11000 | J25: =SUMIFS( INDIRECT("'[S2 Subcon IPC Log.xlsx]Subcon IPC Log'!"&"$O:$O"), INDIRECT("'[S2 Subcon IPC Log.xlsx]Subcon IPC Log'!"&"$C:$C"), "KLN-SPP2-"&_xlfn.XLOOKUP(C25,log_contracts!B:B,log_contracts!C:C)&"-"&TEXT(C25,"000"), INDIRECT("'[S2 Subcon IPC Log.xlsx]Subcon IPC Log'!"&"$D:$D"), D25) -> #REF! | K25: #REF!
A26: 25 | B26: 031-002 | C26: 31 | D26: 2 | E26: {=_xlfn.XLOOKUP(B26,old_ipc_dates!F:F,old_ipc_dates!B:B,IF(D26=1,_xlfn.XLOOKUP(C26,log_contracts!B:B,log_contracts!D:D,,0),_xlfn.XLOOKUP(1,($C$18:C25=C26)*($D$18:D25=D26-1),$F$18:F25+1,,0)),0)} -> 45717 | F26: =_xlfn.XLOOKUP(B26,old_ipc_dates!F:F,old_ipc_dates!C:C,EOMONTH(E26,0),0) -> 45747 | G26: NAR TRANSPORT SERVICES MMC | H26: {=SUM(_xlfn._xlws.FILTER(_xlfn._TRO_TRAILING(quantities!L:L),(_xlfn._TRO_TRAILING(quantities!D:D)=C26)*(_xlfn._TRO_TRAILING(quantities!E:E)=D26)))} -> 38935.15 | J26: =SUMIFS( INDIRECT("'[S2 Subcon IPC Log.xlsx]Subcon IPC Log'!"&"$O:$O"), INDIRECT("'[S2 Subcon IPC Log.xlsx]Subcon IPC Log'!"&"$C:$C"), "KLN-SPP2-"&_xlfn.XLOOKUP(C26,log_contracts!B:B,log_contracts!C:C)&"-"&TEXT(C26,"000"), INDIRECT("'[S2 Subcon IPC Log.xlsx]Subcon IPC Log'!"&"$D:$D"), D26) -> #REF! | K26: #REF!
A27: 26 | B27: 046-002 | C27: 46 | D27: 2 | E27: {=_xlfn.XLOOKUP(B27,old_ipc_dates!F:F,old_ipc_dates!B:B,IF(D27=1,_xlfn.XLOOKUP(C27,log_contracts!B:B,log_contracts!D:D,,0),_xlfn.XLOOKUP(1,($C$18:C26=C27)*($D$18:D26=D27-1),$F$18:F26+1,,0)),0)} -> 45809 | F27: =_xlfn.XLOOKUP(B27,old_ipc_dates!F:F,old_ipc_dates!C:C,EOMONTH(E27,0),0) -> 45838 | G27: HARDCORE CONSTRUCTION AND EQUIPMENT | H27: {=SUM(_xlfn._xlws.FILTER(_xlfn._TRO_TRAILING(quantities!L:L),(_xlfn._TRO_TRAILING(quantities!D:D)=C27)*(_xlfn._TRO_TRAILING(quantities!E:E)=D27)))} -> 17839.286 | J27: =SUMIFS( INDIRECT("'[S2 Subcon IPC Log.xlsx]Subcon IPC Log'!"&"$O:$O"), INDIRECT("'[S2 Subcon IPC Log.xlsx]Subcon IPC Log'!"&"$C:$C"), "KLN-SPP2-"&_xlfn.XLOOKUP(C27,log_contracts!B:B,log_contracts!C:C)&"-"&TEXT(C27,"000"), INDIRECT("'[S2 Subcon IPC Log.xlsx]Subcon IPC Log'!"&"$D:$D"), D27) -> #REF! | K27: #REF!
A28: 27 | B28: 050-002 | C28: 50 | D28: 2 | E28: {=_xlfn.XLOOKUP(B28,old_ipc_dates!F:F,old_ipc_dates!B:B,IF(D28=1,_xlfn.XLOOKUP(C28,log_contracts!B:B,log_contracts!D:D,,0),_xlfn.XLOOKUP(1,($C$18:C27=C28)*($D$18:D27=D28-1),$F$18:F27+1,,0)),0)} -> 45839 | F28: =_xlfn.XLOOKUP(B28,old_ipc_dates!F:F,old_ipc_dates!C:C,EOMONTH(E28,0),0) -> 45869 | G28: LOFT CONSTRUCTION | H28: {=SUM(_xlfn._xlws.FILTER(_xlfn._TRO_TRAILING(quantities!L:L),(_xlfn._TRO_TRAILING(quantities!D:D)=C28)*(_xlfn._TRO_TRAILING(quantities!E:E)=D28)))} -> 10357.143 | J28: =SUMIFS( INDIRECT("'[S2 Subcon IPC Log.xlsx]Subcon IPC Log'!"&"$O:$O"), INDIRECT("'[S2 Subcon IPC Log.xlsx]Subcon IPC Log'!"&"$C:$C"), "KLN-SPP2-"&_xlfn.XLOOKUP(C28,log_contracts!B:B,log_contracts!C:C)&"-"&TEXT(C28,"000"), INDIRECT("'[S2 Subcon IPC Log.xlsx]Subcon IPC Log'!"&"$D:$D"), D28) -> #REF! | K28: #REF!
A29: 28 | B29: 051-002 | C29: 51 | D29: 2 | E29: {=_xlfn.XLOOKUP(B29,old_ipc_dates!F:F,old_ipc_dates!B:B,IF(D29=1,_xlfn.XLOOKUP(C29,log_contracts!B:B,log_contracts!D:D,,0),_xlfn.XLOOKUP(1,($C$18:C28=C29)*($D$18:D28=D29-1),$F$18:F28+1,,0)),0)} -> 45870 | F29: =_xlfn.XLOOKUP(B29,old_ipc_dates!F:F,old_ipc_dates!C:C,EOMONTH(E29,0),0) -> 45930 | G29: INTERMAK GROUP MMC | H29: {=SUM(_xlfn._xlws.FILTER(_xlfn._TRO_TRAILING(quantities!L:L),(_xlfn._TRO_TRAILING(quantities!D:D)=C29)*(_xlfn._TRO_TRAILING(quantities!E:E)=D29)))} -> 9999.82 | J29: =SUMIFS( INDIRECT("'[S2 Subcon IPC Log.xlsx]Subcon IPC Log'!"&"$O:$O"), INDIRECT("'[S2 Subcon IPC Log.xlsx]Subcon IPC Log'!"&"$C:$C"), "KLN-SPP2-"&_xlfn.XLOOKUP(C29,log_contracts!B:B,log_contracts!C:C)&"-"&TEXT(C29,"000"), INDIRECT("'[S2 Subcon IPC Log.xlsx]Subcon IPC Log'!"&"$D:$D"), D29) -> #REF! | K29: #REF!
A30: 29 | B30: 052-002 | C30: 52 | D30: 2 | E30: {=_xlfn.XLOOKUP(B30,old_ipc_dates!F:F,old_ipc_dates!B:B,IF(D30=1,_xlfn.XLOOKUP(C30,log_contracts!B:B,log_contracts!D:D,,0),_xlfn.XLOOKUP(1,($C$18:C29=C30)*($D$18:D29=D30-1),$F$18:F29+1,,0)),0)} -> 45778 | F30: =_xlfn.XLOOKUP(B30,old_ipc_dates!F:F,old_ipc_dates!C:C,EOMONTH(E30,0),0) -> 45808 | G30: DTS MMC | H30: {=SUM(_xlfn._xlws.FILTER(_xlfn._TRO_TRAILING(quantities!L:L),(_xlfn._TRO_TRAILING(quantities!D:D)=C30)*(_xlfn._TRO_TRAILING(quantities!E:E)=D30)))} -> 15178.54 | J30: =SUMIFS( INDIRECT("'[S2 Subcon IPC Log.xlsx]Subcon IPC Log'!"&"$O:$O"), INDIRECT("'[S2 Subcon IPC Log.xlsx]Subcon IPC Log'!"&"$C:$C"), "KLN-SPP2-"&_xlfn.XLOOKUP(C30,log_contracts!B:B,log_contracts!C:C)&"-"&TEXT(C30,"000"), INDIRECT("'[S2 Subcon IPC Log.xlsx]Subcon IPC Log'!"&"$D:$D"), D30) -> #REF! | K30: #REF!
A31: 30 | B31: 065-002 | C31: 65 | D31: 2 | E31: {=_xlfn.XLOOKUP(B31,old_ipc_dates!F:F,old_ipc_dates!B:B,IF(D31=1,_xlfn.XLOOKUP(C31,log_contracts!B:B,log_contracts!D:D,,0),_xlfn.XLOOKUP(1,($C$18:C30=C31)*($D$18:D30=D31-1),$F$18:F30+1,,0)),0)} -> 45809 | F31: =_xlfn.XLOOKUP(B31,old_ipc_dates!F:F,old_ipc_dates!C:C,EOMONTH(E31,0),0) -> 45838 | G31: ETIBAR MAMMADOV | H31: {=SUM(_xlfn._xlws.FILTER(_xlfn._TRO_TRAILING(quantities!L:L),(_xlfn._TRO_TRAILING(quantities!D:D)=C31)*(_xlfn._TRO_TRAILING(quantities!E:E)=D31)))} -> 8955.2414 | J31: =SUMIFS( INDIRECT("'[S2 Subcon IPC Log.xlsx]Subcon IPC Log'!"&"$O:$O"), INDIRECT("'[S2 Subcon IPC Log.xlsx]Subcon IPC Log'!"&"$C:$C"), "KLN-SPP2-"&_xlfn.XLOOKUP(C31,log_contracts!B:B,log_contracts!C:C)&"-"&TEXT(C31,"000"), INDIRECT("'[S2 Subcon IPC Log.xlsx]Subcon IPC Log'!"&"$D:$D"), D31) -> #REF! | K31: #REF!
... A212: 211 | B212: 150-002 | C212: 150 | D212: 2 | E212: {=_xlfn.XLOOKUP(B212,old_ipc_dates!F:F,old_ipc_dates!B:B,IF(D212=1,_xlfn.XLOOKUP(C212,log_contracts!B:B,log_contracts!D:D,,0),_xlfn.XLOOKUP(1,($C$18:C211=C212)*($D$18:D211=D212-1),$F$18:F211+1,,0)),0)} -> 45992 | F212: =_xlfn.XLOOKUP(B212,old_ipc_dates!F:F,old_ipc_dates!C:C,EOMONTH(E212,0),0) -> 46022 | G212: AS RT MMC | H212: {=SUM(_xlfn._xlws.FILTER(_xlfn._TRO_TRAILING(quantities!L:L),(_xlfn._TRO_TRAILING(quantities!D:D)=C212)*(_xlfn._TRO_TRAILING(quantities!E:E)=D212)))} -> 810 | J212: =SUMIFS( INDIRECT("'[S2 Subcon IPC Log.xlsx]Subcon IPC Log'!"&"$O:$O"), INDIRECT("'[S2 Subcon IPC Log.xlsx]Subcon IPC Log'!"&"$C:$C"), "KLN-SPP2-"&_xlfn.XLOOKUP(C212,log_contracts!B:B,log_contracts!C:C)&"-"&TEXT(C212,"000"), INDIRECT("'[S2 Subcon IPC Log.xlsx]Subcon IPC Log'!"&"$D:$D"), D212) -> #REF! | K212: #REF!
E213: {=_xlfn.XLOOKUP(B213,old_ipc_dates!F:F,old_ipc_dates!B:B,IF(D213=1,_xlfn.XLOOKUP(C213,log_contracts!B:B,log_contracts!D:D,,0),_xlfn.XLOOKUP(1,($C$18:C212=C213)*($D$18:D212=D213-1),$F$18:F212+1,,0)),0)} -> Start | F213: =_xlfn.XLOOKUP(B213,old_ipc_dates!F:F,old_ipc_dates!C:C,EOMONTH(E213,0),0) -> Finish | H213: {=SUM(_xlfn._xlws.FILTER(_xlfn._TRO_TRAILING(quantities!L:L),(_xlfn._TRO_TRAILING(quantities!D:D)=C213)*(_xlfn._TRO_TRAILING(quantities!E:E)=D213)))} -> #VALUE! | J213: =SUMIFS( INDIRECT("'[S2 Subcon IPC Log.xlsx]Subcon IPC Log'!"&"$O:$O"), INDIRECT("'[S2 Subcon IPC Log.xlsx]Subcon IPC Log'!"&"$C:$C"), "KLN-SPP2-"&_xlfn.XLOOKUP(C213,log_contracts!B:B,log_contracts!C:C)&"-"&TEXT(C213,"000"), INDIRECT("'[S2 Subcon IPC Log.xlsx]Subcon IPC Log'!"&"$D:$D"), D213) -> #REF! | K213: #VALUE!
E214: {=_xlfn.XLOOKUP(B214,old_ipc_dates!F:F,old_ipc_dates!B:B,IF(D214=1,_xlfn.XLOOKUP(C214,log_contracts!B:B,log_contracts!D:D,,0),_xlfn.XLOOKUP(1,($C$18:C213=C214)*($D$18:D213=D214-1),$F$18:F213+1,,0)),0)} -> Start | F214: =_xlfn.XLOOKUP(B214,old_ipc_dates!F:F,old_ipc_dates!C:C,EOMONTH(E214,0),0) -> Finish
E215: {=_xlfn.XLOOKUP(B215,old_ipc_dates!F:F,old_ipc_dates!B:B,IF(D215=1,_xlfn.XLOOKUP(C215,log_contracts!B:B,log_contracts!D:D,,0),_xlfn.XLOOKUP(1,($C$18:C214=C215)*($D$18:D214=D215-1),$F$18:F214+1,,0)),0)} -> Start | F215: =_xlfn.XLOOKUP(B215,old_ipc_dates!F:F,old_ipc_dates!C:C,EOMONTH(E215,0),0) -> Finish
E216: {=_xlfn.XLOOKUP(B216,old_ipc_dates!F:F,old_ipc_dates!B:B,IF(D216=1,_xlfn.XLOOKUP(C216,log_contracts!B:B,log_contracts!D:D,,0),_xlfn.XLOOKUP(1,($C$18:C215=C216)*($D$18:D215=D216-1),$F$18:F215+1,,0)),0)} -> Start | F216: =_xlfn.XLOOKUP(B216,old_ipc_dates!F:F,old_ipc_dates!C:C,EOMONTH(E216,0),0) -> Finish
E217: {=_xlfn.XLOOKUP(B217,old_ipc_dates!F:F,old_ipc_dates!B:B,IF(D217=1,_xlfn.XLOOKUP(C217,log_contracts!B:B,log_contracts!D:D,,0),_xlfn.XLOOKUP(1,($C$18:C216=C217)*($D$18:D216=D217-1),$F$18:F216+1,,0)),0)} -> Start | F217: =_xlfn.XLOOKUP(B217,old_ipc_dates!F:F,old_ipc_dates!C:C,EOMONTH(E217,0),0) -> Finish
E218: {=_xlfn.XLOOKUP(B218,old_ipc_dates!F:F,old_ipc_dates!B:B,IF(D218=1,_xlfn.XLOOKUP(C218,log_contracts!B:B,log_contracts!D:D,,0),_xlfn.XLOOKUP(1,($C$18:C217=C218)*($D$18:D217=D218-1),$F$18:F217+1,,0)),0)} -> Start | F218: =_xlfn.XLOOKUP(B218,old_ipc_dates!F:F,old_ipc_dates!C:C,EOMONTH(E218,0),0) -> Finish
E219: {=_xlfn.XLOOKUP(B219,old_ipc_dates!F:F,old_ipc_dates!B:B,IF(D219=1,_xlfn.XLOOKUP(C219,log_contracts!B:B,log_contracts!D:D,,0),_xlfn.XLOOKUP(1,($C$18:C218=C219)*($D$18:D218=D219-1),$F$18:F218+1,,0)),0)} -> Start | F219: =_xlfn.XLOOKUP(B219,old_ipc_dates!F:F,old_ipc_dates!C:C,EOMONTH(E219,0),0) -> Finish
E220: {=_xlfn.XLOOKUP(B220,old_ipc_dates!F:F,old_ipc_dates!B:B,IF(D220=1,_xlfn.XLOOKUP(C220,log_contracts!B:B,log_contracts!D:D,,0),_xlfn.XLOOKUP(1,($C$18:C219=C220)*($D$18:D219=D220-1),$F$18:F219+1,,0)),0)} -> Start | F220: =_xlfn.XLOOKUP(B220,old_ipc_dates!F:F,old_ipc_dates!C:C,EOMONTH(E220,0),0) -> Finish
E221: {=_xlfn.XLOOKUP(B221,old_ipc_dates!F:F,old_ipc_dates!B:B,IF(D221=1,_xlfn.XLOOKUP(C221,log_contracts!B:B,log_contracts!D:D,,0),_xlfn.XLOOKUP(1,($C$18:C220=C221)*($D$18:D220=D221-1),$F$18:F220+1,,0)),0)} -> Start | F221: =_xlfn.XLOOKUP(B221,old_ipc_dates!F:F,old_ipc_dates!C:C,EOMONTH(E221,0),0) -> Finish
E222: {=_xlfn.XLOOKUP(B222,old_ipc_dates!F:F,old_ipc_dates!B:B,IF(D222=1,_xlfn.XLOOKUP(C222,log_contracts!B:B,log_contracts!D:D,,0),_xlfn.XLOOKUP(1,($C$18:C221=C222)*($D$18:D221=D222-1),$F$18:F221+1,,0)),0)} -> Start | F222: =_xlfn.XLOOKUP(B222,old_ipc_dates!F:F,old_ipc_dates!C:C,EOMONTH(E222,0),0) -> Finish
E223: {=_xlfn.XLOOKUP(B223,old_ipc_dates!F:F,old_ipc_dates!B:B,IF(D223=1,_xlfn.XLOOKUP(C223,log_contracts!B:B,log_contracts!D:D,,0),_xlfn.XLOOKUP(1,($C$18:C222=C223)*($D$18:D222=D223-1),$F$18:F222+1,,0)),0)} -> #N/A | F223: =_xlfn.XLOOKUP(B223,old_ipc_dates!F:F,old_ipc_dates!C:C,EOMONTH(E223,0),0) -> #N/A
E224: {=_xlfn.XLOOKUP(B224,old_ipc_dates!F:F,old_ipc_dates!B:B,IF(D224=1,_xlfn.XLOOKUP(C224,log_contracts!B:B,log_contracts!D:D,,0),_xlfn.XLOOKUP(1,($C$18:C223=C224)*($D$18:D223=D224-1),$F$18:F223+1,,0)),0)} -> Start | F224: =_xlfn.XLOOKUP(B224,old_ipc_dates!F:F,old_ipc_dates!C:C,EOMONTH(E224,0),0) -> Finish
E225: {=_xlfn.XLOOKUP(B225,old_ipc_dates!F:F,old_ipc_dates!B:B,IF(D225=1,_xlfn.XLOOKUP(C225,log_contracts!B:B,log_contracts!D:D,,0),_xlfn.XLOOKUP(1,($C$18:C224=C225)*($D$18:D224=D225-1),$F$18:F224+1,,0)),0)} -> Start | F225: =_xlfn.XLOOKUP(B225,old_ipc_dates!F:F,old_ipc_dates!C:C,EOMONTH(E225,0),0) -> Finish
... E245: {=_xlfn.XLOOKUP(B245,old_ipc_dates!F:F,old_ipc_dates!B:B,IF(D245=1,_xlfn.XLOOKUP(C245,log_contracts!B:B,log_contracts!D:D,,0),_xlfn.XLOOKUP(1,($C$18:C244=C245)*($D$18:D244=D245-1),$F$18:F244+1,,0)),0)} -> Start | F245: =_xlfn.XLOOKUP(B245,old_ipc_dates!F:F,old_ipc_dates!C:C,EOMONTH(E245,0),0) -> Finish

Sheet log_contracts
A1: # | B1: No | C1: Discipline code | D1: Commencement Date | E1: Subcontractor | F1: Scope of Work | G1: in charge person | H1: Contract Date | I1: Folder Name | J1: Phone numbers | K1: PDF Folder link | L1: Active | M1: In Charge | N1: Whatsapp
A2: {=_xlfn.SEQUENCE(ROWS(_xlfn._TRO_TRAILING(E:E))-1)} -> 1 | B2: 11 | C2: CW | D2: 45646 | E2: CASPIAN ENGINEERING SOLUTIONS MMC | F2: Monitorinq Xidməti | G2: Hakan Alkan | H2: 45646 | I2: 011_Caspian Engineering | J2: +994776371714 | K2: https://drive.google.com/drive/folders/1RTbySgxWzvB86fkBJ2hhAV8Sdp0evw1K?usp=sharing | L2: Active | M2: EB | N2: {=IF(_xlfn.DROP(_xlfn._TRO_TRAILING(J:J),1)="","",HYPERLINK("https://api.whatsapp.com/send?phone="&MID(_xlfn.DROP(_xlfn._TRO_TRAILING(J:J),1),2,15)&"&text=-","💬"))} -> 💬
A3: 2 | B3: 14 | C3: EQ | D3: 45652 | E3: HİLAL LTD | F3: Jenerator Hizmeti | G3: Mesut Fırat | H3: 45652 | I3: 014_Hilal Ltd | J3: +994502459043 | K3: https://drive.google.com/drive/folders/1TU7kGm8O57LowutFwQrPgedqtaIfI9Q5?usp=sharing | L3: Active | M3: EB | N3: 💬
A4: 3 | B4: 30 | C4: AA | D4: 45679 | E4: NAR TRANSPORT SERVICES MMC | F4: Rental Vehicle Kiralıq Vasitə | G4: İbrahim Kemik | H4: 45679 | I4: 030_Nar Transport_Ambulance | J4: +994512449400 | L4: Active | M4: EB | N4: 💬
A5: 4 | B5: 31 | C5: AA | D5: 45693 | E5: NAR TRANSPORT SERVICES MMC | F5: Rental Vehicle Kiralıq Vasitə | G5: İbrahim Kemik | H5: 45693 | I5: 031_Nar Transport_Services | J5: +994512449400 | K5: https://drive.google.com/drive/folders/1-9qvvhOEkqe0d21skfpYNC4z22wlYln8?usp=sharing | L5: Active | M5: EB | N5: 💬
A6: 5 | B6: 33 | C6: AA | D6: 45658 | E6: AKKOL HAZIR YEMEK SAN. TIC. AS | F6: Cartering Service | G6: İbrahim Kemik | H6: 45536 | I6: 033_Akkol Hazir Yemek | J6: +994514299334 | K6: https://drive.google.com/drive/folders/1PNEoaQDXbNgUGYReeztRkUTLC7H6-Wcn?usp=sharing | L6: Active | M6: EB | N6: 💬
A7: 6 | B7: 46 | C7: EQ | D7: 45748 | E7: HARDCORE CONSTRUCTION AND EQUIPMENT | F7: Rental Vehicle Kiralıq Vasitə | G7: Barış Gültekin | H7: 45748 | I7: 046_Hardcore Equipment | J7: +994703775515 | M7: EB | N7: 💬
A8: 7 | B8: 50 | C8: EQ | D8: 45758 | E8: LOFT CONSTRUCTION | F8: Rental Vehicle Kiralıq Vasitə | G8: Barış Gültekin | H8: 45748 | I8: 050_Loft Construction | J8: +994503774242 | K8: https://drive.google.com/drive/folders/142DR3TGBLzpjgWZ1F78DojtfSMPtjze2?usp=sharing | L8: Active | M8: EB | N8: 💬
A9: 8 | B9: 51 | C9: EQ | D9: 45761 | E9: INTERMAK GROUP MMC | F9: Rental Vehicle Kiralıq Vasitə | G9: İrfan Karakaya | H9: 45761 | I9: 051_Intermak Group | J9: +994102305309 | K9: https://drive.google.com/drive/folders/1ml3Q1rpL0TOOWpRzE1GY0AOCLSJXv7UD?usp=sharing | L9: Active | M9: EB | N9: 💬
A10: 9 | B10: 52 | C10: EQ | D10: 45762 | E10: DTS MMC | F10: Rental Vehicle Kiralıq Vasitə | G10: - | H10: 45762 | I10: 052_DTS | M10: EB
A11: 10 | B11: 65 | C11: EQ | D11: 45783 | E11: ETIBAR MAMMADOV | F11: Rental Vehicle Kiralıq Vasitə | G11: Barış Gültekin | H11: 45783 | I11: 065_Etibar Mammadov | J11: +994555923919 | K11: https://drive.google.com/drive/folders/177UTtWaWCyOQxtxb8hXPwJzqaIQh9SVI?usp=sharing | L11: Active | M11: EB | N11: 💬
A12: 11 | B12: 85 | C12: EQ | D12: 45824 | E12: BABEK ALBANDOV | F12: Rental Vehicle Kiralıq Vasitə | G12: Ertuğ Kuban | H12: 45824 | I12: 085_Babek Albandov | J12: +994773389192 | K12: https://drive.google.com/drive/folders/1G4c8mB0Yw0QQFItKQxhfihyD_Y7dRGIV?usp=sharing | L12: Active | M12: EB | N12: 💬
A13: 12 | B13: 91 | C13: EQ | D13: 45834 | E13: ELSAD QULIYEV | F13: Rental Vehicle Kiralıq Vasitə | G13: İbrahim Akgün | H13: 45834 | I13: 091_Quliyev Elşad Ramis | J13: +994515992662 | K13: https://drive.google.com/drive/folders/1NTIDOS2OvgAzZMXHlNhfpr3JhXPk2zOm?usp=sharing | L13: Active | M13: EB | N13: 💬
A14: 13 | B14: 94 | C14: EQ | D14: 45809 | E14: XANIM ABDULLAYEVA | F14: Rental Vehicle Kiralıq Vasitə | G14: Dilaver Türk | H14: 45809 | I14: 094_Abdullayeva Xanım (Rasim) | J14: +994517928522 | M14: EB | N14: 💬
A15: 14 | B15: 95 | C15: EQ | D15: 45848 | E15: IBRAHIM XALILOV | F15: Rental Vehicle Kiralıq Vasitə | G15: Barış Gültekin | H15: 45848 | I15: 095_Xəlilov İbrahim | J15: +994502324211 | K15: https://drive.google.com/drive/folders/1TxDlJAKcQJvhj4YfdVsDMA84KYon0Eig?usp=sharing | L15: Active | M15: EB | N15: 💬
A16: 15 | B16: 98 | C16: EQ | D16: 45854 | E16: HACIAGA KERIMOV | F16: Rental Vehicle Kiralıq Vasitə | G16: Ertuğ Kuban | H16: 45854 | I16: 098_Kərimov Hacıağa | J16: +994503466032 | K16: https://drive.google.com/drive/folders/1EN2LCshwd4uA-FBkQwoo3Ejw4BTLDLfI?usp=sharing | L16: Active | M16: EB | N16: 💬
A17: 16 | B17: 99 | C17: EQ | D17: 45859 | E17: YUSIF MAHARRAMOV | F17: Rental Vehicle Kiralıq Vasitə | G17: Dilaver Türk | H17: 45859 | I17: 099_Maharramov Yusif Qurban oğlu | J17: 994559997804 | M17: EB | N17: 💬
A18: 17 | B18: 100 | C18: EQ | D18: 45859 | E18: RUSLAN HUSEYNOV | F18: Rental Vehicle Kiralıq Vasitə | G18: Barış Gültekin | H18: 45859 | I18: 100_Hüseyinov Ruslan | J18: +994552212085 | K18: https://drive.google.com/drive/folders/1jJLSXJZMd5mNU0F7nQqC40nV6nTqDAVb?usp=sharing | L18: Active | M18: EB | N18: 💬
A19: 18 | B19: 102 | C19: EQ | D19: 45892 | E19: KONUL HUSEYNOVA | F19: Rental Vehicle Kiralıq Vasitə | G19: Dilaver Türk | H19: 45892 | I19: 102_Huseynova Konul | J19: +994517928522 | K19: https://drive.google.com/drive/folders/1HVFrbtCu5RwlpD9UT74iMuIdGa_5fRHQ?usp=sharing | L19: Active | M19: EB | N19: 💬
A20: 19 | B20: 103 | C20: QM | D20: 45880 | E20: BUREAU VERITAS AZERI MMC | F20: Personnel Trainings | G20: Hakan Alkan | H20: 45880 | I20: 103_Büro Veritas Azeri MMC | M20: EB
A21: 20 | B21: 107 | C21: CW | D21: 45856 | E21: QUALIFY MMC | F21: Monitorinq Xidməti | G21: Hakan Alkan | H21: 45856 | I21: 107_Qualify | J21: +994708207470 | M21: EB | N21: 💬
A22: 21 | B22: 110 | C22: EQ | D22: 45890 | E22: MAMMAD QALANDARLI | F22: Rental Vehicle Kiralıq Vasitə | G22: Ertuğ Kuban | H22: 45890 | I22: 110_Qalandarli Mammad | J22: +994502490088 | K22: https://drive.google.com/drive/folders/14IVFENbPf9zcZ0pksLzsPtqxaTm-yLUk?usp=sharing | L22: Active | M22: EB | N22: 💬
A23: 22 | B23: 115 | E23: Gülanə Hüseynova | I23: 115_Gülanə Hüseynova | M23: EB
A24: 23 | I24: 117_Mehdiyeva Səadət | M24: EB
A25: 24 | B25: 119 | C25: EQ | E25: NAR KRAN MMC | I25: 119_NAR KRAN MMC | L25: Active | M25: DY
A26: 25 | B26: 121 | C26: EQ | D26: 45925 | E26: TEYMUR ABBASOV | F26: Truck Dartıcı | G26: Ertuğ Kuban | H26: 45925 | I26: 121_Abbasov Teymur | J26: +994503851015 | K26: https://drive.google.com/drive/folders/1MlUuXhEyTVHQ9ZchQfCykcPmRqwRODOM?usp=sharing | L26: Active | M26: EB | N26: 💬
A27: 26 | I27: 124_Qafqaz AZE İnşaat (Finishing Works) | M27: EB
A28: 27 | B28: 141 | C28: EQ | D28: 45601 | E28: MIRELEM CABBROV | F28: Rental Vehicle Kiralıq Vasitə | G28: Barış Gültekin | H28: 45601 | I28: 141_Cabbarov Mirelem_(Asfalt Silindir) | J28: +994503462100 | K28: https://drive.google.com/drive/folders/1CrwG3ob5BEFABuz5-YmzV6HrRZhCMCUB?usp=sharing | L28: Active | M28: EB | N28: 💬
A29: 28 | B29: 150 | C29: CW | D29: 45989 | E29: AS RT MMC | F29: Monitorinq Xidməti | G29: Hakan Alkan | H29: 45989 | I29: 150_AS RT MMC | J29: +994506142283 | K29: https://drive.google.com/drive/folders/1I2QQvT6OZVy4T-dRj0k9yfggLcRlYnFN?usp=sharing | L29: Active | M29: EB | N29: 💬
A30: 29 | B30: 163 | C30: EQ | D30: 46035 | E30: Əsgərov Yaşar | F30: Rental Vehicle Kiralıq Vasitə | G30: Nurettin Biçer | H30: 46035 | I30: 163_Əsgərov Yaşar | J30: +994558864957 | K30: https://drive.google.com/drive/folders/1lKKetY3A2eVGjDOoR01MEz93Yaihkaa6?usp=sharing | M30: EB | N30: 💬
A31: 30 | B31: 164 | C31: EQ | D31: 46035 | E31: Əliyev Fizuli | F31: Rental Vehicle Kiralıq Vasitə | H31: 46035 | I31: 164_Əliyev Fizuli | J31: +994555711494 | K31: https://drive.google.com/drive/folders/1eo3mmH6MI0Cp36wazLWJZvuEefWiZBI5?usp=sharing | M31: EB | N31: 💬
A32: 31 | B32: 172 | C32: EQ | D32: 46034 | E32: Mahmudov Rüstəm | F32: Rental Vehicle Kiralıq Vasitə | G32: Barış Gültekin | H32: 46034 | I32: 172_Mahmudov Rüstəm | J32: +994555155362 | K32: https://drive.google.com/drive/folders/1_4ohQ2w2bYgVwf6kaSt-1pkA6LnL3oUS?usp=sharing | L32: Active | M32: EB | N32: 💬
A33: 32 | B33: 173 | C33: EQ | D33: 46054 | E33: Hüseynov Pərviz | F33: Rental Vehicle Kiralıq Vasitə | G33: Ertuğ Kuban | H33: 46054 | I33: 173_Hüseynov Pərviz | J33: +994556519191 | K33: https://drive.google.com/drive/folders/1-5T04mDWAcX6L4rC5MejMDmcjYArOZjv?usp=sharing | L33: Active | M33: EB | N33: 💬
A34: 33 | B34: 179 | C34: EQ | D34: 46077 | E34: INFRACON MMC | F34: Rental Vehicle Kiralıq Vasitə | G34: Burak Papila | H34: 46077 | I34: 179_INFRACON | J34: +994502424644 | K34: https://drive.google.com/drive/folders/1GF0RgNNzPRR6vtSBss-Qqjd8eNWJZScU?usp=sharing | L34: Active | M34: EB | N34: 💬
A35: 34 | B35: 182 | C35: EQ | D35: 46075 | E35: Rüstəmov Sakit | F35: Rental Vehicle Kiralıq Vasitə | G35: İrfan Karakaya | H35: 46075 | I35: 182_Rüstəmov Sakit | J35: +994772954541 | K35: https://drive.google.com/drive/folders/1yTODQR1SFWtkzB3SLvEFhCXxYBKAY0uJ?usp=sharing | L35: Active | M35: EB | N35: 💬

Sheet log_addendums
A1: # | B1: contract no | C1: addendum no | D1: price no | E1: description | F1: unit | G1: is active | H1: Coeifficient Price | I1: day count | J1: Total price | K1: Fuel lt/100km | L1: Plateno | M1: Person in Charge
A2: {=_xlfn.SEQUENCE(ROWS(_xlfn._TRO_TRAILING(B:B))-1)} -> 1 | B2: 30 | D2: 1 | E2: AMBULANCE - 99AS882-gün | F2: single | G2: FALSE | H2: 183.33333 | I2: 30 | J2: 5500 | L2: 99AS882 | M2: İbrahim Kemik
A3: 2 | B3: 30 | D3: 2 | E3: AMBULANCE - 99JE233-gün | F3: single | G3: FALSE | H3: 183.33333 | I3: 30 | J3: 5500 | L3: 99JE233 | M3: İbrahim Kemik
A4: 3 | B4: 30 | D4: 3 | E4: AMBULANCE - 99AS882 | F4: month | H4: 5500 | L4: 99AS882 | M4: İbrahim Kemik
A5: 4 | B5: 30 | D5: 4 | E5: AMBULANCE - 99JE233 | F5: month | H5: 5500 | L5: 99JE233 | M5: İbrahim Kemik
A6: 5 | B6: 31 | D6: 1 | E6: SERVIS - 99LT168 - Baku-tək | F6: single | H6: 73.33 | I6: 30 | K6: 18 | L6: 99LT168 | M6: İbrahim Kemik
A7: 6 | B7: 31 | D7: 2 | E7: SERVIS - 99LT168 - Baku-saat | F7: hour | H7: 7.333 | K7: 18 | L7: 99LT168 | M7: İbrahim Kemik
A8: 7 | B8: 31 | D8: 3 | E8: SERVIS - 99HZ395 - Sumqayıt-tək | F8: single | H8: 65 | I8: 30 | K8: 18 | L8: 99HZ395 | M8: İbrahim Kemik
A9: 8 | B9: 31 | D9: 4 | E9: SERVIS - 99HZ395 - Sumqayıt-saat | F9: hour | H9: 6.5 | K9: 18 | L9: 99HZ395 | M9: İbrahim Kemik
A10: 9 | B10: 31 | D10: 5 | E10: SERVIS - 90OV187 - Baku-tək | F10: single | H10: 73.33 | I10: 30 | K10: 18 | L10: 90OV187 | M10: İbrahim Kemik
A11: 10 | B11: 31 | D11: 6 | E11: SERVIS - 90OV187 - Baku-saat | F11: hour | H11: 7.333 | K11: 18 | L11: 90OV187 | M11: İbrahim Kemik
A12: 11 | B12: 31 | D12: 7 | E12: SERVIS - 77UG347 - Sumqayıt-tək | F12: single | H12: 65 | I12: 30 | L12: 77UG347 | M12: İbrahim Kemik
A13: 12 | B13: 31 | D13: 8 | E13: SERVIS - 77UG347 - Sumqayıt-saat | F13: hour | H13: 6.5 | L13: 77UG347 | M13: İbrahim Kemik
A14: 13 | B14: 31 | D14: 9 | E14: SERVIS - 99FB123 - Baku-tək | F14: single | H14: 73.33 | I14: 30 | L14: 99FB123 | M14: İbrahim Kemik
A15: 14 | B15: 31 | D15: 10 | E15: SERVIS - 99FB123 - Baku-saat | F15: hour | H15: 7.333 | L15: 99FB123 | M15: İbrahim Kemik
A16: 15 | B16: 31 | D16: 11 | E16: SERVIS - 90ZP408 - Sahə-tək | F16: single | H16: 55.36 | K16: 15 | L16: 90ZP408 | M16: İbrahim Kemik
A17: 16 | B17: 31 | D17: 12 | E17: SERVIS - 90ZP408 - Sahə-saat | F17: hour | H17: 5.536 | K17: 15 | L17: 90ZP408 | M17: İbrahim Kemik
A18: 17 | B18: 31 | D18: 13 | E18: SERVIS - 77AT386 - Satınalma-tək | F18: single | H18: 46.67 | I18: 30 | K18: 15 | L18: 77AT386 | M18: İbrahim Kemik
A19: 18 | B19: 31 | D19: 14 | E19: SERVIS - 77AT386 - Satınalma-saat | F19: hour | H19: 4.667 | K19: 15 | L19: 77AT386 | M19: İbrahim Kemik
A20: 19 | B20: 31 | D20: 15 | E20: SERVIS - 66CC029 - Sahə-tək | F20: single | H20: 55.36 | K20: 15 | L20: 66CC029 | M20: İbrahim Kemik
A21: 20 | B21: 31 | D21: 16 | E21: SERVIS - 66CC029 - Sahə-saat | F21: hour | H21: 5.536 | K21: 15 | L21: 66CC029 | M21: İbrahim Kemik
A22: 21 | B22: 31 | D22: 17 | E22: ZİBİL MAŞINI - 77QK725-tək | F22: single | H22: 275 | L22: 77QK725 | M22: İbrahim Kemik
A23: 22 | B23: 31 | D23: 18 | E23: ZİBİL MAŞINI - 77QK725-saat | F23: hour | H23: 27.5 | L23: 77QK725 | M23: İbrahim Kemik
A24: 23 | B24: 31 | D24: 19 | E24: SERVIS - 90SL686 - Aeroport-tək | F24: single | H24: 58.93 | K24: 12 | L24: 90SL686 | M24: İbrahim Kemik
A25: 24 | B25: 31 | D25: 20 | E25: SERVIS - 90SL686 - Aeroport-saat | F25: hour | H25: 5.893 | K25: 12 | L25: 90SL686 | M25: İbrahim Kemik
A26: 25 | B26: 31 | D26: 21 | E26: Pickup - 77DK884 - Çift Kabin (Remez)-tək | F26: single | H26: 96.43 | L26: 77DK884 | M26: İbrahim Kemik
A27: 26 | B27: 31 | D27: 22 | E27: Pickup - 77DK884 - Çift Kabin (Remez)-saat | F27: hour | H27: 9.643 | L27: 77DK884 | M27: İbrahim Kemik
A28: 27 | B28: 31 | D28: 23 | E28: Pickup - 50FB264 - Kamyonet-tək | F28: single | H28: 66.07 | K28: 15 | L28: 50FB264 | M28: İbrahim Kemik
A29: 28 | B29: 31 | D29: 24 | E29: Pickup - 50FB264 - Kamyonet-saat | F29: hour | H29: 6.607 | K29: 15 | L29: 50FB264 | M29: İbrahim Kemik
A30: 29 | B30: 31 | D30: 25 | E30: SERVIS - 01CC689 - Sahə-saat | F30: hour | H30: 5.536 | K30: 15 | L30: 01CC689 | M30: İbrahim Kemik
A31: 30 | B31: 31 | D31: 26 | E31: SERVIS - 01CC689 - Sahə-tək | F31: single | H31: 55.36 | K31: 15 | L31: 01CC689 | M31: İbrahim Kemik
A32: 31 | B32: 31 | D32: 27 | E32: SERVIS - 10NS184 - Sahə-saat | F32: hour | H32: 5.536 | K32: 15 | L32: 10NS184 | M32: İbrahim Kemik
A33: 32 | B33: 31 | D33: 28 | E33: SERVIS - 10NS184 - Sahə-tək | F33: single | H33: 55.36 | K33: 15 | L33: 10NS184 | M33: İbrahim Kemik
A34: 33 | B34: 31 | D34: 29 | E34: SERVIS - 10RN527 - Sahə-saat | F34: hour | H34: 5.536 | K34: 15 | L34: 10RN527 | M34: İbrahim Kemik
A35: 34 | B35: 31 | D35: 30 | E35: SERVIS - 10RN527 - Sahə_v1-saat | F35: hour | H35: 6.25 | K35: 15 | L35: 10RN527 | M35: İbrahim Kemik
A36: 35 | B36: 31 | D36: 31 | E36: SERVIS - 10RN527 - Sahə-tək | F36: single | H36: 55.36 | K36: 15 | L36: 10RN527 | M36: İbrahim Kemik
A37: 36 | B37: 31 | D37: 32 | E37: SERVIS - 10RN527 - Sahə_v1-tək | F37: single | H37: 62.5 | K37: 15 | L37: 10RN527 | M37: İbrahim Kemik
A38: 37 | B38: 31 | D38: 33 | E38: SERVIS - 10ZS260 - Sahə-tək | F38: single | H38: 66.67 | I38: 30 | K38: 15 | L38: 10ZS260 | M38: İbrahim Kemik
A39: 38 | B39: 31 | D39: 34 | E39: SERVIS - 15BZ942 - Sahə-saat | F39: hour | H39: 5.536 | K39: 15 | L39: 15BZ942 | M39: İbrahim Kemik
A40: 39 | B40: 31 | D40: 35 | E40: SERVIS - 15BZ942 - Sahə-tək | F40: single | H40: 55.36 | K40: 15 | L40: 15BZ942 | M40: İbrahim Kemik
A41: 40 | B41: 31 | D41: 36 | E41: SERVIS - 17BE358 - Sahə-saat | F41: hour | H41: 5.536 | K41: 15 | L41: 17BE358 | M41: İbrahim Kemik
A42: 41 | B42: 31 | D42: 37 | E42: SERVIS - 17BE358 - Sahə-tək | F42: single | H42: 55.36 | K42: 15 | L42: 17BE358 | M42: İbrahim Kemik
A43: 42 | B43: 31 | D43: 38 | E43: SERVIS - 21BF442 - Sahə-saat | F43: hour | H43: 5.536 | K43: 15 | L43: 21BF442 | M43: İbrahim Kemik
A44: 43 | B44: 31 | D44: 39 | E44: SERVIS - 21BF442 - Sahə-tək | F44: single | H44: 55.36 | K44: 15 | L44: 21BF442 | M44: İbrahim Kemik
A45: 44 | B45: 31 | D45: 40 | E45: SERVIS - 50BD165 - Sahə-saat | F45: hour | H45: 5.536 | K45: 15 | L45: 50BD165 | M45: İbrahim Kemik
A46: 45 | B46: 31 | D46: 41 | E46: SERVIS - 50BD165 - Sahə-tək | F46: single | H46: 55.36 | K46: 15 | L46: 50BD165 | M46: İbrahim Kemik
A47: 46 | B47: 31 | D47: 42 | E47: SERVIS - 50BN724 - Sahə-saat | F47: hour | H47: 6.607 | K47: 18 | L47: 50BN724 | M47: İbrahim Kemik
A48: 47 | B48: 31 | D48: 43 | E48: SERVIS - 50BN724 - Sahə-tək | F48: single | H48: 66.07 | K48: 18 | L48: 50BN724 | M48: İbrahim Kemik
A49: 48 | B49: 31 | D49: 44 | E49: SERVIS - 50CN929 - Sahə-saat | F49: hour | H49: 5.536 | K49: 15 | L49: 50CN929 | M49: İbrahim Kemik
A50: 49 | B50: 31 | D50: 45 | E50: SERVIS - 50CN929 - Sahə-tək | F50: single | H50: 55.36 | K50: 15 | L50: 50CN929 | M50: İbrahim Kemik
... A70: 69 | B70: 31 | D70: 65 | E70: SERVIS - 77GR998 - Sahə-tək | F70: single | H70: 55.36 | K70: 15 | L70: 77GR998 | M70: İbrahim Kemik
A71: 70 | B71: 31 | D71: 66 | E71: SERVIS - 77PV619 - Satınalma-saat | F71: hour | H71: 4 | L71: 77PV619 | M71: İbrahim Kemik
A72: 71 | B72: 31 | D72: 67 | E72: SERVIS - 77PV619 - Satınalma-tək | F72: single | H72: 40 | I72: 30 | L72: 77PV619 | M72: İbrahim Kemik
A73: 72 | B73: 31 | D73: 68 | E73: SERVIS - 77QE133 - Baku-saat | F73: hour | H73: 7.333 | K73: 18 | L73: 77QE133 | M73: İbrahim Kemik
A74: 73 | B74: 31 | D74: 69 | E74: SERVIS - 77QE133 - Baku-tək | F74: single | H74: 73.33 | I74: 30 | K74: 18 | L74: 77QE133 | M74: İbrahim Kemik
A75: 74 | B75: 31 | D75: 70 | E75: SERVIS - 77RN868 - Baku-saat | F75: hour | H75: 7.333 | K75: 18 | L75: 77RN868 | M75: İbrahim Kemik
A76: 75 | B76: 31 | D76: 71 | E76: SERVIS - 77RN868 - Baku-tək | F76: single | H76: 73.33 | I76: 30 | K76: 18 | L76: 77RN868 | M76: İbrahim Kemik
A77: 76 | B77: 31 | D77: 72 | E77: SERVIS - 77SR538 - Baku-saat | F77: hour | H77: 7.333 | K77: 18 | L77: 77SR538 | M77: İbrahim Kemik
A78: 77 | B78: 31 | D78: 73 | E78: SERVIS - 77SR538 - Baku-tək | F78: single | H78: 73.33 | I78: 30 | K78: 18 | L78: 77SR538 | M78: İbrahim Kemik
A79: 78 | B79: 31 | D79: 74 | E79: SERVIS - 77TG971 - Sahə-saat | F79: hour | H79: 5.536 | K79: 15 | L79: 77TG971 | M79: İbrahim Kemik
A80: 79 | B80: 31 | D80: 75 | E80: SERVIS - 77TG971 - Sahə-tək | F80: single | H80: 55.36 | K80: 15 | L80: 77TG971 | M80: İbrahim Kemik
A81: 80 | B81: 31 | D81: 76 | E81: SERVIS - 77UR032 - Sahə-saat | F81: hour | H81: 5.536 | K81: 15 | L81: 77UR032 | M81: İbrahim Kemik
A82: 81 | B82: 31 | D82: 77 | E82: SERVIS - 77UR032 - Sahə-tək | F82: single | H82: 55.36 | K82: 15 | L82: 77UR032 | M82: İbrahim Kemik
A83: 82 | B83: 31 | D83: 78 | E83: SERVIS - 90EC344 - Sahə-saat | F83: hour | H83: 6.25 | K83: 15 | L83: 90EC344 | M83: İbrahim Kemik
A84: 83 | B84: 31 | D84: 79 | E84: SERVIS - 90EC344 - Sahə-tək | F84: single | H84: 62.5 | K84: 15 | L84: 90EC344 | M84: İbrahim Kemik
A85: 84 | B85: 31 | D85: 80 | E85: SERVIS - 90LS143 - Sahə-saat | F85: hour | H85: 5.536 | K85: 15 | L85: 90LS143 | M85: İbrahim Kemik
A86: 85 | B86: 31 | D86: 81 | E86: SERVIS - 90LS143 - Sahə-tək | F86: single | H86: 55.36 | K86: 15 | L86: 90LS143 | M86: İbrahim Kemik
A87: 86 | B87: 31 | D87: 82 | E87: SERVIS - 90OE402 - Baku-saat | F87: hour | H87: 7.333 | K87: 18 | L87: 90OE402 | M87: İbrahim Kemik
A88: 87 | B88: 31 | D88: 83 | E88: SERVIS - 90OE402 - Baku-tək | F88: single | H88: 73.33 | I88: 30 | K88: 18 | L88: 90OE402 | M88: İbrahim Kemik
A89: 88 | B89: 31 | D89: 84 | E89: SERVIS - 90PY548 - Satınalma-saat | F89: hour | H89: 4 | L89: 90PY548 | M89: İbrahim Kemik
A90: 89 | B90: 31 | D90: 85 | E90: SERVIS - 90PY548 - Satınalma-tək | F90: single | H90: 40 | I90: 30 | L90: 90PY548 | M90: İbrahim Kemik
A91: 90 | B91: 31 | D91: 86 | E91: SERVIS - 90VS316 - Sahə-saat | F91: hour | H91: 5.536 | K91: 15 | L91: 90VS316 | M91: İbrahim Kemik
A92: 91 | B92: 31 | D92: 87 | E92: SERVIS - 90VS316 - Sahə-tək | F92: single | H92: 55.36 | K92: 15 | L92: 90VS316 | M92: İbrahim Kemik
A93: 92 | B93: 31 | D93: 88 | E93: SERVIS - 90YN163 - Satınalma-saat | F93: hour | H93: 4 | K93: 15 | L93: 90YN163 | M93: İbrahim Kemik
A94: 93 | B94: 31 | D94: 89 | E94: SERVIS - 90YN163 - Satınalma-tək | F94: single | H94: 40 | K94: 15 | L94: 90YN163 | M94: İbrahim Kemik
A95: 94 | B95: 31 | D95: 90 | E95: SERVIS - 99BT339 - Sahə-cüt | F95: double | H95: 91.34 | K95: 15 | L95: 99BT339 | M95: İbrahim Kemik
A96: 95 | B96: 31 | D96: 91 | E96: SERVIS - 99BT339 - Sahə_v1-cüt | F96: double | H96: 99.648 | K96: 15 | L96: 99BT339 | M96: İbrahim Kemik
A97: 96 | B97: 31 | D97: 92 | E97: SERVIS - 99BT339 - Sahə-saat | F97: hour | H97: 5.536 | K97: 15 | L97: 99BT339 | M97: İbrahim Kemik
A98: 97 | B98: 31 | D98: 93 | E98: SERVIS - 99BT339 - Sahə-tək | F98: single | H98: 55.36 | K98: 15 | L98: 99BT339 | M98: İbrahim Kemik
A99: 98 | B99: 31 | D99: 94 | E99: SERVIS - 99CN447 - Sahə-tək | F99: single | H99: 55.36 | K99: 15 | L99: 99CN447 | M99: İbrahim Kemik
A100: 99 | B100: 31 | D100: 95 | E100: SERVIS - 99CN447 - Sahə-saat | F100: hour | H100: 5.536 | K100: 15 | L100: 99CN447 | M100: İbrahim Kemik
A101: 100 | B101: 31 | D101: 96 | E101: SERVIS - 99DX531 - Sahə-saat | F101: hour | H101: 5.536 | K101: 15 | L101: 99DX531 | M101: İbrahim Kemik
A102: 101 | B102: 31 | D102: 97 | E102: SERVIS - 99DX531 - Sahə-tək | F102: single | H102: 55.36 | K102: 15 | L102: 99DX531 | M102: İbrahim Kemik
... A121: 120 | B121: 31 | D121: 116 | E121: VAQON - 99LM412 - Sahə-tək | F121: single | H121: 55.36 | K121: 15 | L121: 99LM412 | M121: İbrahim Kemik
A122: 121 | B122: 31 | D122: 117 | E122: ZİBİL MAŞINI - 77VL420 - Camp-saat | F122: hour | H122: 27.5 | L122: 77VL420 | M122: İbrahim Kemik
A123: 122 | B123: 31 | D123: 118 | E123: ZİBİL MAŞINI - 77VL420 - Camp-tək | F123: single | H123: 275 | L123: 77VL420 | M123: İbrahim Kemik
A124: 123 | B124: 31 | D124: 119 | E124: SERVIS - 57BV285 - Sahə-tək | F124: single | H124: 62.5 | K124: 15 | L124: 57BV285 | M124: İbrahim Kemik
A125: 124 | B125: 31 | D125: 120 | E125: SERVIS - 57BV285 - Sahə-saat | F125: hour | H125: 6.25 | K125: 15 | L125: 57BV285 | M125: İbrahim Kemik
A126: 125 | B126: 31 | D126: 121 | E126: SERVIS - 90UX686 - Sahə-tək | F126: single | H126: 62.5 | K126: 15 | L126: 90UX686 | M126: İbrahim Kemik
A127: 126 | B127: 31 | D127: 122 | E127: SERVIS - 90UX686 - Sahə-saat | F127: hour | H127: 6.25 | K127: 15 | L127: 90UX686 | M127: İbrahim Kemik
A128: 127 | B128: 31 | D128: 123 | E128: SERVIS - 99DT131 - Sahə-tək | F128: single | H128: 55.36 | K128: 15 | L128: 99DT131 | M128: İbrahim Kemik
A129: 128 | B129: 31 | D129: 124 | E129: SERVIS - 99DT131 - Sahə-saat | F129: hour | H129: 5.536 | K129: 15 | L129: 99DT131 | M129: İbrahim Kemik
A130: 129 | B130: 31 | D130: 125 | E130: Pickup - 90RC631 - Cesan crane-tək | F130: single | H130: 96.43 | K130: 15 | L130: 90RC631 | M130: İbrahim Kemik
A131: 130 | B131: 31 | D131: 126 | E131: Pickup - 90RC631 - Cesan crane-saat | F131: hour | H131: 9.643 | K131: 15 | L131: 90RC631 | M131: İbrahim Kemik
A132: 131 | B132: 46 | D132: 1 | E132: 110FY523 - CAT CS 56B Vərdənə (Cylinder)-tək | F132: single | H132: 214.28571 | I132: 28 | J132: 6000 | L132: 110FY523 | M132: Barış Gültekin
A133: 132 | B133: 46 | D133: 2 | E133: 110FY523 - CAT CS 56B Vərdənə (Cylinder)-cüt | F133: double | H133: 385.71444 | L133: 110FY523 | M133: Barış Gültekin
A134: 133 | B134: 46 | D134: 3 | E134: 110FY523 - CAT CS 56B Vərdənə (Cylinder)-saat | F134: hour | H134: 21.42858 | L134: 110FY523 | M134: Barış Gültekin
A135: 134 | B135: 46 | D135: 4 | E135: 10AD801 - Hyundai R380LC-9SH Ekskavator - (Operatorlu)-tək | F135: single | H135: 446.42857 | I135: 28 | J135: 12500 | L135: 10AD801 | M135: Barış Gültekin
A136: 135 | B136: 46 | D136: 5 | E136: 10AD801 - Hyundai R380LC-9SH Ekskavator - (Operatorlu)-cüt | F136: double | H136: 803.57148 | L136: 10AD801 | M136: Barış Gültekin
A137: 136 | B137: 46 | D137: 6 | E137: 10AD801 - Hyundai R380LC-9SH Ekskavator - (Operatorlu)-saat | F137: hour | H137: 44.64286 | L137: 10AD801 | M137: Barış Gültekin
...

Sheet log_prices
A1: # | B1: ID | C1: contract no | D1: addendum | E1: no | F1: description | G1: unit | H1: is active | I1: Coeifficient Price | J1: day count | K1: Total price | L1: Fuel lt/100km | M1: Plateno | N1: starting from date | O1: Person in Charge
A2: {=_xlfn.SEQUENCE(ROWS(_xlfn.ANCHORARRAY(B2)))} -> 1 | B2: {=_xlfn.DROP(_xlfn._TRO_TRAILING(C:C)&"-"&_xlfn._TRO_TRAILING(E:E),1)} -> 11-1 | C2: 11 | D2: 1 | E2: 1 | F2: Monthly Fee | G2: ay | I2: 5500 | N2: 45646
A3: 2 | B3: 11-2 | C3: 11 | D3: 1 | E3: 2 | F3: Additional Fee | G3: gün | I3: 200 | N3: 45646
A4: 3 | B4: 11-3 | C4: 11 | D4: 2 | E4: 3 | F4: Rebar Test (Tensile st., Yield st., Elangation) | G4: əd | I4: 100 | N4: 45646
A5: 4 | B5: 11-4 | C5: 11 | D5: 3 | E5: 4 | F5: Water Test | G5: əd | I5: 300 | N5: 45646
A6: 5 | B6: 11-5 | C6: 11 | D6: 4 | E6: 5 | F6: Welding Test | G6: əd | I6: 540 | N6: 45646
A7: 6 | B7: 11-6 | C7: 11 | D7: 5 | E7: 6 | F7: Ultrasonic Pulse Echo (Reinforced Concrete) | G7: gün | I7: 1000 | N7: 45646
A8: 7 | B8: 11-7 | C8: 11 | D8: 6 | E8: 7 | F8: Rebar Test (Bend) | G8: əd | I8: 110 | N8: 45646
A9: 8 | B9: 11-8 | C9: 11 | D9: 8 | E9: 8 | F9: Pull-Out for Paint | G9: əd | I9: 357 | N9: 45646
A10: 9 | B10: 11-9 | C10: 11 | D10: 7 | E10: 9 | F10: Tensile testing of embedded rebar | G10: əd | I10: 215 | N10: 45646
A11: 10 | B11: 14-1 | C11: 14 | D11: o-1 | E11: 1 | F11: 44 KVA (YT22100145) | G11: ay | I11: 730 | N11: 45652
A12: 11 | B12: 14-2 | C12: 14 | D12: o-1 | E12: 2 | F12: 110 KVA (YT19105911) | G12: ay | I12: 1100 | N12: 45652
A13: 12 | B13: 14-3 | C13: 14 | D13: 1 | E13: 3 | F13: 75 KVA (YT21225224) | G13: ay | I13: 900 | N13: 45652
A14: 13 | B14: 14-4 | C14: 14 | D14: o-1 | E14: 4 | F14: 50 KVA (YT05103727) | G14: ay | I14: 800 | N14: 45652
A15: 14 | B15: 14-5 | C15: 14 | D15: o-1 | E15: 5 | F15: 70 KVA | G15: ay | I15: 900 | N15: 45652
A16: 15 | B16: 14-6 | C16: 14 | D16: 1 | E16: 6 | F16: 490 KVA (EA20A100709) | G16: ay | I16: 4000 | N16: 45652
A17: 16 | B17: 14-7 | C17: 14 | D17: 2 | E17: 7 | F17: 75 KVA (YT24124975) | G17: ay | I17: 900 | N17: 45652
A18: 17 | B18: 14-8 | C18: 14 | D18: o-1 | E18: 8 | F18: 44 KVA Maintenance Fee | G18: hour | I18: 2 | N18: 45652
A19: 18 | B19: 14-9 | C19: 14 | D19: o-1 | E19: 9 | F19: 110 KVA Maintenance Fee | G19: hour | I19: 2.5 | N19: 45652
A20: 19 | B20: 14-10 | C20: 14 | D20: 1 | E20: 10 | F20: 75 KVA Maintenance Fee | G20: hour | I20: 2 | N20: 45652
A21: 20 | B21: 14-11 | C21: 14 | D21: o-1 | E21: 11 | F21: 50 KVA Maintenance Fee | G21: hour | I21: 2 | N21: 45652
A22: 21 | B22: 14-12 | C22: 14 | D22: o-1 | E22: 12 | F22: 70 KVA Maintenance Fee | G22: hour | I22: 2 | N22: 45652
A23: 22 | B23: 14-13 | C23: 14 | D23: 1 | E23: 13 | F23: 490 KVA Maintenance Fee | G23: hour | I23: 4 | N23: 45652
A24: 23 | B24: 14-14 | C24: 14 | D24: 3 | E24: 14 | F24: 75 KVA Maintenance Fee | G24: hour | I24: 2 | N24: 45652
A25: 24 | B25: 14-15 | C25: 14 | D25: 2 | E25: 15 | F25: AKSA AD 330 KVA | G25: hour | I25: 4000 | N25: 45652
A26: 25 | B26: 14-16 | C26: 14 | D26: 2 | E26: 16 | F26: 330 KVA Maintenance Fee | G26: hour | I26: 3.5 | N26: 45652
A27: 26 | B27: 30-1 | C27: 30 | D27: 0 | E27: 1 | F27: AMBULANCE - 99AS882-day | G27: single | H27: FALSE | I27: =K27/J27 -> 183.33333 | J27: 30 | K27: 5500 | M27: 99AS882 | N27: 45658 | O27: İbrahim Kemik
A28: 27 | B28: 30-2 | C28: 30 | D28: 0 | E28: 2 | F28: AMBULANCE - 99JE233-day | G28: single | H28: FALSE | I28: =K28/J28 -> 183.33333 | J28: 30 | K28: 5500 | M28: 99JE233 | N28: 45679 | O28: İbrahim Kemik
A29: 28 | B29: 30-3 | C29: 30 | D29: 0 | E29: 3 | F29: AMBULANCE - 99AS882 | G29: month | I29: 5500 | M29: 99AS882 | N29: 45658 | O29: İbrahim Kemik
A30: 29 | B30: 30-4 | C30: 30 | D30: 0 | E30: 4 | F30: AMBULANCE - 99JE233 | G30: month | I30: 5500 | M30: 99JE233 | N30: 45679 | O30: İbrahim Kemik
A31: 30 | B31: 31-1 | C31: 31 | D31: 1 | E31: 1 | F31: SERVICE - 99LT168 - Baku-single | G31: single | I31: 73.33 | J31: 30 | L31: 18 | M31: 99LT168 | N31: 45658 | O31: İbrahim Kemik
A32: 31 | B32: 31-2 | C32: 31 | D32: 1 | E32: 2 | F32: SERVICE - 99LT168 - Baku-hour | G32: hour | I32: 7.333 | L32: 18 | M32: 99LT168 | N32: 45658 | O32: İbrahim Kemik
A33: 32 | B33: 31-3 | C33: 31 | D33: 1 | E33: 3 | F33: SERVICE - 99HZ395 - Sumqayıt-single | G33: single | I33: 65 | J33: 28 | K33: =I33*J33 -> 1820 | L33: 18 | M33: 99HZ395 | N33: 45658 | O33: İbrahim Kemik
A34: 33 | B34: 31-4 | C34: 31 | D34: 1 | E34: 4 | F34: SERVICE - 99HZ395 - Sumqayıt-hour | G34: hour | I34: 6.5 | L34: 18 | M34: 99HZ395 | N34: 45658 | O34: İbrahim Kemik
A35: 34 | B35: 31-5 | C35: 31 | D35: 1 | E35: 5 | F35: SERVICE - 90OV187 - Baku-single | G35: single | I35: 73.33 | J35: 30 | L35: 18 | M35: 90OV187 | N35: 45658 | O35: İbrahim Kemik
A36: 35 | B36: 31-6 | C36: 31 | D36: 1 | E36: 6 | F36: SERVICE - 90OV187 - Baku-hour | G36: hour | I36: 7.333 | L36: 18 | M36: 90OV187 | N36: 45658 | O36: İbrahim Kemik
A37: 36 | B37: 31-7 | C37: 31 | D37: 1 | E37: 7 | F37: SERVICE - 77UG347 - Sumqayıt-single | G37: single | I37: 65 | J37: 30 | M37: 77UG347 | N37: 45658 | O37: İbrahim Kemik
A38: 37 | B38: 31-8 | C38: 31 | D38: 1 | E38: 8 | F38: SERVICE - 77UG347 - Sumqayıt-hour | G38: hour | I38: 6.5 | M38: 77UG347 | N38: 45658 | O38: İbrahim Kemik
A39: 38 | B39: 31-9 | C39: 31 | D39: 1 | E39: 9 | F39: SERVICE - 99FB123 - Baku-single | G39: single | I39: 73.33 | J39: 30 | M39: 99FB123 | N39: 45658 | O39: İbrahim Kemik
A40: 39 | B40: 31-10 | C40: 31 | D40: 1 | E40: 10 | F40: SERVICE - 99FB123 - Baku-hour | G40: hour | I40: 7.333 | M40: 99FB123 | N40: 45658 | O40: İbrahim Kemik
A41: 40 | B41: 31-11 | C41: 31 | D41: 1 | E41: 11 | F41: SERVICE - 90ZP408 - Site-single | G41: single | I41: 55.36 | J41: 28 | L41: 15 | M41: 90ZP408 | N41: 45658 | O41: İbrahim Kemik
A42: 41 | B42: 31-12 | C42: 31 | D42: 1 | E42: 12 | F42: SERVICE - 90ZP408 - Site-hour | G42: hour | I42: 5.536 | L42: 15 | M42: 90ZP408 | N42: 45658 | O42: İbrahim Kemik
A43: 42 | B43: 31-13 | C43: 31 | D43: 1 | E43: 13 | F43: SERVICE - 77AT386 - Procurement-single | G43: single | I43: 46.67 | J43: 30 | K43: =I43*J43 -> 1400.1 | L43: 15 | M43: 77AT386 | N43: 45658 | O43: İbrahim Kemik
A44: 43 | B44: 31-14 | C44: 31 | D44: 1 | E44: 14 | F44: SERVICE - 77AT386 - Procurement-hour | G44: hour | I44: 4.667 | L44: 15 | M44: 77AT386 | N44: 45658 | O44: İbrahim Kemik
A45: 44 | B45: 31-15 | C45: 31 | D45: 1 | E45: 15 | F45: SERVICE - 66CC029 - Site-single | G45: single | I45: 55.36 | J45: 28 | L45: 15 | M45: 66CC029 | N45: 45658 | O45: İbrahim Kemik
A46: 45 | B46: 31-16 | C46: 31 | D46: 1 | E46: 16 | F46: SERVICE - 66CC029 - Site-hour | G46: hour | I46: 5.536 | L46: 15 | M46: 66CC029 | N46: 45658 | O46: İbrahim Kemik
A47: 46 | B47: 31-17 | C47: 31 | D47: 1 | E47: 17 | F47: GARBAGE TRUCK - 77QK725-single | G47: single | I47: 275 | J47: 28 | M47: 77QK725 | N47: 45658 | O47: İbrahim Kemik
A48: 47 | B48: 31-18 | C48: 31 | D48: 1 | E48: 18 | F48: GARBAGE TRUCK - 77QK725-hour | G48: hour | I48: 27.5 | M48: 77QK725 | N48: 45658 | O48: İbrahim Kemik
A49: 48 | B49: 31-19 | C49: 31 | D49: 1 | E49: 19 | F49: SERVICE - 90SL686 - Aeroport-single | G49: single | I49: 58.93 | J49: 28 | L49: 12 | M49: 90SL686 | N49: 45693 | O49: İbrahim Kemik
A50: 49 | B50: 31-20 | C50: 31 | D50: 1 | E50: 20 | F50: SERVICE - 90SL686 - Aeroport-hour | G50: hour | I50: 5.893 | L50: 12 | M50: 90SL686 | N50: 45693 | O50: İbrahim Kemik
A51: 50 | B51: 31-21 | C51: 31 | D51: 15 | E51: 21 | F51: Pickup - 77DK884 - Double Cab (Remez)-single | G51: single | I51: 96.43 | J51: 28 | M51: 77DK884 | N51: 45693 | O51: İbrahim Kemik
A52: 51 | B52: 31-22 | C52: 31 | D52: 15 | E52: 22 | F52: Pickup - 77DK884 - Double Cab (Remez)-hour | G52: hour | I52: 9.643 | M52: 77DK884 | N52: 45693 | O52: İbrahim Kemik
A53: 52 | B53: 31-23 | C53: 31 | D53: 15 | E53: 23 | F53: Pickup - 50FB264 - Van-single | G53: single | I53: 66.07 | J53: 28 | L53: 15 | M53: 50FB264 | N53: 45693 | O53: İbrahim Kemik
A54: 53 | B54: 31-24 | C54: 31 | D54: 15 | E54: 24 | F54: Pickup - 50FB264 - Van-hour | G54: hour | I54: 6.607 | L54: 15 | M54: 50FB264 | N54: 45693 | O54: İbrahim Kemik
A55: 54 | B55: 31-25 | C55: 31 | D55: 7 | E55: 25 | F55: SERVICE - 01CC689 - Site-hour | G55: hour | I55: 5.536 | L55: 15 | M55: 01CC689 | N55: 45693 | O55: İbrahim Kemik
A56: 55 | B56: 31-26 | C56: 31 | D56: 7 | E56: 26 | F56: SERVICE - 01CC689 - Site-single | G56: single | I56: 55.36 | J56: 28 | L56: 15 | M56: 01CC689 | N56: 45693 | O56: İbrahim Kemik
A57: 56 | B57: 31-27 | C57: 31 | D57: 16 | E57: 27 | F57: SERVICE - 10NS184 - Site-hour | G57: hour | I57: 5.536 | L57: 15 | M57: 10NS184 | N57: 45693 | O57: İbrahim Kemik
A58: 57 | B58: 31-28 | C58: 31 | D58: 16 | E58: 28 | F58: SERVICE - 10NS184 - Site-single | G58: single | I58: 55.36 | J58: 28 | L58: 15 | M58: 10NS184 | N58: 45693 | O58: İbrahim Kemik
A59: 58 | B59: 31-29 | C59: 31 | D59: 2 | E59: 29 | F59: SERVICE - 10RN527 - Site-hour | G59: hour | I59: 5.536 | L59: 15 | M59: 10RN527 | N59: 45693 | O59: İbrahim Kemik
A60: 59 | B60: 31-30 | C60: 31 | D60: 12 | E60: 30 | F60: SERVICE - 10RN527 - Site_v1-hour | G60: hour | I60: 6.25 | L60: 15 | M60: 10RN527 | N60: 45870 | O60: İbrahim Kemik
A61: 60 | B61: 31-31 | C61: 31 | D61: 2 | E61: 31 | F61: SERVICE - 10RN527 - Site-single | G61: single | I61: 55.36 | J61: 28 | L61: 15 | M61: 10RN527 | N61: 45693 | O61: İbrahim Kemik
A62: 61 | B62: 31-32 | C62: 31 | D62: 12 | E62: 32 | F62: SERVICE - 10RN527 - Site_v1-single | G62: single | I62: 62.5 | J62: 28 | L62: 15 | M62: 10RN527 | N62: 45870 | O62: İbrahim Kemik
A63: 62 | B63: 31-33 | C63: 31 | D63: 16 | E63: 33 | F63: SERVICE - 10ZS260 - Site-single | G63: single | I63: 66.67 | J63: 30 | L63: 15 | M63: 10ZS260 | N63: 45693 | O63: İbrahim Kemik
A64: 63 | B64: 31-34 | C64: 31 | D64: 2 | E64: 34 | F64: SERVICE - 15BZ942 - Site-hour | G64: hour | I64: 5.536 | L64: 15 | M64: 15BZ942 | N64: 45693 | O64: İbrahim Kemik
A65: 64 | B65: 31-35 | C65: 31 | D65: 2 | E65: 35 | F65: SERVICE - 15BZ942 - Site-single | G65: single | I65: 55.36 | J65: 28 | L65: 15 | M65: 15BZ942 | N65: 45693 | O65: İbrahim Kemik
A66: 65 | B66: 31-36 | C66: 31 | D66: 15 | E66: 36 | F66: SERVICE - 17BE358 - Site-hour | G66: hour | I66: 5.536 | L66: 15 | M66: 17BE358 | N66: 45693 | O66: İbrahim Kemik
A67: 66 | B67: 31-37 | C67: 31 | D67: 15 | E67: 37 | F67: SERVICE - 17BE358 - Site-single | G67: single | I67: 55.36 | J67: 28 | L67: 15 | M67: 17BE358 | N67: 45693 | O67: İbrahim Kemik
A68: 67 | B68: 31-38 | C68: 31 | D68: 15 | E68: 38 | F68: SERVICE - 21BF442 - Site-hour | G68: hour | I68: 5.536 | L68: 15 | M68: 21BF442 | N68: 45693 | O68: İbrahim Kemik
A69: 68 | B69: 31-39 | C69: 31 | D69: 15 | E69: 39 | F69: SERVICE - 21BF442 - Site-single | G69: single | I69: 55.36 | J69: 28 | L69: 15 | M69: 21BF442 | N69: 45693 | O69: İbrahim Kemik
A70: 69 | B70: 31-40 | C70: 31 | D70: 3 | E70: 40 | F70: SERVICE - 50BD165 - Site-hour | G70: hour | I70: 5.536 | L70: 15 | M70: 50BD165 | N70: 45693 | O70: İbrahim Kemik
A71: 70 | B71: 31-41 | C71: 31 | D71: 3 | E71: 41 | F71: SERVICE - 50BD165 - Site-single | G71: single | I71: 55.36 | J71: 28 | L71: 15 | M71: 50BD165 | N71: 45693 | O71: İbrahim Kemik
A72: 71 | B72: 31-42 | C72: 31 | D72: 8 | E72: 42 | F72: SERVICE - 50BN724 - Site-hour | G72: hour | I72: 6.607 | L72: 18 | M72: 50BN724 | N72: 45693 | O72: İbrahim Kemik
A73: 72 | B73: 31-43 | C73: 31 | D73: 8 | E73: 43 | F73: SERVICE - 50BN724 - Site-single | G73: single | I73: 66.07 | J73: 28 | L73: 18 | M73: 50BN724 | N73: 45693 | O73: İbrahim Kemik
A74: 73 | B74: 31-44 | C74: 31 | D74: 12 | E74: 44 | F74: SERVICE - 50CN929 - Site-hour | G74: hour | I74: 5.536 | L74: 15 | M74: 50CN929 | N74: 45693 | O74: İbrahim Kemik
A75: 74 | B75: 31-45 | C75: 31 | D75: 12 | E75: 45 | F75: SERVICE - 50CN929 - Site-single | G75: single | I75: 55.36 | J75: 28 | L75: 15 | M75: 50CN929 | N75: 45693 | O75: İbrahim Kemik
A76: 75 | B76: 31-46 | C76: 31 | D76: 2 | E76: 46 | F76: SERVICE - 50DK730 - Site-hour | G76: hour | I76: 5.536 | L76: 15 | M76: 50DK730 | N76: 45693 | O76: İbrahim Kemik
A77: 76 | B77: 31-47 | C77: 31 | D77: 2 | E77: 47 | F77: SERVICE - 50DK730 - Site-single | G77: single | I77: 55.36 | J77: 28 | L77: 15 | M77: 50DK730 | N77: 45693 | O77: İbrahim Kemik
A78: 77 | B78: 31-48 | C78: 31 | D78: 12 | E78: 48 | F78: SERVICE - 50EF902 - Site-hour | G78: hour | I78: 6.25 | L78: 15 | M78: 50EF902 | N78: 45693 | O78: İbrahim Kemik
A79: 78 | B79: 31-49 | C79: 31 | D79: 12 | E79: 49 | F79: SERVICE - 50EF902 - Site-single | G79: single | I79: 62.5 | J79: 28 | L79: 15 | M79: 50EF902 | N79: 45693 | O79: İbrahim Kemik
A80: 79 | B80: 31-50 | C80: 31 | D80: 2 | E80: 50 | F80: SERVICE - 52BK688 - Site-hour | G80: hour | I80: 5.536 | L80: 15 | M80: 52BK688 | N80: 45693 | O80: İbrahim Kemik
A81: 80 | B81: 31-51 | C81: 31 | D81: 2 | E81: 51 | F81: SERVICE - 52BK688 - Site-single | G81: single | I81: 55.36 | J81: 28 | L81: 15 | M81: 52BK688 | N81: 45693 | O81: İbrahim Kemik
A82: 81 | B82: 31-52 | C82: 31 | D82: 4 | E82: 52 | F82: SERVICE - 53BB774 - Site-hour | G82: hour | I82: 0 | L82: 15 | M82: 53BB774 | N82: 45693 | O82: İbrahim Kemik
A83: 82 | B83: 31-53 | C83: 31 | D83: 4 | E83: 53 | F83: SERVICE - 53BB774 - Site-single | G83: single | I83: 55.36 | J83: 28 | L83: 15 | M83: 53BB774 | N83: 45693 | O83: İbrahim Kemik
A84: 83 | B84: 31-54 | C84: 31 | D84: 15 | E84: 54 | F84: SERVICE - 53BD338 - Site-hour | G84: hour | I84: 5.536 | L84: 15 | M84: 53BD338 | N84: 45693 | O84: İbrahim Kemik
A85: 84 | B85: 31-55 | C85: 31 | D85: 15 | E85: 55 | F85: SERVICE - 53BD338 - Site-single | G85: single | I85: 55.36 | J85: 28 | L85: 15 | M85: 53BD338 | N85: 45693 | O85: İbrahim Kemik
A86: 85 | B86: 31-56 | C86: 31 | D86: 2 | E86: 56 | F86: SERVICE - 55CB633 - Site-hour | G86: hour | I86: 5.536 | L86: 15 | M86: 55CB633 | N86: 45693 | O86: İbrahim Kemik
A87: 86 | B87: 31-57 | C87: 31 | D87: 2 | E87: 57 | F87: SERVICE - 55CB633 - Site-single | G87: single | I87: 55.36 | J87: 28 | K87: =I87*J87 -> 1550.08 | L87: 15 | M87: 55CB633 | N87: 45693 | O87: İbrahim Kemik
A88: 87 | B88: 31-58 | C88: 31 | D88: 2 | E88: 58 | F88: SERVICE - 77ET143 - Site-hour | G88: hour | I88: 5.536 | L88: 15 | M88: 77ET143 | N88: 45693 | O88: İbrahim Kemik
A89: 88 | B89: 31-59 | C89: 31 | D89: 2 | E89: 59 | F89: SERVICE - 77ET143 - Site-single | G89: single | I89: 55.36 | J89: 28 | L89: 15 | M89: 77ET143 | N89: 45693 | O89: İbrahim Kemik
A90: 89 | B90: 31-60 | C90: 31 | D90: 2 | E90: 60 | F90: SERVICE - 77GM723 - Site-hour | G90: hour | I90: 5.536 | L90: 15 | M90: 77GM723 | N90: 45693 | O90: İbrahim Kemik
A91: 90 | B91: 31-61 | C91: 31 | D91: 2 | E91: 61 | F91: SERVICE - 77GM723 - Site-single | G91: single | I91: 55.36 | J91: 28 | L91: 15 | M91: 77GM723 | N91: 45693 | O91: İbrahim Kemik
A92: 91 | B92: 31-62 | C92: 31 | D92: 7 | E92: 62 | F92: SERVICE - 77GR998 - Site-double | G92: double | I92: =K92/J92 -> 91.339286 | J92: 28 | K92: 2557.5 | L92: 15 | M92: 77GR998 | N92: 45809 | O92: İbrahim Kemik
A93: 92 | B93: 31-63 | C93: 31 | D93: 9 | E93: 63 | F93: SERVICE - 77GR998 - Site_v1-double | G93: double | I93: =K93/J93 -> 99.642857 | J93: 28 | K93: 2790 | L93: 15 | M93: 77GR998 | N93: 45839 | O93: İbrahim Kemik
A94: 93 | B94: 31-64 | C94: 31 | D94: 7 | E94: 64 | F94: SERVICE - 77GR998 - Site-hour | G94: hour | I94: =K94/J94 -> 5.5357143 | J94: =28*10 -> 280 | K94: 1550 | L94: 15 | M94: 77GR998 | N94: 45693 | O94: İbrahim Kemik
A95: 94 | B95: 31-65 | C95: 31 | D95: 7 | E95: 65 | F95: SERVICE - 77GR998 - Site-single | G95: single | I95: =K95/J95 -> 55.357143 | J95: 28 | K95: 1550 | L95: 15 | M95: 77GR998 | N95: 45693 | O95: İbrahim Kemik
A96: 95 | B96: 31-66 | C96: 31 | D96: 15 | E96: 66 | F96: SERVICE - 77PV619 - Procurement-hour | G96: hour | I96: 4 | M96: 77PV619 | N96: 45693 | O96: İbrahim Kemik
A97: 96 | B97: 31-67 | C97: 31 | D97: 15 | E97: 67 | F97: SERVICE - 77PV619 - Procurement-single | G97: single | I97: 40 | J97: 30 | M97: 77PV619 | N97: 45693 | O97: İbrahim Kemik
A98: 97 | B98: 31-68 | C98: 31 | D98: 3 | E98: 68 | F98: SERVICE - 77QE133 - Baku-hour | G98: hour | I98: 7.333 | L98: 18 | M98: 77QE133 | N98: 45693 | O98: İbrahim Kemik
A99: 98 | B99: 31-69 | C99: 31 | D99: 3 | E99: 69 | F99: SERVICE - 77QE133 - Baku-single | G99: single | I99: 73.33 | J99: 30 | L99: 18 | M99: 77QE133 | N99: 45693 | O99: İbrahim Kemik
A100: 99 | B100: 31-70 | C100: 31 | D100: 2 | E100: 70 | F100: SERVICE - 77RN868 - Baku-hour | G100: hour | I100: 7.333 | L100: 18 | M100: 77RN868 | N100: 45693 | O100: İbrahim Kemik
...

Sheet log_fuel_provision
A1: Date | B1: Contract no | C1: Plateno | D1: Quantity | E1: Amount | F1: Recorded by
A2: 45992 | B2: 31 | C2: 90RC631 | D2: 28 | E2: {=D2:D301*1} -> 28
A3: 45992 | B3: 31 | C3: 10RN527 | D3: 65 | E3: 65
A4: 45992 | B4: 31 | C4: 99UK314 | D4: 55 | E4: 55
A5: 45992 | B5: 31 | C5: 53BD338 | D5: 66 | E5: 66
A6: 45992 | B6: 31 | C6: 50DK730 | D6: 52 | E6: 52
A7: 45992 | B7: 31 | C7: 99LM412 | D7: 46 | E7: 46
A8: 45992 | B8: 31 | C8: 21BF442 | D8: 33 | E8: 33
A9: 45992 | B9: 31 | C9: 99MN472 | D9: 49 | E9: 49
A10: 45992 | B10: 31 | C10: 50BN724 | D10: 42 | E10: 42
A11: 45992 | B11: 31 | C11: 99DX531 | D11: 15 | E11: 15
A12: 45993 | B12: 31 | C12: 55CB633 | D12: 53 | E12: 53
A13: 45993 | B13: 31 | C13: 50EF902 | D13: 38 | E13: 38
A14: 45993 | B14: 31 | C14: 99FO779 | D14: 80 | E14: 80
... A301: 46021 | B301: 31 | C301: 90OE402 | D301: 6 | E301: 6
A302: 46023 | B302: 31 | C302: 77MU119 | D302: 200 | E302: {=IF(F302:F855="Accounting",1,1.1)*D302:D855} -> 200 | F302: Accounting | G302: x
A303: 46023 | B303: 31 | C303: 99MN472 | D303: 45 | E303: 49.5
A304: 46023 | B304: 31 | C304: 50DK730 | D304: 22 | E304: 24.2
A305: 46023 | B305: 31 | C305: 10RN527 | D305: 51 | E305: 56.1
A306: 46023 | B306: 31 | C306: 77TG971 | D306: 59 | E306: 64.9
A307: 46023 | B307: 31 | C307: 10NS184 | D307: 45 | E307: 49.5
A308: 46023 | B308: 31 | C308: 99BT339 | D308: 25 | E308: 27.5
A309: 46023 | B309: 31 | C309: 55CB633 | D309: 58 | E309: 63.8
A310: 46023 | B310: 31 | C310: 99UK314 | D310: 79 | E310: 86.9
A311: 46023 | B311: 31 | C311: 99KL663 | D311: 55 | E311: 60.5
A312: 46024 | B312: 31 | C312: 99HZ395 | D312: 67 | E312: 73.7
A313: 46024 | B313: 31 | C313: 99GZ612 | D313: 37 | E313: 40.7
A314: 46024 | B314: 31 | C314: 90EC344 | D314: 70 | E314: 77
... A567: 46025 | B567: 31 | C567: 90EC344 | D567: 10 | E567: 11
A568: 46025 | B568: 31 | C568: 77AT386 | D568: 600 | E568: 600 | F568: Accounting
A569: 46025 | B569: 31 | C569: 90PY548 | D569: 750 | E569: 750 | F569: Accounting
A570: 46025 | B570: 31 | C570: 90OE402 | D570: 639 | E570: 639 | F570: Accounting
A571: 46025 | B571: 31 | C571: 77PV659 | D571: 107 | E571: 107 | F571: Accounting
A572: 46054 | B572: 31 | C572: 50EF902 | D572: 64 | E572: 70.4
A573: 46054 | B573: 31 | C573: 77UR032 | D573: 55 | E573: 60.5
A574: 46054 | B574: 31 | C574: 38BG860 | D574: 54 | E574: 59.4
A575: 46054 | B575: 31 | C575: 99BT339 | D575: 58 | E575: 63.8
A576: 46054 | B576: 31 | C576: 10ZU722 | D576: 65 | E576: 71.5
A577: 46054 | B577: 31 | C577: 90EC344 | D577: 68 | E577: 74.8
A578: 46054 | B578: 31 | C578: 90UX686 | D578: 61 | E578: 67.1
A579: 46054 | B579: 31 | C579: 10RN527 | D579: 46 | E579: 50.6
A580: 46054 | B580: 31 | C580: 50DK730 | D580: 47 | E580: 51.7
A581: 46054 | B581: 31 | C581: 99MN472 | D581: 23 | E581: 25.3
A582: 46054 | B582: 31 | C582: 99LM412 | D582: 19 | E582: 20.9
A583: 46054 | B583: 31 | C583: 99OR961 | D583: 46 | E583: 50.6
... A724: 46069 | B724: 31 | C724: 21BF442 | D724: 24 | E724: 26.4
A725: 46070 | B725: 31 | C725: 77UR032 | E725: 0
A726: 46070 | B726: 31 | C726: 10RN527 | D726: 54 | E726: 59.4
A727: 46070 | B727: 31 | C727: 21BF442 | D727: 60 | E727: 66
A728: 46070 | B728: 31 | C728: 50DK730 | D728: 26 | E728: 28.6
A729: 46070 | B729: 31 | C729: 53BD239 | D729: 31 | E729: 34.1
A730: 46070 | B730: 31 | C730: 77GR998 | D730: 52 | E730: 57.2
A731: 46070 | B731: 31 | C731: 38BG860 | D731: 65 | E731: 71.5
A732: 46070 | B732: 31 | C732: 99CN447 | D732: 59 | E732: 64.9
A733: 46071 | B733: 31 | C733: 50EF902 | D733: 59 | E733: 64.9
A734: 46071 | B734: 31 | C734: 21BF442 | D734: 28 | E734: 30.8
A735: 46071 | B735: 31 | C735: 99UK314 | D735: 57 | E735: 62.7
A736: 46071 | B736: 31 | C736: 99LM412 | D736: 39 | E736: 42.9
A737: 46071 | B737: 31 | C737: 50DK730 | D737: 31 | E737: 34.1
... A847: 46081 | B847: 31 | C847: 99MN472 | D847: 27 | E847: 29.7
A848: 46057 | B848: 31 | C848: 77YL852 | D848: 265 | E848: 265 | F848: Accounting
A849: 46067 | B849: 31 | C849: 90YG742 | D849: 500 | E849: 500 | F849: Accounting
A850: 46069 | B850: 31 | C850: 90YG746 | D850: 500 | E850: 500 | F850: Accounting
A851: 46069 | B851: 31 | C851: 77JS132 | D851: 400 | E851: 400 | F851: Accounting
A852: 46069 | B852: 31 | C852: 90OE402 | D852: 500 | E852: 500 | F852: Accounting
A853: 46073 | B853: 31 | C853: 77MU119 | D853: 300 | E853: 300 | F853: Accounting
A854: 46076 | B854: 31 | C854: 90PY548 | D854: 500 | E854: 500 | F854: Accounting
A855: 46081 | B855: 31 | C855: 90YG745 | D855: 500 | E855: 500 | F855: Accounting

Sheet daily_quantities
A1: # | B1: year | C1: month | D1: contract no | E1: ipc no | F1: plate no | G1: quantity | H1: price type | I1: notes | J1: price no | K1: date
A2: {=_xlfn.SEQUENCE(ROWS(_xlfn.ANCHORARRAY(B2)))} -> 1 | B2: {=_xlfn._xlws.SORT(_xlfn.LET(_xlpm.getData,_xlfn.LAMBDA(_xlpm.type,_xlfn.LET( _xlpm.t, TRIM(CLEAN(_xlpm.type)), _xlpm.quantityCol, _xlfn.SWITCH(_xlpm.t, "single", log_daily_records!AM:AM, "double", log_daily_records!AN:AN, "hour", log_daily_records!AO:AO ), _xlpm.cond, (IFERROR(_xlpm.quantityCol,"")<>"") * (IFERROR(_xlpm.quantityCol,0)<>0), _xlfn.IFNA( _xlfn.DROP(_xlfn._xlws.FILTER(_xlfn.HSTACK(log_daily_records!B:C, log_daily_records!E:F, log_daily_records!D:D, _xlpm.quantityCol, ""),_xlpm.cond),1), _xlpm.t ) )),_xlfn.VSTACK(_xlpm.getData("single"),_xlpm.getData("double"),_xlpm.getData("hour"))),{4,3,2,1})} -> 2025 | C2: 1 | D2: 30 | E2: 1 | F2: 99AS882 | G2: 10 | H2: single | J2: {=_xlfn.MAKEARRAY(ROWS(_xlfn.ANCHORARRAY(B2)),1,_xlfn.LAMBDA(_xlpm.r,_xlpm.c,_xlfn.XLOOKUP(1,(_xlfn._TRO_TRAILING(log_prices!C:C)=INDEX(_xlfn.ANCHORARRAY(B2),_xlpm.r,3))*(_xlfn._TRO_TRAILING(log_prices!G:G)=INDEX(_xlfn.ANCHORARRAY(B2),_xlpm.r,7))*(_xlfn._TRO_TRAILING(log_prices!M:M)=INDEX(_xlfn.ANCHORARRAY(B2),_xlpm.r,5))*(_xlfn._TRO_TRAILING(log_prices!N:N)<=INDEX(_xlfn.ANCHORARRAY(K2),_xlpm.r)),_xlfn._TRO_TRAILING(log_prices!E:E),,0,-1)))} -> 1 | K2: {=DATE(INDEX(_xlfn.ANCHORARRAY(B2),,1),INDEX(_xlfn.ANCHORARRAY(B2),,2),1)} -> 45658
A3: 2 | B3: 2025 | C3: 1 | D3: 31 | E3: 1 | F3: 99LT168 | G3: 8 | H3: single | J3: 1 | K3: 45658
A4: 3 | B4: 2025 | C4: 1 | D4: 31 | E4: 1 | F4: 99HZ395 | G4: 3 | H4: single | J4: 3 | K4: 45658
A5: 4 | B5: 2025 | C5: 2 | D5: 31 | E5: 1 | F5: 99LT168 | G5: 28 | H5: single | J5: 1 | K5: 45689
A6: 5 | B6: 2025 | C6: 2 | D6: 31 | E6: 1 | F6: 99HZ395 | G6: 28 | H6: single | J6: 3 | K6: 45689
A7: 6 | B7: 2025 | C7: 2 | D7: 31 | E7: 1 | F7: 99FB123 | G7: 6 | H7: single | J7: 9 | K7: 45689
A8: 7 | B8: 2025 | C8: 2 | D8: 31 | E8: 1 | F8: 90OV187 | G8: 17 | H8: single | J8: 5 | K8: 45689
A9: 8 | B9: 2025 | C9: 2 | D9: 31 | E9: 1 | F9: 77UG347 | G9: 6 | H9: single | J9: 7 | K9: 45689
A10: 9 | B10: 2025 | C10: 2 | D10: 31 | E10: 1 | F10: 90ZP408 | G10: 17 | H10: single | J10: 11 | K10: 45689
A11: 10 | B11: 2025 | C11: 2 | D11: 31 | E11: 1 | F11: 66CC029 | G11: 19 | H11: single | J11: 15 | K11: 45689
A12: 11 | B12: 2025 | C12: 2 | D12: 31 | E12: 1 | F12: 77QK725 | G12: 7 | H12: single | J12: 17 | K12: 45689
A13: 12 | B13: 2025 | C13: 2 | D13: 31 | E13: 1 | F13: 77AT386 | G13: 9 | H13: single | J13: 13 | K13: 45689
A14: 13 | B14: 2025 | C14: 2 | D14: 31 | E14: 1 | F14: 99LT168 | G14: 2 | H14: hour | J14: 2 | K14: 45689
... A829: 828 | B829: 2026 | C829: 3 | D829: 31 | E829: 14 | F829: 90GG153 | G829: 15 | H829: hour | J829: 203 | K829: 46082

Sheet quantities
A1: # | B1: year | C1: month | D1: contract no | E1: ipc no | F1: plate no | G1: quantity | H1: price type | I1: notes | J1: price no | K1: Price | L1: Amount | O1: LET(y,LET(x,DROP(VSTACK(daily_quantities!B:.J,DROP(log_monthly_records!B:.J,1)),1),IF(x="","",SORT(x, {1,2,3,4}, {1,1,1,1}))),IF(y=0,"",y)) | AA1: {=_xlfn.LET( _xlpm.last, MATCH(2,1/(log_daily_records!E:E<>""),1), _xlpm.e, log_daily_records!E2:INDEX(log_daily_records!E:E,_xlpm.last), _xlpm.F, log_daily_records!F2:INDEX(log_daily_records!F:F,_xlpm.last), _xlpm.d, log_daily_records!D2:INDEX(log_daily_records!D:D,_xlpm.last), _xlpm.AM,log_daily_records!AM2:INDEX(log_daily_records!AM:AM,_xlpm.last), _xlpm.AN,log_daily_records!AN2:INDEX(log_daily_records!AN:AN,_xlpm.last), _xlpm.AO,log_daily_records!AO2:INDEX(log_daily_records!AO:AO,_xlpm.last), _xlpm.AT,log_daily_records!AS2:INDEX(log_daily_records!AS:AS,_xlpm.last), _xlfn.VSTACK( _xlfn.IFNA(_xlfn._xlws.FILTER(_xlfn.HSTACK(_xlpm.e,_xlpm.F,_xlpm.d,_xlpm.AM,""),_xlpm.AM>0),"single"), _xlfn.IFNA(_xlfn._xlws.FILTER(_xlfn.HSTACK(_xlpm.e,_xlpm.F,_xlpm.d,_xlpm.AN,""),_xlpm.AN>0),"double"), _xlfn.IFNA(_xlfn._xlws.FILTER(_xlfn.HSTACK(_xlpm.e,_xlpm.F,_xlpm.d,_xlpm.AO,""),_xlpm.AO>0),"hour"), _xlfn.IFNA(_xlfn._xlws.FILTER(_xlfn.HSTACK(_xlpm.e,_xlpm.F,_xlpm.d,_xlpm.AT,""),_xlpm.AT>0),"dist") ) )} -> 30 | AB1: 1 | AC1: 99AS882 | AD1: 10 | AE1: single
A2: {=_xlfn.SEQUENCE(ROWS(_xlfn.ANCHORARRAY(B2)))} -> 1 | B2: {=_xlfn.DROP(_xlfn.VSTACK(_xlfn._TRO_TRAILING(daily_quantities!B:J),_xlfn.DROP(_xlfn._TRO_TRAILING(log_monthly_records!B:J),1)),1)} -> 2025 | C2: 1 | D2: 30 | E2: 1 | F2: 99AS882 | G2: 10 | H2: single | I2: 0 | J2: 1 | K2: {=_xlfn.XLOOKUP(INDEX(_xlfn.ANCHORARRAY(B2),,3)&"-"&INDEX(_xlfn.ANCHORARRAY(B2),,9),_xlfn._TRO_TRAILING(log_prices!B:B),_xlfn._TRO_TRAILING(log_prices!I:I),,0)} -> 183.33333 | L2: {=_xlfn.LET(_xlpm.d,INDEX(_xlfn.ANCHORARRAY(B2),,6),_xlpm.d*_xlfn.ANCHORARRAY(K2))} -> 1833.3333 | AA2: 30 | AB2: 2 | AC2: 99AS882 | AD2: 30 | AE2: single
A3: 2 | B3: 2025 | C3: 1 | D3: 31 | E3: 1 | F3: 99LT168 | G3: 8 | H3: single | I3: 0 | J3: 1 | K3: 73.33 | L3: 586.64 | AA3: 30 | AB3: 2 | AC3: 99JE233 | AD3: 30 | AE3: single
A4: 3 | B4: 2025 | C4: 1 | D4: 31 | E4: 1 | F4: 99HZ395 | G4: 3 | H4: single | I4: 0 | J4: 3 | K4: 65 | L4: 195 | AA4: 31 | AB4: 1 | AC4: 99LT168 | AD4: 8 | AE4: single
A5: 4 | B5: 2025 | C5: 2 | D5: 31 | E5: 1 | F5: 99LT168 | G5: 28 | H5: single | I5: 0 | J5: 1 | K5: 73.33 | L5: 2053.24 | AA5: 31 | AB5: 1 | AC5: 99LT168 | AD5: 28 | AE5: single
A6: 5 | B6: 2025 | C6: 2 | D6: 31 | E6: 1 | F6: 99HZ395 | G6: 28 | H6: single | I6: 0 | J6: 3 | K6: 65 | L6: 1820 | AA6: 31 | AB6: 1 | AC6: 99HZ395 | AD6: 3 | AE6: single
A7: 6 | B7: 2025 | C7: 2 | D7: 31 | E7: 1 | F7: 99FB123 | G7: 6 | H7: single | I7: 0 | J7: 9 | K7: 73.33 | L7: 439.98 | AA7: 31 | AB7: 1 | AC7: 99HZ395 | AD7: 28 | AE7: single
A8: 7 | B8: 2025 | C8: 2 | D8: 31 | E8: 1 | F8: 90OV187 | G8: 17 | H8: single | I8: 0 | J8: 5 | K8: 73.33 | L8: 1246.61 | AA8: 31 | AB8: 1 | AC8: 99FB123 | AD8: 6 | AE8: single
A9: 8 | B9: 2025 | C9: 2 | D9: 31 | E9: 1 | F9: 77UG347 | G9: 6 | H9: single | I9: 0 | J9: 7 | K9: 65 | L9: 390 | AA9: 31 | AB9: 1 | AC9: 90OV187 | AD9: 17 | AE9: single
A10: 9 | B10: 2025 | C10: 2 | D10: 31 | E10: 1 | F10: 90ZP408 | G10: 17 | H10: single | I10: 0 | J10: 11 | K10: 55.36 | L10: 941.12 | AA10: 31 | AB10: 1 | AC10: 77UG347 | AD10: 6 | AE10: single
A11: 10 | B11: 2025 | C11: 2 | D11: 31 | E11: 1 | F11: 66CC029 | G11: 19 | H11: single | I11: 0 | J11: 15 | K11: 55.36 | L11: 1051.84 | AA11: 31 | AB11: 1 | AC11: 90ZP408 | AD11: 17 | AE11: single
A12: 11 | B12: 2025 | C12: 2 | D12: 31 | E12: 1 | F12: 77QK725 | G12: 7 | H12: single | I12: 0 | J12: 17 | K12: 275 | L12: 1925 | AA12: 31 | AB12: 1 | AC12: 66CC029 | AD12: 19 | AE12: single
A13: 12 | B13: 2025 | C13: 2 | D13: 31 | E13: 1 | F13: 77AT386 | G13: 9 | H13: single | I13: 0 | J13: 13 | K13: 46.67 | L13: 420.03 | AA13: 31 | AB13: 1 | AC13: 77QK725 | AD13: 7 | AE13: single
A14: 13 | B14: 2025 | C14: 2 | D14: 31 | E14: 1 | F14: 99LT168 | G14: 2 | H14: hour | I14: 0 | J14: 2 | K14: 7.333 | L14: 14.666 | AA14: 31 | AB14: 1 | AC14: 77AT386 | AD14: 9 | AE14: single
... A20: 19 | B20: 2025 | C20: 7 | D20: 51 | E20: 1 | F20: 10BA194 | G20: 4 | H20: hour | I20: 0 | J20: 2 | K20: 25 | L20: 100 | AA20: 31 | AB20: 2 | AC20: 77QK725 | AD20: 24 | AE20: single
A21: 20 | B21: 2025 | C21: 4 | D21: 52 | E21: 1 | F21: 10AC750 | G21: 16 | H21: single | I21: 0 | J21: 1 | K21: 375 | L21: 6000 | AA21: 31 | AB21: 2 | AC21: 77QK725 | AE21: single
A22: 21 | B22: 2025 | C22: 4 | D22: 52 | E22: 1 | F22: 10AC750 | G22: 7 | H22: hour | I22: 0 | J22: 2 | K22: 37.5 | L22: 262.5 | AA22: 31 | AB22: 2 | AC22: 77AT386 | AD22: 31 | AE22: single
A23: 22 | B23: 2025 | C23: 5 | D23: 65 | E23: 1 | F23: 01BA176 | G23: 25 | H23: single | I23: 0 | J23: 1 | K23: 196.42857 | L23: 4910.7143 | AA23: 31 | AB23: 2 | AC23: 90SL686 | AD23: 30 | AE23: single
A24: 23 | B24: 2025 | C24: 5 | D24: 65 | E24: 1 | F24: 10BD252 | G24: 22 | H24: single | I24: 0 | J24: 2 | K24: 160.71 | L24: 3535.62 | AA24: 31 | AB24: 2 | AC24: 55CB633 | AD24: 25 | AE24: single
A25: 24 | B25: 2025 | C25: 6 | D25: 85 | E25: 1 | F25: 77SN951 | G25: 15 | H25: single | I25: 0 | J25: 1 | K25: 446.43 | L25: 6696.45 | AA25: 31 | AB25: 2 | AC25: 77GM723 | AD25: 28 | AE25: single
A26: 25 | B26: 2025 | C26: 6 | D26: 85 | E26: 1 | F26: 77SN951 | G26: 26 | H26: hour | I26: 0 | J26: 2 | K26: 44.643 | L26: 1160.718 | AA26: 31 | AB26: 2 | AC26: 99DX531 | AD26: 27 | AE26: single
A27: 26 | B27: 2025 | C27: 6 | D27: 94 | E27: 1 | F27: 54BM823 | G27: 28 | H27: single | I27: 0 | J27: 1 | K27: 125 | L27: 3500 | AA27: 31 | AB27: 2 | AC27: 15BZ942 | AD27: 29 | AE27: single
A28: 27 | B28: 2025 | C28: 7 | D28: 95 | E28: 1 | F28: 54BA209 | G28: 16.5 | H28: single | I28: 0 | J28: 1 | K28: 285.71 | L28: 4714.215 | AA28: 31 | AB28: 2 | AC28: 99BT339 | AD28: 26 | AE28: single
A29: 28 | B29: 2025 | C29: 7 | D29: 98 | E29: 1 | F29: 50BD416 | G29: 12 | H29: single | I29: 0 | J29: 1 | K29: 107.14 | L29: 1285.68 | AA29: 31 | AB29: 2 | AC29: 77ET143 | AD29: 25 | AE29: single
A30: 29 | B30: 2025 | C30: 7 | D30: 99 | E30: 1 | F30: 50BX301 | G30: 10 | H30: single | I30: 0 | J30: 1 | K30: 125 | L30: 1250 | AA30: 31 | AB30: 2 | AC30: 50DK730 | AD30: 28 | AE30: single
A31: 30 | B31: 2025 | C31: 7 | D31: 100 | E31: 1 | F31: 22AB273 | G31: 9 | H31: single | I31: 0 | J31: 1 | K31: 196.42857 | L31: 1767.8571 | AA31: 31 | AB31: 2 | AC31: 99MN472 | AD31: 29 | AE31: single
A32: 31 | B32: 2025 | C32: 8 | D32: 102 | E32: 1 | F32: 99HQ687 | G32: 5 | H32: single | I32: 0 | J32: 1 | K32: 125 | L32: 625 | AA32: 31 | AB32: 2 | AC32: 52BK688 | AD32: 25 | AE32: single
A33: 32 | B33: 2025 | C33: 8 | D33: 110 | E33: 1 | F33: 99XC106 | G33: 6 | H33: single | I33: 0 | J33: 1 | K33: 221.42857 | L33: 1328.5714 | AA33: 31 | AB33: 2 | AC33: 10RN527 | AD33: 18 | AE33: single
... A40: 39 | B40: 2026 | C40: 1 | D40: 164 | E40: 1 | F40: 77DN323 | G40: 35 | H40: hour | I40: 0 | J40: 2 | K40: 39.285714 | L40: 1375 | AA40: 31 | AB40: 3 | AC40: 77QK725 | AD40: 20 | AE40: single
A41: 40 | B41: 2026 | C41: 1 | D41: 172 | E41: 1 | F41: 22T727 | G41: 19 | H41: single | I41: 0 | J41: 1 | K41: 196.42857 | L41: 3732.1429 | AA41: 31 | AB41: 3 | AC41: 77QK725 | AE41: single
A42: 41 | B42: 2026 | C42: 2 | D42: 173 | E42: 1 | F42: 99BQ963 | G42: 29 | H42: single | I42: 0 | J42: 1 | K42: 357.14286 | L42: 10357.143 | AA42: 31 | AB42: 3 | AC42: 77AT386 | AD42: 30 | AE42: single
A43: 42 | B43: 2026 | C43: 2 | D43: 179 | E43: 1 | F43: 10O046 | G43: 4 | H43: single | I43: 0 | J43: 1 | K43: 178.57143 | L43: 714.28571 | AA43: 31 | AB43: 3 | AC43: 90SL686 | AD43: 31 | AE43: single
A44: 43 | B44: 2026 | C44: 3 | D44: 179 | E44: 1 | F44: 10O046 | G44: 19 | H44: single | I44: 0 | J44: 1 | K44: 178.57143 | L44: 3392.8571 | AA44: 31 | AB44: 3 | AC44: 55CB633 | AD44: 30 | AE44: single
A45: 44 | B45: 2026 | C45: 2 | D45: 182 | E45: 1 | F45: 99MD834 | G45: 7 | H45: single | I45: 0 | J45: 1 | K45: 214.28571 | L45: 1500 | AA45: 31 | AB45: 3 | AC45: 99BT339 | AD45: 30 | AE45: single
A46: 45 | B46: 2026 | C46: 2 | D46: 182 | E46: 1 | F46: 77VS178 | G46: 4 | H46: single | I46: 0 | J46: 2 | K46: 196.42857 | L46: 785.71429 | AA46: 31 | AB46: 3 | AC46: 77ET143 | AD46: 30 | AE46: single
A47: 46 | B47: 2025 | C47: 2 | D47: 30 | E47: 2 | F47: 99AS882 | G47: 30 | H47: single | I47: 0 | J47: 1 | K47: 183.33333 | L47: 5500 | AA47: 31 | AB47: 3 | AC47: 50DK730 | AD47: 30 | AE47: single
A48: 47 | B48: 2025 | C48: 2 | D48: 30 | E48: 2 | F48: 99JE233 | G48: 30 | H48: single | I48: 0 | J48: 2 | K48: 183.33333 | L48: 5500 | AA48: 31 | AB48: 3 | AC48: 99MN472 | AD48: 30 | AE48: single
A49: 48 | B49: 2025 | C49: 3 | D49: 31 | E49: 2 | F49: 99LT168 | G49: 21 | H49: single | I49: 0 | J49: 1 | K49: 73.33 | L49: 1539.93 | AA49: 31 | AB49: 3 | AC49: 52BK688 | AD49: 5 | AE49: single
A50: 49 | B50: 2025 | C50: 3 | D50: 31 | E50: 2 | F50: 90OV187 | G50: 30 | H50: single | I50: 0 | J50: 5 | K50: 73.33 | L50: 2199.9 | AA50: 31 | AB50: 3 | AC50: 77RN868 | AD50: 31 | AE50: single
A51: 50 | B51: 2025 | C51: 3 | D51: 31 | E51: 2 | F51: 99HZ395 | G51: 25 | H51: single | I51: 0 | J51: 3 | K51: 65 | L51: 1625 | AA51: 31 | AB51: 3 | AC51: 99LM412 | AD51: 30 | AE51: single
A52: 51 | B52: 2025 | C52: 3 | D52: 31 | E52: 2 | F52: 90ZP408 | G52: 24 | H52: single | I52: 0 | J52: 11 | K52: 55.36 | L52: 1328.64 | AA52: 31 | AB52: 3 | AC52: 50BD165 | AD52: 25 | AE52: single
A53: 52 | B53: 2025 | C53: 3 | D53: 31 | E53: 2 | F53: 66CC029 | G53: 25 | H53: single | I53: 0 | J53: 15 | K53: 55.36 | L53: 1384 | AA53: 31 | AB53: 3 | AC53: 77QE133 | AD53: 7 | AE53: single
... A57: 56 | B57: 2025 | C57: 3 | D57: 31 | E57: 2 | F57: 55CB633 | G57: 25 | H57: single | I57: 0 | J57: 57 | K57: 55.36 | L57: 1384 | AA57: 31 | AB57: 4 | AC57: 77QK725 | AD57: 15 | AE57: single
A58: 57 | B58: 2025 | C58: 3 | D58: 31 | E58: 2 | F58: 77GM723 | G58: 28 | H58: single | I58: 0 | J58: 61 | K58: 55.36 | L58: 1550.08 | AA58: 31 | AB58: 4 | AC58: 77QK725 | AE58: single
A59: 58 | B59: 2025 | C59: 3 | D59: 31 | E59: 2 | F59: 99DX531 | G59: 27 | H59: single | I59: 0 | J59: 97 | K59: 55.36 | L59: 1494.72 | AA59: 31 | AB59: 4 | AC59: 77AT386 | AD59: 31 | AE59: single
A60: 59 | B60: 2025 | C60: 3 | D60: 31 | E60: 2 | F60: 15BZ942 | G60: 29 | H60: single | I60: 0 | J60: 35 | K60: 55.36 | L60: 1605.44 | AA60: 31 | AB60: 4 | AC60: 90SL686 | AD60: 31 | AE60: single
A61: 60 | B61: 2025 | C61: 3 | D61: 31 | E61: 2 | F61: 99BT339 | G61: 26 | H61: single | I61: 0 | J61: 93 | K61: 55.36 | L61: 1439.36 | AA61: 31 | AB61: 4 | AC61: 55CB633 | AD61: 29 | AE61: single
A62: 61 | B62: 2025 | C62: 3 | D62: 31 | E62: 2 | F62: 77ET143 | G62: 25 | H62: single | I62: 0 | J62: 59 | K62: 55.36 | L62: 1384 | AA62: 31 | AB62: 4 | AC62: 99BT339 | AD62: 39 | AE62: single
A63: 62 | B63: 2025 | C63: 3 | D63: 31 | E63: 2 | F63: 50DK730 | G63: 28 | H63: single | I63: 0 | J63: 47 | K63: 55.36 | L63: 1550.08 | AA63: 31 | AB63: 4 | AC63: 77ET143 | AD63: 30 | AE63: single
A64: 63 | B64: 2025 | C64: 3 | D64: 31 | E64: 2 | F64: 99MN472 | G64: 29 | H64: single | I64: 0 | J64: 108 | K64: 55.36 | L64: 1605.44 | AA64: 31 | AB64: 4 | AC64: 50DK730 | AD64: 31 | AE64: single
A65: 64 | B65: 2025 | C65: 3 | D65: 31 | E65: 2 | F65: 52BK688 | G65: 25 | H65: single | I65: 0 | J65: 51 | K65: 55.36 | L65: 1384 | AA65: 31 | AB65: 4 | AC65: 99MN472 | AD65: 31 | AE65: single
A66: 65 | B66: 2025 | C66: 3 | D66: 31 | E66: 2 | F66: 10RN527 | G66: 18 | H66: single | I66: 0 | J66: 31 | K66: 55.36 | L66: 996.48 | AA66: 31 | AB66: 4 | AC66: 99LM412 | AD66: 31 | AE66: single
A67: 66 | B67: 2025 | C67: 3 | D67: 31 | E67: 2 | F67: 77RN868 | G67: 10 | H67: single | I67: 0 | J67: 71 | K67: 73.33 | L67: 733.3 | AA67: 31 | AB67: 4 | AC67: 50BD165 | AD67: 31 | AE67: single
A68: 67 | B68: 2025 | C68: 3 | D68: 31 | E68: 2 | F68: 99LM412 | G68: 4 | H68: single | I68: 0 | J68: 116 | K68: 55.357143 | L68: 221.42857 | AA68: 31 | AB68: 4 | AC68: 77QE133 | AD68: 28 | AE68: single
A69: 68 | B69: 2025 | C69: 3 | D69: 31 | E69: 2 | F69: 99TV366 | G69: 14 | H69: single | I69: 0 | J69: 112 | K69: 55.36 | L69: 775.04 | AA69: 31 | AB69: 4 | AC69: 90VS316 | AD69: 30 | AE69: single
A70: 69 | B70: 2025 | C70: 3 | D70: 31 | E70: 2 | F70: 90OV187 | G70: 49 | H70: hour | I70: 0 | J70: 6 | K70: 7.333 | L70: 359.317 | AA70: 31 | AB70: 4 | AC70: 99EM163 | AD70: 4 | AE70: single
... A80: 79 | B80: 2025 | C80: 3 | D80: 31 | E80: 2 | F80: 99LM412 | G80: 5 | H80: hour | I80: 0 | J80: 115 | K80: 5.5357143 | L80: 27.678571 | AA80: 31 | AB80: 5 | AC80: 77QK725 | AD80: 15 | AE80: single
A81: 80 | B81: 2025 | C81: 3 | D81: 31 | E81: 2 | F81: 99TV366 | G81: 21 | H81: hour | I81: 0 | J81: 111 | K81: 5.536 | L81: 116.256 | AA81: 31 | AB81: 5 | AC81: 77QK725 | AE81: single
A82: 81 | B82: 2025 | C82: 6 | D82: 46 | E82: 2 | F82: 110FY523 | G82: 27 | H82: single | I82: 0 | J82: 1 | K82: 214.28571 | L82: 5785.7143 | AA82: 31 | AB82: 5 | AC82: 77UR032 | AD82: 27 | AE82: single
A83: 82 | B83: 2025 | C83: 6 | D83: 46 | E83: 2 | F83: 10AD801 | G83: 27 | H83: single | I83: 0 | J83: 4 | K83: 446.42857 | L83: 12053.571 | AA83: 31 | AB83: 5 | AC83: 90PY548 | AD83: 27 | AE83: single
A84: 83 | B84: 2025 | C84: 7 | D84: 50 | E84: 2 | F84: 61AB256 | G84: 29 | H84: single | I84: 0 | J84: 1 | K84: 357.14286 | L84: 10357.143 | AA84: 31 | AB84: 5 | AC84: 90SL686 | AD84: 29 | AE84: single
A85: 84 | B85: 2025 | C85: 8 | D85: 51 | E85: 2 | F85: 10BA857 | G85: 13 | H85: single | I85: 0 | J85: 3 | K85: 235.71 | L85: 3064.23 | AA85: 31 | AB85: 5 | AC85: 90VS316 | AD85: 27 | AE85: single
A86: 85 | B86: 2025 | C86: 8 | D86: 51 | E86: 2 | F86: 10BA857 | G86: 30 | H86: hour | I86: 0 | J86: 4 | K86: 26.071 | L86: 782.13 | AA86: 31 | AB86: 5 | AC86: 99EM163 | AD86: 27 | AE86: single
A87: 86 | B87: 2025 | C87: 9 | D87: 51 | E87: 2 | F87: 10BA857 | G87: 25 | H87: single | I87: 0 | J87: 3 | K87: 235.71 | L87: 5892.75 | AA87: 31 | AB87: 5 | AC87: 99HZ395 | AD87: 30 | AE87: single
A88: 87 | B88: 2025 | C88: 9 | D88: 51 | E88: 2 | F88: 10BA857 | G88: 10 | H88: hour | I88: 0 | J88: 4 | K88: 26.071 | L88: 260.71 | AA88: 31 | AB88: 5 | AC88: 99LM412 | AD88: 29 | AE88: single
A89: 88 | B89: 2025 | C89: 5 | D89: 52 | E89: 2 | F89: 10AC750 | G89: 30 | H89: single | I89: 0 | J89: 1 | K89: 375 | L89: 11250 | AA89: 31 | AB89: 5 | AC89: 99MN472 | AD89: 29 | AE89: single
A90: 89 | B90: 2025 | C90: 5 | D90: 52 | E90: 2 | F90: 10BC326 | G90: 11 | H90: single | I90: 0 | J90: 3 | K90: 357.14 | L90: 3928.54 | AA90: 31 | AB90: 6 | AC90: 01CC689 | AD90: 31 | AE90: single
A91: 90 | B91: 2025 | C91: 6 | D91: 65 | E91: 2 | F91: 01BA176 | G91: 23.5 | H91: single | I91: 0 | J91: 1 | K91: 196.42857 | L91: 4616.0714 | AA91: 31 | AB91: 6 | AC91: 50BD165 | AD91: 30 | AE91: single
A92: 91 | B92: 2025 | C92: 6 | D92: 65 | E92: 2 | F92: 10BD252 | G92: 27 | H92: single | I92: 0 | J92: 2 | K92: 160.71 | L92: 4339.17 | AA92: 31 | AB92: 6 | AC92: 50BN724 | AD92: 16 | AE92: single
A93: 92 | B93: 2025 | C93: 7 | D93: 85 | E93: 2 | F93: 77SN951 | G93: 29 | H93: single | I93: 0 | J93: 1 | K93: 446.43 | L93: 12946.47 | AA93: 31 | AB93: 6 | AC93: 50DK730 | AD93: 31 | AE93: single
... A829: 828 | B829: 2026 | C829: 3 | D829: 31 | E829: 14 | F829: 90GG153 | G829: 15 | H829: hour | I829: 0 | J829: 203 | K829: 16.071429 | L829: 241.07143 | AA829: 141 | AB829: 5 | AC829: 10V288 | AD829: 29 | AE829: hour
A830: 829 | B830: 2024 | C830: 12 | D830: 11 | E830: 1 | F830: 0 | G830: 1 | H830: 0 | I830: 0 | J830: 1 | K830: 5500 | L830: 5500 | AA830: 182 | AB830: 2 | AC830: 77VS178 | AD830: 3 | AE830: hour
A831: 830 | B831: 2024 | C831: 12 | D831: 11 | E831: 1 | F831: 0 | G831: 8 | H831: 0 | I831: 0 | J831: 2 | K831: 200 | L831: 1600 | AA831: 85 | AB831: 10 | AC831: 77SN951 | AD831: 7 | AE831: hour
A832: 831 | B832: 2024 | C832: 12 | D832: 11 | E832: 1 | F832: 0 | G832: 12 | H832: 0 | I832: 0 | J832: 3 | K832: 100 | L832: 1200 | AA832: 31 | AB832: 2 | AC832: 99LT168 | AD832: 5286 | AE832: dist
A833: 832 | B833: 2025 | C833: 2 | D833: 11 | E833: 2 | F833: 0 | G833: 1 | H833: 0 | I833: 0 | J833: 1 | K833: 5500 | L833: 5500 | AA833: 31 | AB833: 2 | AC833: 90OV187 | AD833: 5941 | AE833: dist
A834: 833 | B834: 2025 | C834: 2 | D834: 11 | E834: 2 | F834: 0 | G834: 3.1 | H834: 0 | I834: 0 | J834: 2 | K834: 200 | L834: 620 | AA834: 31 | AB834: 2 | AC834: 99HZ395 | AD834: 4300 | AE834: dist
A835: 834 | B835: 2025 | C835: 2 | D835: 11 | E835: 2 | F835: 0 | G835: 18 | H835: 0 | I835: 0 | J835: 3 | K835: 100 | L835: 1800 | AA835: 31 | AB835: 2 | AC835: 90ZP408 | AD835: 2288 | AE835: dist
A836: 835 | B836: 2025 | C836: 2 | D836: 11 | E836: 2 | F836: 0 | G836: 1 | H836: 0 | I836: 0 | J836: 4 | K836: 300 | L836: 300 | AA836: 31 | AB836: 2 | AC836: 66CC029 | AD836: 949 | AE836: dist
A837: 836 | B837: 2025 | C837: 2 | D837: 11 | E837: 2 | F837: 0 | G837: 1 | H837: 0 | I837: 0 | J837: 5 | K837: 540 | L837: 540 | AA837: 31 | AB837: 2 | AC837: 90SL686 | AD837: 7084 | AE837: dist
A838: 837 | B838: 2025 | C838: 3 | D838: 11 | E838: 3 | F838: 0 | G838: 1 | H838: 0 | I838: 0 | J838: 1 | K838: 5500 | L838: 5500 | AA838: 31 | AB838: 2 | AC838: 55CB633 | AD838: 2400 | AE838: dist
A839: 838 | B839: 2025 | C839: 3 | D839: 11 | E839: 3 | F839: 0 | G839: 13 | H839: 0 | I839: 0 | J839: 2 | K839: 200 | L839: 2600 | AA839: 31 | AB839: 2 | AC839: 77GM723 | AD839: 7372 | AE839: dist
A840: 839 | B840: 2025 | C840: 3 | D840: 11 | E840: 3 | F840: 0 | G840: 14 | H840: 0 | I840: 0 | J840: 3 | K840: 100 | L840: 1400 | AA840: 31 | AB840: 2 | AC840: 99DX531 | AD840: 3304 | AE840: dist
A841: 840 | B841: 2025 | C841: 3 | D841: 11 | E841: 3 | F841: 0 | G841: 1 | H841: 0 | I841: 0 | J841: 6 | K841: 1000 | L841: 1000 | AA841: 31 | AB841: 2 | AC841: 15BZ942 | AD841: 3934 | AE841: dist
... A921: 920 | B921: 2025 | C921: 5 | D921: 30 | E921: 5 | F921: 0 | G921: 1 | H921: 0 | I921: 0 | J921: 4 | K921: 5500 | L921: 5500 | AA921: 31 | AB921: 7 | AC921: 55CB633 | AD921: 2051 | AE921: dist
A922: 921 | B922: 2025 | C922: 6 | D922: 30 | E922: 6 | F922: 0 | G922: 1 | H922: 0 | I922: 0 | J922: 4 | K922: 5500 | L922: 5500 | AA922: 31 | AB922: 7 | AC922: 77AT386 | AE922: dist
A923: 922 | B923: 2025 | C923: 7 | D923: 30 | E923: 7 | F923: 0 | G923: 1 | H923: 0 | I923: 0 | J923: 4 | K923: 5500 | L923: 5500 | AA923: 31 | AB923: 7 | AC923: 77GR998 | AD923: 3530 | AE923: dist
A924: 923 | B924: 2025 | C924: 8 | D924: 30 | E924: 8 | F924: 0 | G924: 1 | H924: 0 | I924: 0 | J924: 4 | K924: 5500 | L924: 5500 | AA924: 31 | AB924: 7 | AC924: 77QE133 | AD924: 5845 | AE924: dist
A925: 924 | B925: 2025 | C925: 9 | D925: 30 | E925: 9 | F925: 0 | G925: 1 | H925: 0 | I925: 0 | J925: 4 | K925: 5500 | L925: 5500 | AA925: 31 | AB925: 7 | AC925: 77TG971 | AD925: 1485 | AE925: dist
A926: 925 | B926: 2025 | C926: 10 | D926: 30 | E926: 10 | F926: 0 | G926: 1 | H926: 0 | I926: 0 | J926: 4 | K926: 5500 | L926: 5500 | AA926: 31 | AB926: 7 | AC926: 77UR032 | AD926: 2293 | AE926: dist
A927: 926 | B927: 2025 | C927: 11 | D927: 30 | E927: 11 | F927: 0 | G927: 1 | H927: 0 | I927: 0 | J927: 4 | K927: 5500 | L927: 5500 | AA927: 31 | AB927: 7 | AC927: 90LS143 | AD927: 2327 | AE927: dist
A928: 927 | B928: 2025 | C928: 2 | D928: 31 | E928: 1 | F928: 0 | G928: 2956 | H928: 0 | I928: 0 | J928: M-1 | K928: 1 | L928: 2956 | AA928: 31 | AB928: 7 | AC928: 90OE402 | AD928: 1719 | AE928: dist
A929: 928 | B929: 2025 | C929: 2 | D929: 31 | E929: 1 | F929: 0 | G929: 2956 | H929: 0 | I929: 0 | J929: R-1 | K929: -1 | L929: -2956 | AA929: 31 | AB929: 7 | AC929: 90SL686 | AD929: 9102 | AE929: dist
A930: 929 | B930: 2025 | C930: 3 | D930: 31 | E930: 2 | F930: 0 | G930: 11129.91 | H930: 0 | I930: 0 | J930: M-1 | K930: 1 | L930: 11129.91 | AA930: 31 | AB930: 7 | AC930: 90VS316 | AD930: 2571 | AE930: dist
A931: 930 | B931: 2025 | C931: 3 | D931: 31 | E931: 2 | F931: 0 | G931: 9319 | H931: 0 | I931: 0 | J931: R-1 | K931: -1 | L931: -9319 | AA931: 31 | AB931: 7 | AC931: 99BT339 | AD931: 4429 | AE931: dist
A932: 931 | B932: 2025 | C932: 3 | D932: 31 | E932: 2 | F932: 0 | G932: 100 | H932: 0 | I932: 0 | J932: R-2 | K932: -1 | L932: -100 | AA932: 31 | AB932: 7 | AC932: 99EM163 | AD932: 1926 | AE932: dist
A933: 932 | B933: 2025 | C933: 4 | D933: 31 | E933: 3 | F933: 0 | G933: 7666.74 | H933: 0 | I933: 0 | J933: M-1 | K933: 1 | L933: 7666.74 | AA933: 31 | AB933: 7 | AC933: 99HZ395 | AD933: 5269 | AE933: dist
A934: 933 | B934: 2025 | C934: 4 | D934: 31 | E934: 3 | F934: 0 | G934: 6009 | H934: 0 | I934: 0 | J934: R-1 | K934: -1 | L934: -6009 | AA934: 31 | AB934: 7 | AC934: 99KL663 | AD934: 2375 | AE934: dist
A935: 934 | B935: 2025 | C935: 5 | D935: 31 | E935: 4 | F935: 0 | G935: 7701.45 | H935: 0 | I935: 0 | J935: M-1 | K935: 1 | L935: 7701.45 | AA935: 31 | AB935: 7 | AC935: 99LM412 | AD935: 522 | AE935: dist
A936: 935 | B936: 2025 | C936: 5 | D936: 31 | E936: 4 | F936: 0 | G936: 6357 | H936: 0 | I936: 0 | J936: R-1 | K936: -1 | L936: -6357 | AA936: 31 | AB936: 7 | AC936: 99MN472 | AD936: 5842 | AE936: dist
A937: 936 | B937: 2025 | C937: 6 | D937: 31 | E937: 5 | F937: 0 | G937: 8670.24 | H937: 0 | I937: 0 | J937: M-1 | K937: 1 | L937: 8670.24 | AA937: 31 | AB937: 8 | AC937: 10RN527 | AD937: 3670 | AE937: dist
...

Sheet log_positions

Sheet old_ipc_dates
A1: Contr-Ipc | B1: Start | C1: Finish | D1: Commencement
A2: 150-1 | B2: 45989 | C2: 45991 | D2: 45989 | F2: 150-001 | G2: {=_xlfn.NUMBERVALUE(LEFT(F2:F130,3))} -> 150
A3: 141-1 | B3: 45601 | C3: 45626 | D3: 45601 | F3: 141-001 | G3: 141
A4: 121-1 | B4: 45931 | C4: 45961 | D4: 45925 | F4: 121-001 | G4: 121
A5: 121-2 | B5: 45962 | C5: 45991 | D5: 45925 | F5: 121-002 | G5: 121
A6: 110-1 | B6: 45895 | C6: 45900 | D6: 45890 | F6: 110-001 | G6: 110
A7: 110-2 | B7: 45901 | C7: 45930 | D7: 45890 | F7: 110-002 | G7: 110
A8: 110-3 | B8: 45931 | C8: 45961 | D8: 45890 | F8: 110-003 | G8: 110
A9: 110-4 | B9: 45962 | C9: 45991 | D9: 45890 | F9: 110-004 | G9: 110
A10: 107-1 | B10: 45856 | C10: 45900 | D10: 45856 | F10: 107-001 | G10: 107
A11: 107-2 | B11: 45931 | C11: 45961 | D11: 45856 | F11: 107-002 | G11: 107
A12: 103-1 | B12: 45880 | C12: 45900 | D12: 45880 | F12: 103-001 | G12: 103
A13: 102-1 | B13: 45892 | C13: 45900 | D13: 45892 | F13: 102-001 | G13: 102
A14: 102-2 | B14: 45901 | C14: 45930 | D14: 45892 | F14: 102-002 | G14: 102
... A130: 11-9 | B130: 45901 | C130: 45930 | D130: 45646 | F130: 011-009 | G130: 11
